Workbook

Sheet Ceras
A1: ID_Cera | B1: Nombre de cera | C1: Proveedor | D1: Presentación / paquete | E1: Gramos paquete | F1: Precio paquete | G1: Costo por gramo
A2: SOYA | B2: Cera de soya | C2: Proveedor Banderas | D2: Bolsa 1000g | E2: 1000 | F2: 28000 | G2: =IFERROR(F2/E2,0) -> 28
A3: PARAFINA | B3: Parafina | C3: Proveedor Banderas | D3: Bolsa 1000g | E3: 1000 | F3: 13500 | G3: =IFERROR(F3/E3,0) -> 13.5
A4: CERA_COCO | B4: Cera de coco | C4: Proveedor ejemplo | D4: Bolsa 1000g | E4: 1000 | F4: 35000 | G4: =IFERROR(F4/E4,0) -> 35
A5: CERA_MOLDE | B5: Cera de molde | C5: Proveedor ejemplo | D5: Bolsa 1000g | E5: 1000 | F5: 18000 | G5: =IFERROR(F5/E5,0) -> 18
A6: CERA_BPF | B6: Bajo punto de fusión masajes | C6: 360 | D6: Bolsa 1000g | E6: 1000 | F6: 28000 | G6: =IFERROR(F6/E6,0) -> 28
G7: =IFERROR(F7/E7,0) -> 0
G8: =IFERROR(F8/E8,0) -> 0
G9: =IFERROR(F9/E9,0) -> 0
G10: =IFERROR(F10/E10,0) -> 0
G11: =IFERROR(F11/E11,0) -> 0
G12: =IFERROR(F12/E12,0) -> 0
G13: =IFERROR(F13/E13,0) -> 0
G14: =IFERROR(F14/E14,0) -> 0
G15: =IFERROR(F15/E15,0) -> 0
G16: =IFERROR(F16/E16,0) -> 0
G17: =IFERROR(F17/E17,0) -> 0
G18: =IFERROR(F18/E18,0) -> 0
... G500: =IFERROR(F500/E500,0) -> 0

Sheet Pabilos
A1: ID_Pabilo | B1: Calibre / nombre | C1: Proveedor | D1: Presentación / paquete | E1: Longitud paquete | F1: Unidad longitud | G1: Precio paquete | H1: Costo por cm | I1: Notas
A2: PABILO2-4 | B2: Pabilo calibre 2-4 | C2: Proveedor La Rueca | D2: Rollo 10m | E2: 10 | F2: m | G2: 15000 | H2: =IFERROR(IF(F2="m",G2/(E2*100),IF(F2="cm",G2/E2,0)),0) -> 15 | I2: La fórmula convierte metros a centímetros.
A3: PABILO4-6 | B3: Pabilo calibre 4-6 | C3: Proveedor La Rueca | D3: Rollo 10m | E3: 10 | F3: m | G3: 18000 | H3: =IFERROR(IF(F3="m",G3/(E3*100),IF(F3="cm",G3/E3,0)),0) -> 18 | I3: La fórmula convierte metros a centímetros.
A4: PABILO6-8 | B4: Pabilo calibre 6-8 | C4: Proveedor La Rueca | D4: Rollo 10m | E4: 10 | F4: m | G4: 20000 | H4: =IFERROR(IF(F4="m",G4/(E4*100),IF(F4="cm",G4/E4,0)),0) -> 20 | I4: La fórmula convierte metros a centímetros.
H5: =IFERROR(IF(F5="m",G5/(E5*100),IF(F5="cm",G5/E5,0)),0) -> 0
H6: =IFERROR(IF(F6="m",G6/(E6*100),IF(F6="cm",G6/E6,0)),0) -> 0
H7: =IFERROR(IF(F7="m",G7/(E7*100),IF(F7="cm",G7/E7,0)),0) -> 0
H8: =IFERROR(IF(F8="m",G8/(E8*100),IF(F8="cm",G8/E8,0)),0) -> 0
H9: =IFERROR(IF(F9="m",G9/(E9*100),IF(F9="cm",G9/E9,0)),0) -> 0
H10: =IFERROR(IF(F10="m",G10/(E10*100),IF(F10="cm",G10/E10,0)),0) -> 0
H11: =IFERROR(IF(F11="m",G11/(E11*100),IF(F11="cm",G11/E11,0)),0) -> 0
H12: =IFERROR(IF(F12="m",G12/(E12*100),IF(F12="cm",G12/E12,0)),0) -> 0
H13: =IFERROR(IF(F13="m",G13/(E13*100),IF(F13="cm",G13/E13,0)),0) -> 0
H14: =IFERROR(IF(F14="m",G14/(E14*100),IF(F14="cm",G14/E14,0)),0) -> 0
H15: =IFERROR(IF(F15="m",G15/(E15*100),IF(F15="cm",G15/E15,0)),0) -> 0
H16: =IFERROR(IF(F16="m",G16/(E16*100),IF(F16="cm",G16/E16,0)),0) -> 0
... H500: =IFERROR(IF(F500="m",G500/(E500*100),IF(F500="cm",G500/E500,0)),0) -> 0

Sheet Esencias
A1: ID_Esencia | B1: Nombre esencia | C1: Proveedor | D1: Presentación / paquete | E1: Gramos paquete | F1: Precio paquete | G1: Costo por gramo | H1: Notas
A2: ES_MARACUYA | B2: Esencia maracuyá | C2: Proveedor ejemplo | D2: Frasco 40g | E2: 40 | F2: 10000 | G2: =IFERROR(F2/E2,0) -> 250 | H2: El costo se calcula por gramos.
A3: ES_VAINILLA | B3: Esencia vainilla | C3: Proveedor ejemplo | D3: Frasco 100g | E3: 100 | F3: 16000 | G3: =IFERROR(F3/E3,0) -> 160 | H3: Ejemplo adicional.
A4: ES_CHOCOLATE | B4: Esencia Chocolate | C4: Proveedor La Rueca | D4: Frasco 20ml | E4: 20 | F4: 10000 | G4: =IFERROR(F4/E4,0) -> 500 | H4: NEGOCIO GALERIAS
A5: ES_CANELA | B5: Esencia Canela | C5: inventario inicial | D5: Frasco 25 ml | E5: 25 | F5: 6000 | G5: =IFERROR(F5/E5,0) -> 240 | H5: FRANGANCIAS DE ANGGIE
A6: ES_BEDOYA | B6: Escencia de Carlos Bedoya | C6: Proveedor de Leidy Ramos | D6: Frasco 1 onza | E6: 28.4 | F6: 4000 | G6: =IFERROR(F6/E6,0) -> 140.84507 | H6: PROVEEDOR LEIDY RAMOS
A7: ES_CHO | B7: fragancia Tarro | C7: Azahaar | D7: Tarro 1000 | E7: 1000 | F7: 80000 | G7: =IFERROR(F7/E7,0) -> 80 | H7: NEGOCIO NORTE DE BOGOTA
A8: ES_FRU | B8: fragancia Tarro | C8: Azahaar | D8: Tarro 1000 | E8: 1000 | F8: 78000 | G8: =IFERROR(F8/E8,0) -> 78
A9: ES_MAR | B9: fragancia Tarro | C9: Azahaar | D9: Tarro 1000 | E9: 1000 | F9: 80000 | G9: =IFERROR(F9/E9,0) -> 80
G10: =IFERROR(F10/E10,0) -> 0
G11: =IFERROR(F11/E11,0) -> 0
G12: =IFERROR(F12/E12,0) -> 0
G13: =IFERROR(F13/E13,0) -> 0
G14: =IFERROR(F14/E14,0) -> 0
G15: =IFERROR(F15/E15,0) -> 0
G16: =IFERROR(F16/E16,0) -> 0
G17: =IFERROR(F17/E17,0) -> 0
G18: =IFERROR(F18/E18,0) -> 0
G19: =IFERROR(F19/E19,0) -> 0
G20: =IFERROR(F20/E20,0) -> 0
G21: =IFERROR(F21/E21,0) -> 0
... G501: =IFERROR(F501/E501,0) -> 0

Sheet Colores
A1: ID_Color | B1: Nombre color | C1: Proveedor | D1: Presentación / paquete | E1: Cantidad paquete | F1: Unidad base | G1: Precio paquete | H1: Costo unitario | I1: Notas
A2: COLOR_AZUL | B2: Colorante azul 2 crayola2 | C2: Inventario inicial | D2: Frasco 65g | E2: 65 | F2: g | G2: 6000 | H2: =IFERROR(G2/E2,0) -> 92.307692 | I2: Ejemplo: una dosis de color para una vela.
A3: COLOR_VERDE | B3: Colorante verde 2 crayolas | C3: Inventario inicial | D3: Frasco 65g | E3: 65 | F3: g | G3: 6000 | H3: =IFERROR(G3/E3,0) -> 92.307692 | I3: Si se calcula por gramo, en Velas la cantidad debe escribirse en gramos.
A4: COLOR_CAFE | B4: Colorante café 2 crayones | C4: Inventario inicial | D4: Frasco 65g | E4: 65 | F4: g | G4: 6000 | H4: =IFERROR(G4/E4,0) -> 92.307692
A5: COLOR_ROJO | B5: Colorante Rojo 2 crayones | C5: Inventario inicial | D5: Frasco 65g | E5: 65 | F5: g | G5: 6000 | H5: =IFERROR(G5/E5,0) -> 92.307692
H6: =IFERROR(G6/E6,0) -> 0
H7: =IFERROR(G7/E7,0) -> 0
H8: =IFERROR(G8/E8,0) -> 0
H9: =IFERROR(G9/E9,0) -> 0
H10: =IFERROR(G10/E10,0) -> 0
H11: =IFERROR(G11/E11,0) -> 0
H12: =IFERROR(G12/E12,0) -> 0
H13: =IFERROR(G13/E13,0) -> 0
H14: =IFERROR(G14/E14,0) -> 0
H15: =IFERROR(G15/E15,0) -> 0
H16: =IFERROR(G16/E16,0) -> 0
H17: =IFERROR(G17/E17,0) -> 0
... H500: =IFERROR(G500/E500,0) -> 0

Sheet Materiales
A1: ID_Material | B1: Categoría | C1: Nombre material | D1: Unidad base | E1: Costo unitario | F1: Proveedor | G1: Notas
A2: PINTURA_VERDE | B2: Bisutería | C2: Pintura decorativa verde | D2: unidad | E2: 200 | F2: Proveedor ejemplo | G2: Para decoración
A3: STICKER_ARCANA | B3: Papelería | C3: Sticker ARCANA | D3: unidad | E3: 150 | F3: Proveedor ejemplo | G3: Para empaque o presentación
A4: ENV_YESO | B4: Insumo | C4: Envase YESO 120 ml | D4: unidad | E4: 4000 | F4: Proveedor ejemplo | G4: Envase principal de la vela
A5: REC_YESO | B5: Insumo | C5: Envase YESO 120 ml | D5: unidad | E5: 3000 | F5: Proveedor ejemplo | G5: Envase principal de la vela
A6: TAPA_YESO | B6: Insumo | C6: tapa yeso | D6: unidad | E6: 1000 | F6: Proveedor ejemplo | G6: Envase principal de la vela
A7: CAJA_KRAFT | B7: Empaque | C7: Caja kraft pequeña | D7: unidad | E7: 900 | F7: Proveedor ejemplo | G7: Puede agregarse en Insumos como CAJA_KRAFT:1
A8: PINCHO | B8: Empaque | C8: Pincho para flores | D8: unidad | E8: 30 | F8: El sol | G8: Para las margaritas
A9: PAPEL_AZUCAR | B9: Empaque | C9: Papel para envolver | D9: unidad | E9: 300 | F9: Papelería x | G9: Para las margaritas
A10: ACEITE | B10: Insumo | C10: Para que brille | D10: unidad | E10: 100 | F10: jhonson | G10: Para que brille, par superficies geométricas
A11: ENV2_YESO | B11: Insumo | C11: ENVase YESO 90ml | D11: unidad | E11: 2000 | F11: Inventario inicial | G11: Envase de yeso
A12: REPOLLO | B12: Otro | D12: unidad | E12: =Velas!X12 -> 722.67497
A13: PEONIA S | B13: Otro | D13: unidad | E13: =Velas!X14 -> 554.75244
A14: PEONIA M | B14: Otro | D14: unidad | E14: =Velas!X15 -> 1138.2584
A15: CINTA | B15: Papelería | C15: CINTA BLANCA | D15: cm | E15: 17
A16: FLORES | B16: Insumo | C16: RAMO DE FLORES SECAS | D16: unidad | E16: 500
A17: CINTA1 | B17: Papelería | C17: Cinta blanca gruesa | D17: cm | E17: 7
A18: FOSTO | B18: Papelería | C18: Fosforo | D18: unidad | E18: 20
A19: TUL | B19: Papelería | C19: TUL empaque margaritas | D19: unidad | E19: 180
A20: STICKER | B20: Papelería | C20: STICKER | D20: unidad | E20: 120
A21: RECIPIENTE | B21: Envase | C21: RECINA TRANSPARENTE | D21: unidad | E21: 3500
A22: ESCARCHA | B22: Insumo | C22: ESCARCHA | D22: unidad | E22: 100
A23: RECIPIENTE_VIDRIO | B23: Envase | C23: VELA BELLA | D23: unidad | E23: 3600
A24: ROSA M | B24: Otro | C24: VELA | D24: unidad | E24: =Velas!X23 -> 1895.1176
A25: CAJALARGA | B25: Empaque | C25: Caja larga | D25: unidad | E25: 5000
A26: PAPELSEDA | B26: Papelería | C26: papel seda | D26: unidad | E26: 500
A27: CINTAN | B27: Papelería | C27: Cinta blanca gruesa | D27: cm | E27: 2
A28: CHAPA | B28: Envase | C28: CHAPA | D28: unidad | E28: 83
A29: ENVASE_PEQUEÑO | B29: Envase | C29: Envase pequeño | D29: Unidad | E29: 2200

Sheet Ventas
A1: Descripcion | B1: Costo | C1: Precio sugerido | D1: Precio Actual | E1: Utilidad | F1: Antes | G1: 46215
A2: =Velas!A2 -> Vela Margarita en yeso sin tapa | B2: =Velas!X2 -> 7645.3077 | C2: =Velas!$AB2 -> 22935.923 | D2: =Velas!AC2 -> 22000 | E2: =Velas!$AE2 -> 14354.692 | F2: 0 | G2: 0
A3: =Velas!A3 -> Vela Margarita en yeso con tapa | B3: =Velas!X3 -> 8645.3077 | C3: =Velas!$AB3 -> 25935.923 | D3: =Velas!AC3 -> 25000 | E3: =Velas!$AE3 -> 16354.692 | F3: 0 | G3: 0
A4: =Velas!A4 -> Vela Margarita sola | B4: =Velas!X4 -> 814.19502 | C4: =Velas!$AB4 -> 2442.585 | D4: =Velas!AC4 -> 2500 | E4: =Velas!$AE4 -> 1685.805 | F4: 1 | G4: 2
A5: =Velas!A5 -> Vela Margarita en papel azucar | B5: =Velas!X5 -> 1206.1668 | C5: =Velas!$AB5 -> 3618.5005 | D5: =Velas!AC5 -> 3500 | E5: =Velas!$AE5 -> 2293.8332 | F5: 0 | G5: 0
A6: =Velas!A6 -> Vela Margarita en TUL | B6: =Velas!X6 -> 1481.1668 | C6: =Velas!$AB6 -> 4443.5005 | D6: =Velas!AC6 -> 4000 | E6: =Velas!$AE6 -> 2518.8332 | F6: 0 | G6: 1
A7: =Velas!A7 -> Velon corto con cara de rosas mediano | B7: =Velas!X7 -> 1608.4415 | C7: =Velas!$AB7 -> 4825.3245 | D7: =Velas!AC7 -> 4500 | E7: =Velas!$AE7 -> 2891.5585 | F7: 0 | G7: 0
A8: =Velas!A8 -> Vela bubble candle sola | B8: =Velas!X8 -> 4701.3077 | C8: =Velas!$AB8 -> 14103.923 | D8: =Velas!AC8 -> 14000 | E8: =Velas!$AE8 -> 9298.6923 | F8: 0 | G8: 1
A9: =Velas!A9 -> Vela ramo de tulipanes | B9: =Velas!X9 -> 3046.6528 | C9: =Velas!$AB9 -> 9139.9583 | D9: =Velas!AC9 -> 12000 | E9: =Velas!$AE9 -> 8953.3472 | F9: 0 | G9: 2
A10: =Velas!A10 -> Vela Oso floreado | B10: =Velas!X10 -> 2132.6246 | C10: =Velas!$AB10 -> 6397.8738 | D10: =Velas!AC10 -> 10000 | E10: =Velas!$AE10 -> 7867.3754 | F10: 1 | G10: 3
A11: =Velas!A11 -> Vela Oso xs | B11: =Velas!X11 -> 657.92145 | C11: =Velas!$AB11 -> 1973.7644 | D11: =Velas!AC11 -> 4000 | E11: =Velas!$AE11 -> 3342.0785 | F11: 0 | G11: 6
A12: =Velas!A12 -> Vela Repollo | B12: =Velas!X12 -> 722.67497 | C12: =Velas!$AB12 -> 2168.0249 | D12: =Velas!AC12 -> 2000 | E12: =Velas!$AE12 -> 1277.325 | F12: 0 | G12: 0
A13: =Velas!A13 -> Vela cactus mediana | B13: =Velas!X13 -> 1336.1961 | C13: =Velas!$AB13 -> 4008.5883 | D13: =Velas!AC13 -> 4000 | E13: =Velas!$AE13 -> 2663.8039 | F13: 0 | G13: 1
... A45: =Velas!A45 -> Vela Perro | B45: =Velas!X45 -> 931.16685 | C45: =Velas!$AB45 -> 2793.5005 | D45: =Velas!AC45 -> 3000 | E45: =Velas!$AE45 -> 2068.8332 | F45: 0 | G45: 0
A46: =Velas!A46
A47: =Velas!A47
A48: =Velas!A48
A49: =Velas!A49
A50: =Velas!A50
A51: =Velas!A51
A52: =Velas!A52
A53: =Velas!A53
A54: =Velas!A54
A55: =Velas!A55
A56: =Velas!A56
A57: =Velas!A57
... A59: =Velas!A59

Sheet Velas
A1: Descripción | B1: Cera 1 | C1: % Cera 1 | D1: Cera 2 | E1: % Cera 2 | F1: Peso total cera g | G1: Costo cera | H1: Costo en energía | I1: Pabilo | J1: Centímetros pabilo | K1: Costo pabilo | L1: Esencia | M1: Gramos esencia | N1: Costo esencia | O1: Color | P1: Cantidad color | Q1: Costo color | R1: Bisutería | S1: Costo bisutería | T1: Papelería | U1: Costo papelería | V1: Insumos | W1: Costo insumos | X1: Costo total | Y1: Margen ( temporada baja = 3 ) | Z1: Precio sin mano de obra | AA1: Mano de obra | AB1: TOTAL | AC1: Precio final | AD1: Utilidad Ideal | AE1: Utilidad | AF1: relacion %
A2: Vela Margarita en yeso sin tapa | B2: CERA_MOLDE | C2: 1 | F2: 74 | G2: {=IF($A2="","",IFERROR($F2*(N($C2)*XLOOKUP($B2,Ceras!$A$2:$A$500,Ceras!$G$2:$G$500,0)+IF($D2="",0,N($E2)*XLOOKUP($D2,Ceras!$A$2:$A$500,Ceras!$G$2:$G$500,0))),"Revisar cera"))} -> 1332 | H2: =F2*1.5 -> 111 | I2: PABILO6-8 | J2: 3 | K2: {=IF($A2="","",IFERROR($J2*XLOOKUP($I2,Pabilos!$A$2:$A$500,Pabilos!$H$2:$H$500,0),"Revisar pabilo"))} -> 60 | L2: ES_MARACUYA | M2: =F2/10 -> 7.4 | N2: {=IF($A2="","",IFERROR($M2*XLOOKUP($L2,Esencias!$A$2:$A$501,Esencias!$G$2:$G$501,0),"Revisar esencia"))} -> 1850 | O2: COLOR_VERDE | P2: 1 | Q2: {=IF($A2="","",IFERROR(IF($P2="",1,$P2)*XLOOKUP($O2,Colores!$A$2:$A$500,Colores!$H$2:$H$500,0),"Revisar color"))} -> 92.307692 | S2: {=IF($A2="","",IF($R2="",0,IFERROR(VLOOKUP(LEFT(TRIM(MID(SUBSTITUTE($R2,";",REPT(" ",99)),1,99)),FIND(":",TRIM(MID(SUBSTITUTE($R2,";",REPT(" ",99)),1,99)))-1),Materiales!$A$2:$E$502,5,FALSE)*VALUE(MID(TRIM(MID(SUBSTITUTE($R2,";",REPT(" ",99)),1,99)),FIND(":",TRIM(MID(SUBSTITUTE($R2,";",REPT(" ",99)),1,99)))+1,99)),0) + IFERROR(VLOOKUP(LEFT(TRIM(MID(SUBSTITUTE($R2,";",REPT(" ",99)),100,99)),FIND(":",TRIM(MID(SUBSTITUTE($R2,";",REPT(" ",99)),100,99)))-1),Materiales!$A$2:$E$502,5,FALSE)*VALUE(MID(TRIM(MID(SUBSTITUTE($R2,";",REPT(" ",99)),100,99)),FIND(":",TRIM(MID(SUBSTITUTE($R2,";",REPT(" ",99)),100,99)))+1,99)),0) + IFERROR(VLOOKUP(LEFT(TRIM(MID(SUBSTITUTE($R2,";",REPT(" ",99)),199,99)),FIND(":",TRIM(MID(SUBSTITUTE($R2,";",REPT(" ",99)),199,99)))-1),Materiales!$A$2:$E$502,5,FALSE)*VALUE(MID(TRIM(MID(SUBSTITUTE($R2,";",REPT(" ",99)),199,99)),FIND(":",TRIM(MID(SUBSTITUTE($R2,";",REPT(" ",99)),199,99)))+1,99)),0) + IFERROR(VLOOKUP(LEFT(TRIM(MID(SUBSTITUTE($R2,";",REPT(" ",99)),298,99)),FIND(":",TRIM(MID(SUBSTITUTE($R2,";",REPT(" ",99)),298,99)))-1),Materiales!$A$2:$E$502,5,FALSE)*VALUE(MID(TRIM(MID(SUBSTITUTE($R2,";",REPT(" ",99)),298,99)),FIND(":",TRIM(MID(SUBSTITUTE($R2,";",REPT(" ",99)),298,99)))+1,99)),0) + IFERROR(VLOOKUP(LEFT(TRIM(MID(SUBSTITUTE($R2,";",REPT(" ",99)),397,99)),FIND(":",TRIM(MID(SUBSTITUTE($R2,";",REPT(" ",99)),397,99)))-1),Materiales!$A$2:$E$502,5,FALSE)*VALUE(MID(TRIM(MID(SUBSTITUTE($R2,";",REPT(" ",99)),397,99)),FIND(":",TRIM(MID(SUBSTITUTE($R2,";",REPT(" ",99)),397,99)))+1,99)),0) + IFERROR(VLOOKUP(LEFT(TRIM(MID(SUBSTITUTE($R2,";",REPT(" ",99)),496,99)),FIND(":",TRIM(MID(SUBSTITUTE($R2,";",REPT(" ",99)),496,99)))-1),Materiales!$A$2:$E$502,5,FALSE)*VALUE(MID(TRIM(MID(SUBSTITUTE($R2,";",REPT(" ",99)),496,99)),FIND(":",TRIM(MID(SUBSTITUTE($R2,";",REPT(" ",99)),496,99)))+1,99)),0) + IFERROR(VLOOKUP(LEFT(TRIM(MID(SUBSTITUTE($R2,";",REPT(" ",99)),595,99)),FIND(":",TRIM(MID(SUBSTITUTE($R2,";",REPT(" ",99)),595,99)))-1),Materiales!$A$2:$E$502,5,FALSE)*VALUE(MID(TRIM(MID(SUBSTITUTE($R2,";",REPT(" ",99)),595,99)),FIND(":",TRIM(MID(SUBSTITUTE($R2,";",REPT(" ",99)),595,99)))+1,99)),0) + IFERROR(VLOOKUP(LEFT(TRIM(MID(SUBSTITUTE($R2,";",REPT(" ",99)),694,99)),FIND(":",TRIM(MID(SUBSTITUTE($R2,";",REPT(" ",99)),694,99)))-1),Materiales!$A$2:$E$502,5,FALSE)*VALUE(MID(TRIM(MID(SUBSTITUTE($R2,";",REPT(" ",99)),694,99)),FIND(":",TRIM(MID(SUBSTITUTE($R2,";",REPT(" ",99)),694,99)))+1,99)),0) + IFERROR(VLOOKUP(LEFT(TRIM(MID(SUBSTITUTE($R2,";",REPT(" ",99)),793,99)),FIND(":",TRIM(MID(SUBSTITUTE($R2,";",REPT(" ",99)),793,99)))-1),Materiales!$A$2:$E$502,5,FALSE)*VALUE(MID(TRIM(MID(SUBSTITUTE($R2,";",REPT(" ",99)),793,99)),FIND(":",TRIM(MID(SUBSTITUTE($R2,";",REPT(" ",99)),793,99)))+1,99)),0) + IFERROR(VLOOKUP(LEFT(TRIM(MID(SUBSTITUTE($R2,";",REPT(" ",99)),892,99)),FIND(":",TRIM(MID(SUBSTITUTE($R2,";",REPT(" ",99)),892,99)))-1),Materiales!$A$2:$E$502,5,FALSE)*VALUE(MID(TRIM(MID(SUBSTITUTE($R2,";",REPT(" ",99)),892,99)),FIND(":",TRIM(MID(SUBSTITUTE($R2,";",REPT(" ",99)),892,99)))+1,99)),0)))} -> 0 | T2: PINTURA_VERDE:1 | U2: {=IF($A2="","",IF($T2="",0,IFERROR(VLOOKUP(LEFT(TRIM(MID(SUBSTITUTE($T2,";",REPT(" ",99)),1,99)),FIND(":",TRIM(MID(SUBSTITUTE($T2,";",REPT(" ",99)),1,99)))-1),Materiales!$A$2:$E$502,5,FALSE)*VALUE(MID(TRIM(MID(SUBSTITUTE($T2,";",REPT(" ",99)),1,99)),FIND(":",TRIM(MID(SUBSTITUTE($T2,";",REPT(" ",99)),1,99)))+1,99)),0) + IFERROR(VLOOKUP(LEFT(TRIM(MID(SUBSTITUTE($T2,";",REPT(" ",99)),100,99)),FIND(":",TRIM(MID(SUBSTITUTE($T2,";",REPT(" ",99)),100,99)))-1),Materiales!$A$2:$E$502,5,FALSE)*VALUE(MID(TRIM(MID(SUBSTITUTE($T2,";",REPT(" ",99)),100,99)),FIND(":",TRIM(MID(SUBSTITUTE($T2,";",REPT(" ",99)),100,99)))+1,99)),0) + IFERROR(VLOOKUP(LEFT(TRIM(MID(SUBSTITUTE($T2,";",REPT(" ",99)),199,99)),FIND(":",TRIM(MID(SUBSTITUTE($T2,";",REPT(" ",99)),199,99)))-1),Materiales!$A$2:$E$502,5,FALSE)*VALUE(MID(TRIM(MID(SUBSTITUTE($T2,";",REPT(" ",99)),199,99)),FIND(":",TRIM(MID(SUBSTITUTE($T2,";",REPT(" ",99)),199,99)))+1,99)),0) + IFERROR(VLOOKUP(LEFT(TRIM(MID(SUBSTITUTE($T2,";",REPT(" ",99)),298,99)),FIND(":",TRIM(MID(SUBSTITUTE($T2,";",REPT(" ",99)),298,99)))-1),Materiales!$A$2:$E$502,5,FALSE)*VALUE(MID(TRIM(MID(SUBSTITUTE($T2,";",REPT(" ",99)),298,99)),FIND(":",TRIM(MID(SUBSTITUTE($T2,";",REPT(" ",99)),298,99)))+1,99)),0) + IFERROR(VLOOKUP(LEFT(TRIM(MID(SUBSTITUTE($T2,";",REPT(" ",99)),397,99)),FIND(":",TRIM(MID(SUBSTITUTE($T2,";",REPT(" ",99)),397,99)))-1),Materiales!$A$2:$E$502,5,FALSE)*VALUE(MID(TRIM(MID(SUBSTITUTE($T2,";",REPT(" ",99)),397,99)),FIND(":",TRIM(MID(SUBSTITUTE($T2,";",REPT(" ",99)),397,99)))+1,99)),0) + IFERROR(VLOOKUP(LEFT(TRIM(MID(SUBSTITUTE($T2,";",REPT(" ",99)),496,99)),FIND(":",TRIM(MID(SUBSTITUTE($T2,";",REPT(" ",99)),496,99)))-1),Materiales!$A$2:$E$502,5,FALSE)*VALUE(MID(TRIM(MID(SUBSTITUTE($T2,";",REPT(" ",99)),496,99)),FIND(":",TRIM(MID(SUBSTITUTE($T2,";",REPT(" ",99)),496,99)))+1,99)),0) + IFERROR(VLOOKUP(LEFT(TRIM(MID(SUBSTITUTE($T2,";",REPT(" ",99)),595,99)),FIND(":",TRIM(MID(SUBSTITUTE($T2,";",REPT(" ",99)),595,99)))-1),Materiales!$A$2:$E$502,5,FALSE)*VALUE(MID(TRIM(MID(SUBSTITUTE($T2,";",REPT(" ",99)),595,99)),FIND(":",TRIM(MID(SUBSTITUTE($T2,";",REPT(" ",99)),595,99)))+1,99)),0) + IFERROR(VLOOKUP(LEFT(TRIM(MID(SUBSTITUTE($T2,";",REPT(" ",99)),694,99)),FIND(":",TRIM(MID(SUBSTITUTE($T2,";",REPT(" ",99)),694,99)))-1),Materiales!$A$2:$E$502,5,FALSE)*VALUE(MID(TRIM(MID(SUBSTITUTE($T2,";",REPT(" ",99)),694,99)),FIND(":",TRIM(MID(SUBSTITUTE($T2,";",REPT(" ",99)),694,99)))+1,99)),0) + IFERROR(VLOOKUP(LEFT(TRIM(MID(SUBSTITUTE($T2,";",REPT(" ",99)),793,99)),FIND(":",TRIM(MID(SUBSTITUTE($T2,";",REPT(" ",99)),793,99)))-1),Materiales!$A$2:$E$502,5,FALSE)*VALUE(MID(TRIM(MID(SUBSTITUTE($T2,";",REPT(" ",99)),793,99)),FIND(":",TRIM(MID(SUBSTITUTE($T2,";",REPT(" ",99)),793,99)))+1,99)),0) + IFERROR(VLOOKUP(LEFT(TRIM(MID(SUBSTITUTE($T2,";",REPT(" ",99)),892,99)),FIND(":",TRIM(MID(SUBSTITUTE($T2,";",REPT(" ",99)),892,99)))-1),Materiales!$A$2:$E$502,5,FALSE)*VALUE(MID(TRIM(MID(SUBSTITUTE($T2,";",REPT(" ",99)),892,99)),FIND(":",TRIM(MID(SUBSTITUTE($T2,";",REPT(" ",99)),892,99)))+1,99)),0)))} -> 200 | V2: ENV_YESO:1 | W2: {=IF($A2="","",IF($V2="",0,IFERROR(VLOOKUP(LEFT(TRIM(MID(SUBSTITUTE($V2,";",REPT(" ",99)),1,99)),FIND(":",TRIM(MID(SUBSTITUTE($V2,";",REPT(" ",99)),1,99)))-1),Materiales!$A$2:$E$502,5,FALSE)*VALUE(MID(TRIM(MID(SUBSTITUTE($V2,";",REPT(" ",99)),1,99)),FIND(":",TRIM(MID(SUBSTITUTE($V2,";",REPT(" ",99)),1,99)))+1,99)),0) + IFERROR(VLOOKUP(LEFT(TRIM(MID(SUBSTITUTE($V2,";",REPT(" ",99)),100,99)),FIND(":",TRIM(MID(SUBSTITUTE($V2,";",REPT(" ",99)),100,99)))-1),Materiales!$A$2:$E$502,5,FALSE)*VALUE(MID(TRIM(MID(SUBSTITUTE($V2,";",REPT(" ",99)),100,99)),FIND(":",TRIM(MID(SUBSTITUTE($V2,";",REPT(" ",99)),100,99)))+1,99)),0) + IFERROR(VLOOKUP(LEFT(TRIM(MID(SUBSTITUTE($V2,";",REPT(" ",99)),199,99)),FIND(":",TRIM(MID(SUBSTITUTE($V2,";",REPT(" ",99)),199,99)))-1),Materiales!$A$2:$E$502,5,FALSE)*VALUE(MID(TRIM(MID(SUBSTITUTE($V2,";",REPT(" ",99)),199,99)),FIND(":",TRIM(MID(SUBSTITUTE($V2,";",REPT(" ",99)),199,99)))+1,99)),0) + IFERROR(VLOOKUP(LEFT(TRIM(MID(SUBSTITUTE($V2,";",REPT(" ",99)),298,99)),FIND(":",TRIM(MID(SUBSTITUTE($V2,";",REPT(" ",99)),298,99)))-1),Materiales!$A$2:$E$502,5,FALSE)*VALUE(MID(TRIM(MID(SUBSTITUTE($V2,";",REPT(" ",99)),298,99)),FIND(":",TRIM(MID(SUBSTITUTE($V2,";",REPT(" ",99)),298,99)))+1,99)),0) + IFERROR(VLOOKUP(LEFT(TRIM(MID(SUBSTITUTE($V2,";",REPT(" ",99)),397,99)),FIND(":",TRIM(MID(SUBSTITUTE($V2,";",REPT(" ",99)),397,99)))-1),Materiales!$A$2:$E$502,5,FALSE)*VALUE(MID(TRIM(MID(SUBSTITUTE($V2,";",REPT(" ",99)),397,99)),FIND(":",TRIM(MID(SUBSTITUTE($V2,";",REPT(" ",99)),397,99)))+1,99)),0) + IFERROR(VLOOKUP(LEFT(TRIM(MID(SUBSTITUTE($V2,";",REPT(" ",99)),496,99)),FIND(":",TRIM(MID(SUBSTITUTE($V2,";",REPT(" ",99)),496,99)))-1),Materiales!$A$2:$E$502,5,FALSE)*VALUE(MID(TRIM(MID(SUBSTITUTE($V2,";",REPT(" ",99)),496,99)),FIND(":",TRIM(MID(SUBSTITUTE($V2,";",REPT(" ",99)),496,99)))+1,99)),0) + IFERROR(VLOOKUP(LEFT(TRIM(MID(SUBSTITUTE($V2,";",REPT(" ",99)),595,99)),FIND(":",TRIM(MID(SUBSTITUTE($V2,";",REPT(" ",99)),595,99)))-1),Materiales!$A$2:$E$502,5,FALSE)*VALUE(MID(TRIM(MID(SUBSTITUTE($V2,";",REPT(" ",99)),595,99)),FIND(":",TRIM(MID(SUBSTITUTE($V2,";",REPT(" ",99)),595,99)))+1,99)),0) + IFERROR(VLOOKUP(LEFT(TRIM(MID(SUBSTITUTE($V2,";",REPT(" ",99)),694,99)),FIND(":",TRIM(MID(SUBSTITUTE($V2,";",REPT(" ",99)),694,99)))-1),Materiales!$A$2:$E$502,5,FALSE)*VALUE(MID(TRIM(MID(SUBSTITUTE($V2,";",REPT(" ",99)),694,99)),FIND(":",TRIM(MID(SUBSTITUTE($V2,";",REPT(" ",99)),694,99)))+1,99)),0) + IFERROR(VLOOKUP(LEFT(TRIM(MID(SUBSTITUTE($V2,";",REPT(" ",99)),793,99)),FIND(":",TRIM(MID(SUBSTITUTE($V2,";",REPT(" ",99)),793,99)))-1),Materiales!$A$2:$E$502,5,FALSE)*VALUE(MID(TRIM(MID(SUBSTITUTE($V2,";",REPT(" ",99)),793,99)),FIND(":",TRIM(MID(SUBSTITUTE($V2,";",REPT(" ",99)),793,99)))+1,99)),0) + IFERROR(VLOOKUP(LEFT(TRIM(MID(SUBSTITUTE($V2,";",REPT(" ",99)),892,99)),FIND(":",TRIM(MID(SUBSTITUTE($V2,";",REPT(" ",99)),892,99)))-1),Materiales!$A$2:$E$502,5,FALSE)*VALUE(MID(TRIM(MID(SUBSTITUTE($V2,";",REPT(" ",99)),892,99)),FIND(":",TRIM(MID(SUBSTITUTE($V2,";",REPT(" ",99)),892,99)))+1,99)),0)))} -> 4000 | X2: =IF($A2="","",SUM($G2,$H2,$K2,$N2,$Q2,$S2,$U2,$W2)) -> 7645.3077 | Y2: 3 | Z2: =X2*Y2 -> 22935.923 | AA2: 0 | AB2: =AA2+Z2 -> 22935.923 | AC2: 22000 | AD2: =AB2-X2 -> 15290.615 | AE2: =AC2-X2 -> 14354.692 | AF2: =AE2/AD2 -> 0.93879101
A3: Vela Margarita en yeso con tapa | B3: CERA_MOLDE | C3: 1 | F3: 74 | G3: {=IF($A3="","",IFERROR($F3*(N($C3)*XLOOKUP($B3,Ceras!$A$2:$A$500,Ceras!$G$2:$G$500,0)+IF($D3="",0,N($E3)*XLOOKUP($D3,Ceras!$A$2:$A$500,Ceras!$G$2:$G$500,0))),"Revisar cera"))} -> 1332 | H3: =F3*1.5 -> 111 | I3: PABILO6-8 | J3: 3 | K3: {=IF($A3="","",IFERROR($J3*XLOOKUP($I3,Pabilos!$A$2:$A$500,Pabilos!$H$2:$H$500,0),"Revisar pabilo"))} -> 60 | L3: ES_MARACUYA | M3: =F3/10 -> 7.4 | N3: {=IF($A3="","",IFERROR($M3*XLOOKUP($L3,Esencias!$A$2:$A$501,Esencias!$G$2:$G$501,0),"Revisar esencia"))} -> 1850 | O3: COLOR_VERDE | P3: 1 | Q3: {=IF($A3="","",IFERROR(IF($P3="",1,$P3)*XLOOKUP($O3,Colores!$A$2:$A$500,Colores!$H$2:$H$500,0),"Revisar color"))} -> 92.307692 | S3: {=IF($A3="","",IF($R3="",0,IFERROR(VLOOKUP(LEFT(TRIM(MID(SUBSTITUTE($R3,";",REPT(" ",99)),1,99)),FIND(":",TRIM(MID(SUBSTITUTE($R3,";",REPT(" ",99)),1,99)))-1),Materiales!$A$2:$E$502,5,FALSE)*VALUE(MID(TRIM(MID(SUBSTITUTE($R3,";",REPT(" ",99)),1,99)),FIND(":",TRIM(MID(SUBSTITUTE($R3,";",REPT(" ",99)),1,99)))+1,99)),0) + IFERROR(VLOOKUP(LEFT(TRIM(MID(SUBSTITUTE($R3,";",REPT(" ",99)),100,99)),FIND(":",TRIM(MID(SUBSTITUTE($R3,";",REPT(" ",99)),100,99)))-1),Materiales!$A$2:$E$502,5,FALSE)*VALUE(MID(TRIM(MID(SUBSTITUTE($R3,";",REPT(" ",99)),100,99)),FIND(":",TRIM(MID(SUBSTITUTE($R3,";",REPT(" ",99)),100,99)))+1,99)),0) + IFERROR(VLOOKUP(LEFT(TRIM(MID(SUBSTITUTE($R3,";",REPT(" ",99)),199,99)),FIND(":",TRIM(MID(SUBSTITUTE($R3,";",REPT(" ",99)),199,99)))-1),Materiales!$A$2:$E$502,5,FALSE)*VALUE(MID(TRIM(MID(SUBSTITUTE($R3,";",REPT(" ",99)),199,99)),FIND(":",TRIM(MID(SUBSTITUTE($R3,";",REPT(" ",99)),199,99)))+1,99)),0) + IFERROR(VLOOKUP(LEFT(TRIM(MID(SUBSTITUTE($R3,";",REPT(" ",99)),298,99)),FIND(":",TRIM(MID(SUBSTITUTE($R3,";",REPT(" ",99)),298,99)))-1),Materiales!$A$2:$E$502,5,FALSE)*VALUE(MID(TRIM(MID(SUBSTITUTE($R3,";",REPT(" ",99)),298,99)),FIND(":",TRIM(MID(SUBSTITUTE($R3,";",REPT(" ",99)),298,99)))+1,99)),0) + IFERROR(VLOOKUP(LEFT(TRIM(MID(SUBSTITUTE($R3,";",REPT(" ",99)),397,99)),FIND(":",TRIM(MID(SUBSTITUTE($R3,";",REPT(" ",99)),397,99)))-1),Materiales!$A$2:$E$502,5,FALSE)*VALUE(MID(TRIM(MID(SUBSTITUTE($R3,";",REPT(" ",99)),397,99)),FIND(":",TRIM(MID(SUBSTITUTE($R3,";",REPT(" ",99)),397,99)))+1,99)),0) + IFERROR(VLOOKUP(LEFT(TRIM(MID(SUBSTITUTE($R3,";",REPT(" ",99)),496,99)),FIND(":",TRIM(MID(SUBSTITUTE($R3,";",REPT(" ",99)),496,99)))-1),Materiales!$A$2:$E$502,5,FALSE)*VALUE(MID(TRIM(MID(SUBSTITUTE($R3,";",REPT(" ",99)),496,99)),FIND(":",TRIM(MID(SUBSTITUTE($R3,";",REPT(" ",99)),496,99)))+1,99)),0) + IFERROR(VLOOKUP(LEFT(TRIM(MID(SUBSTITUTE($R3,";",REPT(" ",99)),595,99)),FIND(":",TRIM(MID(SUBSTITUTE($R3,";",REPT(" ",99)),595,99)))-1),Materiales!$A$2:$E$502,5,FALSE)*VALUE(MID(TRIM(MID(SUBSTITUTE($R3,";",REPT(" ",99)),595,99)),FIND(":",TRIM(MID(SUBSTITUTE($R3,";",REPT(" ",99)),595,99)))+1,99)),0) + IFERROR(VLOOKUP(LEFT(TRIM(MID(SUBSTITUTE($R3,";",REPT(" ",99)),694,99)),FIND(":",TRIM(MID(SUBSTITUTE($R3,";",REPT(" ",99)),694,99)))-1),Materiales!$A$2:$E$502,5,FALSE)*VALUE(MID(TRIM(MID(SUBSTITUTE($R3,";",REPT(" ",99)),694,99)),FIND(":",TRIM(MID(SUBSTITUTE($R3,";",REPT(" ",99)),694,99)))+1,99)),0) + IFERROR(VLOOKUP(LEFT(TRIM(MID(SUBSTITUTE($R3,";",REPT(" ",99)),793,99)),FIND(":",TRIM(MID(SUBSTITUTE($R3,";",REPT(" ",99)),793,99)))-1),Materiales!$A$2:$E$502,5,FALSE)*VALUE(MID(TRIM(MID(SUBSTITUTE($R3,";",REPT(" ",99)),793,99)),FIND(":",TRIM(MID(SUBSTITUTE($R3,";",REPT(" ",99)),793,99)))+1,99)),0) + IFERROR(VLOOKUP(LEFT(TRIM(MID(SUBSTITUTE($R3,";",REPT(" ",99)),892,99)),FIND(":",TRIM(MID(SUBSTITUTE($R3,";",REPT(" ",99)),892,99)))-1),Materiales!$A$2:$E$502,5,FALSE)*VALUE(MID(TRIM(MID(SUBSTITUTE($R3,";",REPT(" ",99)),892,99)),FIND(":",TRIM(MID(SUBSTITUTE($R3,";",REPT(" ",99)),892,99)))+1,99)),0)))} -> 0 | T3: PINTURA_VERDE:1 | U3: {=IF($A3="","",IF($T3="",0,IFERROR(VLOOKUP(LEFT(TRIM(MID(SUBSTITUTE($T3,";",REPT(" ",99)),1,99)),FIND(":",TRIM(MID(SUBSTITUTE($T3,";",REPT(" ",99)),1,99)))-1),Materiales!$A$2:$E$502,5,FALSE)*VALUE(MID(TRIM(MID(SUBSTITUTE($T3,";",REPT(" ",99)),1,99)),FIND(":",TRIM(MID(SUBSTITUTE($T3,";",REPT(" ",99)),1,99)))+1,99)),0) + IFERROR(VLOOKUP(LEFT(TRIM(MID(SUBSTITUTE($T3,";",REPT(" ",99)),100,99)),FIND(":",TRIM(MID(SUBSTITUTE($T3,";",REPT(" ",99)),100,99)))-1),Materiales!$A$2:$E$502,5,FALSE)*VALUE(MID(TRIM(MID(SUBSTITUTE($T3,";",REPT(" ",99)),100,99)),FIND(":",TRIM(MID(SUBSTITUTE($T3,";",REPT(" ",99)),100,99)))+1,99)),0) + IFERROR(VLOOKUP(LEFT(TRIM(MID(SUBSTITUTE($T3,";",REPT(" ",99)),199,99)),FIND(":",TRIM(MID(SUBSTITUTE($T3,";",REPT(" ",99)),199,99)))-1),Materiales!$A$2:$E$502,5,FALSE)*VALUE(MID(TRIM(MID(SUBSTITUTE($T3,";",REPT(" ",99)),199,99)),FIND(":",TRIM(MID(SUBSTITUTE($T3,";",REPT(" ",99)),199,99)))+1,99)),0) + IFERROR(VLOOKUP(LEFT(TRIM(MID(SUBSTITUTE($T3,";",REPT(" ",99)),298,99)),FIND(":",TRIM(MID(SUBSTITUTE($T3,";",REPT(" ",99)),298,99)))-1),Materiales!$A$2:$E$502,5,FALSE)*VALUE(MID(TRIM(MID(SUBSTITUTE($T3,";",REPT(" ",99)),298,99)),FIND(":",TRIM(MID(SUBSTITUTE($T3,";",REPT(" ",99)),298,99)))+1,99)),0) + IFERROR(VLOOKUP(LEFT(TRIM(MID(SUBSTITUTE($T3,";",REPT(" ",99)),397,99)),FIND(":",TRIM(MID(SUBSTITUTE($T3,";",REPT(" ",99)),397,99)))-1),Materiales!$A$2:$E$502,5,FALSE)*VALUE(MID(TRIM(MID(SUBSTITUTE($T3,";",REPT(" ",99)),397,99)),FIND(":",TRIM(MID(SUBSTITUTE($T3,";",REPT(" ",99)),397,99)))+1,99)),0) + IFERROR(VLOOKUP(LEFT(TRIM(MID(SUBSTITUTE($T3,";",REPT(" ",99)),496,99)),FIND(":",TRIM(MID(SUBSTITUTE($T3,";",REPT(" ",99)),496,99)))-1),Materiales!$A$2:$E$502,5,FALSE)*VALUE(MID(TRIM(MID(SUBSTITUTE($T3,";",REPT(" ",99)),496,99)),FIND(":",TRIM(MID(SUBSTITUTE($T3,";",REPT(" ",99)),496,99)))+1,99)),0) + IFERROR(VLOOKUP(LEFT(TRIM(MID(SUBSTITUTE($T3,";",REPT(" ",99)),595,99)),FIND(":",TRIM(MID(SUBSTITUTE($T3,";",REPT(" ",99)),595,99)))-1),Materiales!$A$2:$E$502,5,FALSE)*VALUE(MID(TRIM(MID(SUBSTITUTE($T3,";",REPT(" ",99)),595,99)),FIND(":",TRIM(MID(SUBSTITUTE($T3,";",REPT(" ",99)),595,99)))+1,99)),0) + IFERROR(VLOOKUP(LEFT(TRIM(MID(SUBSTITUTE($T3,";",REPT(" ",99)),694,99)),FIND(":",TRIM(MID(SUBSTITUTE($T3,";",REPT(" ",99)),694,99)))-1),Materiales!$A$2:$E$502,5,FALSE)*VALUE(MID(TRIM(MID(SUBSTITUTE($T3,";",REPT(" ",99)),694,99)),FIND(":",TRIM(MID(SUBSTITUTE($T3,";",REPT(" ",99)),694,99)))+1,99)),0) + IFERROR(VLOOKUP(LEFT(TRIM(MID(SUBSTITUTE($T3,";",REPT(" ",99)),793,99)),FIND(":",TRIM(MID(SUBSTITUTE($T3,";",REPT(" ",99)),793,99)))-1),Materiales!$A$2:$E$502,5,FALSE)*VALUE(MID(TRIM(MID(SUBSTITUTE($T3,";",REPT(" ",99)),793,99)),FIND(":",TRIM(MID(SUBSTITUTE($T3,";",REPT(" ",99)),793,99)))+1,99)),0) + IFERROR(VLOOKUP(LEFT(TRIM(MID(SUBSTITUTE($T3,";",REPT(" ",99)),892,99)),FIND(":",TRIM(MID(SUBSTITUTE($T3,";",REPT(" ",99)),892,99)))-1),Materiales!$A$2:$E$502,5,FALSE)*VALUE(MID(TRIM(MID(SUBSTITUTE($T3,";",REPT(" ",99)),892,99)),FIND(":",TRIM(MID(SUBSTITUTE($T3,";",REPT(" ",99)),892,99)))+1,99)),0)))} -> 200 | V3: ENV_YESO:1;TAPA_YESO:1 | W3: {=IF($A3="","",IF($V3="",0,IFERROR(VLOOKUP(LEFT(TRIM(MID(SUBSTITUTE($V3,";",REPT(" ",99)),1,99)),FIND(":",TRIM(MID(SUBSTITUTE($V3,";",REPT(" ",99)),1,99)))-1),Materiales!$A$2:$E$502,5,FALSE)*VALUE(MID(TRIM(MID(SUBSTITUTE($V3,";",REPT(" ",99)),1,99)),FIND(":",TRIM(MID(SUBSTITUTE($V3,";",REPT(" ",99)),1,99)))+1,99)),0) + IFERROR(VLOOKUP(LEFT(TRIM(MID(SUBSTITUTE($V3,";",REPT(" ",99)),100,99)),FIND(":",TRIM(MID(SUBSTITUTE($V3,";",REPT(" ",99)),100,99)))-1),Materiales!$A$2:$E$502,5,FALSE)*VALUE(MID(TRIM(MID(SUBSTITUTE($V3,";",REPT(" ",99)),100,99)),FIND(":",TRIM(MID(SUBSTITUTE($V3,";",REPT(" ",99)),100,99)))+1,99)),0) + IFERROR(VLOOKUP(LEFT(TRIM(MID(SUBSTITUTE($V3,";",REPT(" ",99)),199,99)),FIND(":",TRIM(MID(SUBSTITUTE($V3,";",REPT(" ",99)),199,99)))-1),Materiales!$A$2:$E$502,5,FALSE)*VALUE(MID(TRIM(MID(SUBSTITUTE($V3,";",REPT(" ",99)),199,99)),FIND(":",TRIM(MID(SUBSTITUTE($V3,";",REPT(" ",99)),199,99)))+1,99)),0) + IFERROR(VLOOKUP(LEFT(TRIM(MID(SUBSTITUTE($V3,";",REPT(" ",99)),298,99)),FIND(":",TRIM(MID(SUBSTITUTE($V3,";",REPT(" ",99)),298,99)))-1),Materiales!$A$2:$E$502,5,FALSE)*VALUE(MID(TRIM(MID(SUBSTITUTE($V3,";",REPT(" ",99)),298,99)),FIND(":",TRIM(MID(SUBSTITUTE($V3,";",REPT(" ",99)),298,99)))+1,99)),0) + IFERROR(VLOOKUP(LEFT(TRIM(MID(SUBSTITUTE($V3,";",REPT(" ",99)),397,99)),FIND(":",TRIM(MID(SUBSTITUTE($V3,";",REPT(" ",99)),397,99)))-1),Materiales!$A$2:$E$502,5,FALSE)*VALUE(MID(TRIM(MID(SUBSTITUTE($V3,";",REPT(" ",99)),397,99)),FIND(":",TRIM(MID(SUBSTITUTE($V3,";",REPT(" ",99)),397,99)))+1,99)),0) + IFERROR(VLOOKUP(LEFT(TRIM(MID(SUBSTITUTE($V3,";",REPT(" ",99)),496,99)),FIND(":",TRIM(MID(SUBSTITUTE($V3,";",REPT(" ",99)),496,99)))-1),Materiales!$A$2:$E$502,5,FALSE)*VALUE(MID(TRIM(MID(SUBSTITUTE($V3,";",REPT(" ",99)),496,99)),FIND(":",TRIM(MID(SUBSTITUTE($V3,";",REPT(" ",99)),496,99)))+1,99)),0) + IFERROR(VLOOKUP(LEFT(TRIM(MID(SUBSTITUTE($V3,";",REPT(" ",99)),595,99)),FIND(":",TRIM(MID(SUBSTITUTE($V3,";",REPT(" ",99)),595,99)))-1),Materiales!$A$2:$E$502,5,FALSE)*VALUE(MID(TRIM(MID(SUBSTITUTE($V3,";",REPT(" ",99)),595,99)),FIND(":",TRIM(MID(SUBSTITUTE($V3,";",REPT(" ",99)),595,99)))+1,99)),0) + IFERROR(VLOOKUP(LEFT(TRIM(MID(SUBSTITUTE($V3,";",REPT(" ",99)),694,99)),FIND(":",TRIM(MID(SUBSTITUTE($V3,";",REPT(" ",99)),694,99)))-1),Materiales!$A$2:$E$502,5,FALSE)*VALUE(MID(TRIM(MID(SUBSTITUTE($V3,";",REPT(" ",99)),694,99)),FIND(":",TRIM(MID(SUBSTITUTE($V3,";",REPT(" ",99)),694,99)))+1,99)),0) + IFERROR(VLOOKUP(LEFT(TRIM(MID(SUBSTITUTE($V3,";",REPT(" ",99)),793,99)),FIND(":",TRIM(MID(SUBSTITUTE($V3,";",REPT(" ",99)),793,99)))-1),Materiales!$A$2:$E$502,5,FALSE)*VALUE(MID(TRIM(MID(SUBSTITUTE($V3,";",REPT(" ",99)),793,99)),FIND(":",TRIM(MID(SUBSTITUTE($V3,";",REPT(" ",99)),793,99)))+1,99)),0) + IFERROR(VLOOKUP(LEFT(TRIM(MID(SUBSTITUTE($V3,";",REPT(" ",99)),892,99)),FIND(":",TRIM(MID(SUBSTITUTE($V3,";",REPT(" ",99)),892,99)))-1),Materiales!$A$2:$E$502,5,FALSE)*VALUE(MID(TRIM(MID(SUBSTITUTE($V3,";",REPT(" ",99)),892,99)),FIND(":",TRIM(MID(SUBSTITUTE($V3,";",REPT(" ",99)),892,99)))+1,99)),0)))} -> 5000 | X3: =IF($A3="","",SUM($G3,$H3,$K3,$N3,$Q3,$S3,$U3,$W3)) -> 8645.3077 | Y3: 3 | Z3: =X3*Y3 -> 25935.923 | AA3: 0 | AB3: =AA3+Z3 -> 25935.923 | AC3: 25000 | AD3: =AB3-X3 -> 17290.615 | AE3: =AC3-X3 -> 16354.692 | AF3: =AE3/AD3 -> 0.94587104
A4: Vela Margarita sola | B4: CERA_MOLDE | C4: 1 | F4: 22 | G4: {=IF($A4="","",IFERROR($F4*(N($C4)*XLOOKUP($B4,Ceras!$A$2:$A$500,Ceras!$G$2:$G$500,0)+IF($D4="",0,N($E4)*XLOOKUP($D4,Ceras!$A$2:$A$500,Ceras!$G$2:$G$500,0))),"Revisar cera"))} -> 396 | H4: =F4*1.5 -> 33 | I4: PABILO2-4 | J4: 3 | K4: {=IF($A4="","",IFERROR($J4*XLOOKUP($I4,Pabilos!$A$2:$A$500,Pabilos!$H$2:$H$500,0),"Revisar pabilo"))} -> 45 | L4: ES_BEDOYA | M4: =F4*0.08 -> 1.76 | N4: {=IF($A4="","",IFERROR($M4*XLOOKUP($L4,Esencias!$A$2:$A$501,Esencias!$G$2:$G$501,0),"Revisar esencia"))} -> 247.88732 | O4: COLOR_CAFE | P4: 1 | Q4: {=IF($A4="","",IFERROR(IF($P4="",1,$P4)*XLOOKUP($O4,Colores!$A$2:$A$500,Colores!$H$2:$H$500,0),"Revisar color"))} -> 92.307692 | S4: {=IF($A4="","",IF($R4="",0,IFERROR(VLOOKUP(LEFT(TRIM(MID(SUBSTITUTE($R4,";",REPT(" ",99)),1,99)),FIND(":",TRIM(MID(SUBSTITUTE($R4,";",REPT(" ",99)),1,99)))-1),Materiales!$A$2:$E$502,5,FALSE)*VALUE(MID(TRIM(MID(SUBSTITUTE($R4,";",REPT(" ",99)),1,99)),FIND(":",TRIM(MID(SUBSTITUTE($R4,";",REPT(" ",99)),1,99)))+1,99)),0) + IFERROR(VLOOKUP(LEFT(TRIM(MID(SUBSTITUTE($R4,";",REPT(" ",99)),100,99)),FIND(":",TRIM(MID(SUBSTITUTE($R4,";",REPT(" ",99)),100,99)))-1),Materiales!$A$2:$E$502,5,FALSE)*VALUE(MID(TRIM(MID(SUBSTITUTE($R4,";",REPT(" ",99)),100,99)),FIND(":",TRIM(MID(SUBSTITUTE($R4,";",REPT(" ",99)),100,99)))+1,99)),0) + IFERROR(VLOOKUP(LEFT(TRIM(MID(SUBSTITUTE($R4,";",REPT(" ",99)),199,99)),FIND(":",TRIM(MID(SUBSTITUTE($R4,";",REPT(" ",99)),199,99)))-1),Materiales!$A$2:$E$502,5,FALSE)*VALUE(MID(TRIM(MID(SUBSTITUTE($R4,";",REPT(" ",99)),199,99)),FIND(":",TRIM(MID(SUBSTITUTE($R4,";",REPT(" ",99)),199,99)))+1,99)),0) + IFERROR(VLOOKUP(LEFT(TRIM(MID(SUBSTITUTE($R4,";",REPT(" ",99)),298,99)),FIND(":",TRIM(MID(SUBSTITUTE($R4,";",REPT(" ",99)),298,99)))-1),Materiales!$A$2:$E$502,5,FALSE)*VALUE(MID(TRIM(MID(SUBSTITUTE($R4,";",REPT(" ",99)),298,99)),FIND(":",TRIM(MID(SUBSTITUTE($R4,";",REPT(" ",99)),298,99)))+1,99)),0) + IFERROR(VLOOKUP(LEFT(TRIM(MID(SUBSTITUTE($R4,";",REPT(" ",99)),397,99)),FIND(":",TRIM(MID(SUBSTITUTE($R4,";",REPT(" ",99)),397,99)))-1),Materiales!$A$2:$E$502,5,FALSE)*VALUE(MID(TRIM(MID(SUBSTITUTE($R4,";",REPT(" ",99)),397,99)),FIND(":",TRIM(MID(SUBSTITUTE($R4,";",REPT(" ",99)),397,99)))+1,99)),0) + IFERROR(VLOOKUP(LEFT(TRIM(MID(SUBSTITUTE($R4,";",REPT(" ",99)),496,99)),FIND(":",TRIM(MID(SUBSTITUTE($R4,";",REPT(" ",99)),496,99)))-1),Materiales!$A$2:$E$502,5,FALSE)*VALUE(MID(TRIM(MID(SUBSTITUTE($R4,";",REPT(" ",99)),496,99)),FIND(":",TRIM(MID(SUBSTITUTE($R4,";",REPT(" ",99)),496,99)))+1,99)),0) + IFERROR(VLOOKUP(LEFT(TRIM(MID(SUBSTITUTE($R4,";",REPT(" ",99)),595,99)),FIND(":",TRIM(MID(SUBSTITUTE($R4,";",REPT(" ",99)),595,99)))-1),Materiales!$A$2:$E$502,5,FALSE)*VALUE(MID(TRIM(MID(SUBSTITUTE($R4,";",REPT(" ",99)),595,99)),FIND(":",TRIM(MID(SUBSTITUTE($R4,";",REPT(" ",99)),595,99)))+1,99)),0) + IFERROR(VLOOKUP(LEFT(TRIM(MID(SUBSTITUTE($R4,";",REPT(" ",99)),694,99)),FIND(":",TRIM(MID(SUBSTITUTE($R4,";",REPT(" ",99)),694,99)))-1),Materiales!$A$2:$E$502,5,FALSE)*VALUE(MID(TRIM(MID(SUBSTITUTE($R4,";",REPT(" ",99)),694,99)),FIND(":",TRIM(MID(SUBSTITUTE($R4,";",REPT(" ",99)),694,99)))+1,99)),0) + IFERROR(VLOOKUP(LEFT(TRIM(MID(SUBSTITUTE($R4,";",REPT(" ",99)),793,99)),FIND(":",TRIM(MID(SUBSTITUTE($R4,";",REPT(" ",99)),793,99)))-1),Materiales!$A$2:$E$502,5,FALSE)*VALUE(MID(TRIM(MID(SUBSTITUTE($R4,";",REPT(" ",99)),793,99)),FIND(":",TRIM(MID(SUBSTITUTE($R4,";",REPT(" ",99)),793,99)))+1,99)),0) + IFERROR(VLOOKUP(LEFT(TRIM(MID(SUBSTITUTE($R4,";",REPT(" ",99)),892,99)),FIND(":",TRIM(MID(SUBSTITUTE($R4,";",REPT(" ",99)),892,99)))-1),Materiales!$A$2:$E$502,5,FALSE)*VALUE(MID(TRIM(MID(SUBSTITUTE($R4,";",REPT(" ",99)),892,99)),FIND(":",TRIM(MID(SUBSTITUTE($R4,";",REPT(" ",99)),892,99)))+1,99)),0)))} -> 0 | U4: {=IF($A4="","",IF($T4="",0,IFERROR(VLOOKUP(LEFT(TRIM(MID(SUBSTITUTE($T4,";",REPT(" ",99)),1,99)),FIND(":",TRIM(MID(SUBSTITUTE($T4,";",REPT(" ",99)),1,99)))-1),Materiales!$A$2:$E$502,5,FALSE)*VALUE(MID(TRIM(MID(SUBSTITUTE($T4,";",REPT(" ",99)),1,99)),FIND(":",TRIM(MID(SUBSTITUTE($T4,";",REPT(" ",99)),1,99)))+1,99)),0) + IFERROR(VLOOKUP(LEFT(TRIM(MID(SUBSTITUTE($T4,";",REPT(" ",99)),100,99)),FIND(":",TRIM(MID(SUBSTITUTE($T4,";",REPT(" ",99)),100,99)))-1),Materiales!$A$2:$E$502,5,FALSE)*VALUE(MID(TRIM(MID(SUBSTITUTE($T4,";",REPT(" ",99)),100,99)),FIND(":",TRIM(MID(SUBSTITUTE($T4,";",REPT(" ",99)),100,99)))+1,99)),0) + IFERROR(VLOOKUP(LEFT(TRIM(MID(SUBSTITUTE($T4,";",REPT(" ",99)),199,99)),FIND(":",TRIM(MID(SUBSTITUTE($T4,";",REPT(" ",99)),199,99)))-1),Materiales!$A$2:$E$502,5,FALSE)*VALUE(MID(TRIM(MID(SUBSTITUTE($T4,";",REPT(" ",99)),199,99)),FIND(":",TRIM(MID(SUBSTITUTE($T4,";",REPT(" ",99)),199,99)))+1,99)),0) + IFERROR(VLOOKUP(LEFT(TRIM(MID(SUBSTITUTE($T4,";",REPT(" ",99)),298,99)),FIND(":",TRIM(MID(SUBSTITUTE($T4,";",REPT(" ",99)),298,99)))-1),Materiales!$A$2:$E$502,5,FALSE)*VALUE(MID(TRIM(MID(SUBSTITUTE($T4,";",REPT(" ",99)),298,99)),FIND(":",TRIM(MID(SUBSTITUTE($T4,";",REPT(" ",99)),298,99)))+1,99)),0) + IFERROR(VLOOKUP(LEFT(TRIM(MID(SUBSTITUTE($T4,";",REPT(" ",99)),397,99)),FIND(":",TRIM(MID(SUBSTITUTE($T4,";",REPT(" ",99)),397,99)))-1),Materiales!$A$2:$E$502,5,FALSE)*VALUE(MID(TRIM(MID(SUBSTITUTE($T4,";",REPT(" ",99)),397,99)),FIND(":",TRIM(MID(SUBSTITUTE($T4,";",REPT(" ",99)),397,99)))+1,99)),0) + IFERROR(VLOOKUP(LEFT(TRIM(MID(SUBSTITUTE($T4,";",REPT(" ",99)),496,99)),FIND(":",TRIM(MID(SUBSTITUTE($T4,";",REPT(" ",99)),496,99)))-1),Materiales!$A$2:$E$502,5,FALSE)*VALUE(MID(TRIM(MID(SUBSTITUTE($T4,";",REPT(" ",99)),496,99)),FIND(":",TRIM(MID(SUBSTITUTE($T4,";",REPT(" ",99)),496,99)))+1,99)),0) + IFERROR(VLOOKUP(LEFT(TRIM(MID(SUBSTITUTE($T4,";",REPT(" ",99)),595,99)),FIND(":",TRIM(MID(SUBSTITUTE($T4,";",REPT(" ",99)),595,99)))-1),Materiales!$A$2:$E$502,5,FALSE)*VALUE(MID(TRIM(MID(SUBSTITUTE($T4,";",REPT(" ",99)),595,99)),FIND(":",TRIM(MID(SUBSTITUTE($T4,";",REPT(" ",99)),595,99)))+1,99)),0) + IFERROR(VLOOKUP(LEFT(TRIM(MID(SUBSTITUTE($T4,";",REPT(" ",99)),694,99)),FIND(":",TRIM(MID(SUBSTITUTE($T4,";",REPT(" ",99)),694,99)))-1),Materiales!$A$2:$E$502,5,FALSE)*VALUE(MID(TRIM(MID(SUBSTITUTE($T4,";",REPT(" ",99)),694,99)),FIND(":",TRIM(MID(SUBSTITUTE($T4,";",REPT(" ",99)),694,99)))+1,99)),0) + IFERROR(VLOOKUP(LEFT(TRIM(MID(SUBSTITUTE($T4,";",REPT(" ",99)),793,99)),FIND(":",TRIM(MID(SUBSTITUTE($T4,";",REPT(" ",99)),793,99)))-1),Materiales!$A$2:$E$502,5,FALSE)*VALUE(MID(TRIM(MID(SUBSTITUTE($T4,";",REPT(" ",99)),793,99)),FIND(":",TRIM(MID(SUBSTITUTE($T4,";",REPT(" ",99)),793,99)))+1,99)),0) + IFERROR(VLOOKUP(LEFT(TRIM(MID(SUBSTITUTE($T4,";",REPT(" ",99)),892,99)),FIND(":",TRIM(MID(SUBSTITUTE($T4,";",REPT(" ",99)),892,99)))-1),Materiales!$A$2:$E$502,5,FALSE)*VALUE(MID(TRIM(MID(SUBSTITUTE($T4,";",REPT(" ",99)),892,99)),FIND(":",TRIM(MID(SUBSTITUTE($T4,";",REPT(" ",99)),892,99)))+1,99)),0)))} -> 0 | W4: {=IF($A4="","",IF($V4="",0,IFERROR(VLOOKUP(LEFT(TRIM(MID(SUBSTITUTE($V4,";",REPT(" ",99)),1,99)),FIND(":",TRIM(MID(SUBSTITUTE($V4,";",REPT(" ",99)),1,99)))-1),Materiales!$A$2:$E$502,5,FALSE)*VALUE(MID(TRIM(MID(SUBSTITUTE($V4,";",REPT(" ",99)),1,99)),FIND(":",TRIM(MID(SUBSTITUTE($V4,";",REPT(" ",99)),1,99)))+1,99)),0) + IFERROR(VLOOKUP(LEFT(TRIM(MID(SUBSTITUTE($V4,";",REPT(" ",99)),100,99)),FIND(":",TRIM(MID(SUBSTITUTE($V4,";",REPT(" ",99)),100,99)))-1),Materiales!$A$2:$E$502,5,FALSE)*VALUE(MID(TRIM(MID(SUBSTITUTE($V4,";",REPT(" ",99)),100,99)),FIND(":",TRIM(MID(SUBSTITUTE($V4,";",REPT(" ",99)),100,99)))+1,99)),0) + IFERROR(VLOOKUP(LEFT(TRIM(MID(SUBSTITUTE($V4,";",REPT(" ",99)),199,99)),FIND(":",TRIM(MID(SUBSTITUTE($V4,";",REPT(" ",99)),199,99)))-1),Materiales!$A$2:$E$502,5,FALSE)*VALUE(MID(TRIM(MID(SUBSTITUTE($V4,";",REPT(" ",99)),199,99)),FIND(":",TRIM(MID(SUBSTITUTE($V4,";",REPT(" ",99)),199,99)))+1,99)),0) + IFERROR(VLOOKUP(LEFT(TRIM(MID(SUBSTITUTE($V4,";",REPT(" ",99)),298,99)),FIND(":",TRIM(MID(SUBSTITUTE($V4,";",REPT(" ",99)),298,99)))-1),Materiales!$A$2:$E$502,5,FALSE)*VALUE(MID(TRIM(MID(SUBSTITUTE($V4,";",REPT(" ",99)),298,99)),FIND(":",TRIM(MID(SUBSTITUTE($V4,";",REPT(" ",99)),298,99)))+1,99)),0) + IFERROR(VLOOKUP(LEFT(TRIM(MID(SUBSTITUTE($V4,";",REPT(" ",99)),397,99)),FIND(":",TRIM(MID(SUBSTITUTE($V4,";",REPT(" ",99)),397,99)))-1),Materiales!$A$2:$E$502,5,FALSE)*VALUE(MID(TRIM(MID(SUBSTITUTE($V4,";",REPT(" ",99)),397,99)),FIND(":",TRIM(MID(SUBSTITUTE($V4,";",REPT(" ",99)),397,99)))+1,99)),0) + IFERROR(VLOOKUP(LEFT(TRIM(MID(SUBSTITUTE($V4,";",REPT(" ",99)),496,99)),FIND(":",TRIM(MID(SUBSTITUTE($V4,";",REPT(" ",99)),496,99)))-1),Materiales!$A$2:$E$502,5,FALSE)*VALUE(MID(TRIM(MID(SUBSTITUTE($V4,";",REPT(" ",99)),496,99)),FIND(":",TRIM(MID(SUBSTITUTE($V4,";",REPT(" ",99)),496,99)))+1,99)),0) + IFERROR(VLOOKUP(LEFT(TRIM(MID(SUBSTITUTE($V4,";",REPT(" ",99)),595,99)),FIND(":",TRIM(MID(SUBSTITUTE($V4,";",REPT(" ",99)),595,99)))-1),Materiales!$A$2:$E$502,5,FALSE)*VALUE(MID(TRIM(MID(SUBSTITUTE($V4,";",REPT(" ",99)),595,99)),FIND(":",TRIM(MID(SUBSTITUTE($V4,";",REPT(" ",99)),595,99)))+1,99)),0) + IFERROR(VLOOKUP(LEFT(TRIM(MID(SUBSTITUTE($V4,";",REPT(" ",99)),694,99)),FIND(":",TRIM(MID(SUBSTITUTE($V4,";",REPT(" ",99)),694,99)))-1),Materiales!$A$2:$E$502,5,FALSE)*VALUE(MID(TRIM(MID(SUBSTITUTE($V4,";",REPT(" ",99)),694,99)),FIND(":",TRIM(MID(SUBSTITUTE($V4,";",REPT(" ",99)),694,99)))+1,99)),0) + IFERROR(VLOOKUP(LEFT(TRIM(MID(SUBSTITUTE($V4,";",REPT(" ",99)),793,99)),FIND(":",TRIM(MID(SUBSTITUTE($V4,";",REPT(" ",99)),793,99)))-1),Materiales!$A$2:$E$502,5,FALSE)*VALUE(MID(TRIM(MID(SUBSTITUTE($V4,";",REPT(" ",99)),793,99)),FIND(":",TRIM(MID(SUBSTITUTE($V4,";",REPT(" ",99)),793,99)))+1,99)),0) + IFERROR(VLOOKUP(LEFT(TRIM(MID(SUBSTITUTE($V4,";",REPT(" ",99)),892,99)),FIND(":",TRIM(MID(SUBSTITUTE($V4,";",REPT(" ",99)),892,99)))-1),Materiales!$A$2:$E$502,5,FALSE)*VALUE(MID(TRIM(MID(SUBSTITUTE($V4,";",REPT(" ",99)),892,99)),FIND(":",TRIM(MID(SUBSTITUTE($V4,";",REPT(" ",99)),892,99)))+1,99)),0)))} -> 0 | X4: =IF($A4="","",SUM($G4,$H4,$K4,$N4,$Q4,$S4,$U4,$W4)) -> 814.19502 | Y4: 3 | Z4: =X4*Y4 -> 2442.585 | AA4: 0 | AB4: =AA4+Z4 -> 2442.585 | AC4: 2500 | AD4: =AB4-X4 -> 1628.39 | AE4: =AC4-X4 -> 1685.805 | AF4: =AE4/AD4 -> 1.0352587
A5: Vela Margarita en papel azucar | B5: CERA_MOLDE | C5: 1 | F5: 22 | G5: {=IF($A5="","",IFERROR($F5*(N($C5)*XLOOKUP($B5,Ceras!$A$2:$A$500,Ceras!$G$2:$G$500,0)+IF($D5="",0,N($E5)*XLOOKUP($D5,Ceras!$A$2:$A$500,Ceras!$G$2:$G$500,0))),"Revisar cera"))} -> 396 | H5: =F5*1.5 -> 33 | I5: PABILO2-4 | J5: 3 | K5: {=IF($A5="","",IFERROR($J5*XLOOKUP($I5,Pabilos!$A$2:$A$500,Pabilos!$H$2:$H$500,0),"Revisar pabilo"))} -> 45 | L5: ES_BEDOYA | M5: =F5/10 -> 2.2 | N5: {=IF($A5="","",IFERROR($M5*XLOOKUP($L5,Esencias!$A$2:$A$501,Esencias!$G$2:$G$501,0),"Revisar esencia"))} -> 309.85915 | O5: COLOR_CAFE | P5: 1 | Q5: {=IF($A5="","",IFERROR(IF($P5="",1,$P5)*XLOOKUP($O5,Colores!$A$2:$A$500,Colores!$H$2:$H$500,0),"Revisar color"))} -> 92.307692 | S5: {=IF($A5="","",IF($R5="",0,IFERROR(VLOOKUP(LEFT(TRIM(MID(SUBSTITUTE($R5,";",REPT(" ",99)),1,99)),FIND(":",TRIM(MID(SUBSTITUTE($R5,";",REPT(" ",99)),1,99)))-1),Materiales!$A$2:$E$502,5,FALSE)*VALUE(MID(TRIM(MID(SUBSTITUTE($R5,";",REPT(" ",99)),1,99)),FIND(":",TRIM(MID(SUBSTITUTE($R5,";",REPT(" ",99)),1,99)))+1,99)),0) + IFERROR(VLOOKUP(LEFT(TRIM(MID(SUBSTITUTE($R5,";",REPT(" ",99)),100,99)),FIND(":",TRIM(MID(SUBSTITUTE($R5,";",REPT(" ",99)),100,99)))-1),Materiales!$A$2:$E$502,5,FALSE)*VALUE(MID(TRIM(MID(SUBSTITUTE($R5,";",REPT(" ",99)),100,99)),FIND(":",TRIM(MID(SUBSTITUTE($R5,";",REPT(" ",99)),100,99)))+1,99)),0) + IFERROR(VLOOKUP(LEFT(TRIM(MID(SUBSTITUTE($R5,";",REPT(" ",99)),199,99)),FIND(":",TRIM(MID(SUBSTITUTE($R5,";",REPT(" ",99)),199,99)))-1),Materiales!$A$2:$E$502,5,FALSE)*VALUE(MID(TRIM(MID(SUBSTITUTE($R5,";",REPT(" ",99)),199,99)),FIND(":",TRIM(MID(SUBSTITUTE($R5,";",REPT(" ",99)),199,99)))+1,99)),0) + IFERROR(VLOOKUP(LEFT(TRIM(MID(SUBSTITUTE($R5,";",REPT(" ",99)),298,99)),FIND(":",TRIM(MID(SUBSTITUTE($R5,";",REPT(" ",99)),298,99)))-1),Materiales!$A$2:$E$502,5,FALSE)*VALUE(MID(TRIM(MID(SUBSTITUTE($R5,";",REPT(" ",99)),298,99)),FIND(":",TRIM(MID(SUBSTITUTE($R5,";",REPT(" ",99)),298,99)))+1,99)),0) + IFERROR(VLOOKUP(LEFT(TRIM(MID(SUBSTITUTE($R5,";",REPT(" ",99)),397,99)),FIND(":",TRIM(MID(SUBSTITUTE($R5,";",REPT(" ",99)),397,99)))-1),Materiales!$A$2:$E$502,5,FALSE)*VALUE(MID(TRIM(MID(SUBSTITUTE($R5,";",REPT(" ",99)),397,99)),FIND(":",TRIM(MID(SUBSTITUTE($R5,";",REPT(" ",99)),397,99)))+1,99)),0) + IFERROR(VLOOKUP(LEFT(TRIM(MID(SUBSTITUTE($R5,";",REPT(" ",99)),496,99)),FIND(":",TRIM(MID(SUBSTITUTE($R5,";",REPT(" ",99)),496,99)))-1),Materiales!$A$2:$E$502,5,FALSE)*VALUE(MID(TRIM(MID(SUBSTITUTE($R5,";",REPT(" ",99)),496,99)),FIND(":",TRIM(MID(SUBSTITUTE($R5,";",REPT(" ",99)),496,99)))+1,99)),0) + IFERROR(VLOOKUP(LEFT(TRIM(MID(SUBSTITUTE($R5,";",REPT(" ",99)),595,99)),FIND(":",TRIM(MID(SUBSTITUTE($R5,";",REPT(" ",99)),595,99)))-1),Materiales!$A$2:$E$502,5,FALSE)*VALUE(MID(TRIM(MID(SUBSTITUTE($R5,";",REPT(" ",99)),595,99)),FIND(":",TRIM(MID(SUBSTITUTE($R5,";",REPT(" ",99)),595,99)))+1,99)),0) + IFERROR(VLOOKUP(LEFT(TRIM(MID(SUBSTITUTE($R5,";",REPT(" ",99)),694,99)),FIND(":",TRIM(MID(SUBSTITUTE($R5,";",REPT(" ",99)),694,99)))-1),Materiales!$A$2:$E$502,5,FALSE)*VALUE(MID(TRIM(MID(SUBSTITUTE($R5,";",REPT(" ",99)),694,99)),FIND(":",TRIM(MID(SUBSTITUTE($R5,";",REPT(" ",99)),694,99)))+1,99)),0) + IFERROR(VLOOKUP(LEFT(TRIM(MID(SUBSTITUTE($R5,";",REPT(" ",99)),793,99)),FIND(":",TRIM(MID(SUBSTITUTE($R5,";",REPT(" ",99)),793,99)))-1),Materiales!$A$2:$E$502,5,FALSE)*VALUE(MID(TRIM(MID(SUBSTITUTE($R5,";",REPT(" ",99)),793,99)),FIND(":",TRIM(MID(SUBSTITUTE($R5,";",REPT(" ",99)),793,99)))+1,99)),0) + IFERROR(VLOOKUP(LEFT(TRIM(MID(SUBSTITUTE($R5,";",REPT(" ",99)),892,99)),FIND(":",TRIM(MID(SUBSTITUTE($R5,";",REPT(" ",99)),892,99)))-1),Materiales!$A$2:$E$502,5,FALSE)*VALUE(MID(TRIM(MID(SUBSTITUTE($R5,";",REPT(" ",99)),892,99)),FIND(":",TRIM(MID(SUBSTITUTE($R5,";",REPT(" ",99)),892,99)))+1,99)),0)))} -> 0 | T5: PINCHO:1;PAPEL_AZUCAR:1 | U5: {=IF($A5="","",IF($T5="",0,IFERROR(VLOOKUP(LEFT(TRIM(MID(SUBSTITUTE($T5,";",REPT(" ",99)),1,99)),FIND(":",TRIM(MID(SUBSTITUTE($T5,";",REPT(" ",99)),1,99)))-1),Materiales!$A$2:$E$502,5,FALSE)*VALUE(MID(TRIM(MID(SUBSTITUTE($T5,";",REPT(" ",99)),1,99)),FIND(":",TRIM(MID(SUBSTITUTE($T5,";",REPT(" ",99)),1,99)))+1,99)),0) + IFERROR(VLOOKUP(LEFT(TRIM(MID(SUBSTITUTE($T5,";",REPT(" ",99)),100,99)),FIND(":",TRIM(MID(SUBSTITUTE($T5,";",REPT(" ",99)),100,99)))-1),Materiales!$A$2:$E$502,5,FALSE)*VALUE(MID(TRIM(MID(SUBSTITUTE($T5,";",REPT(" ",99)),100,99)),FIND(":",TRIM(MID(SUBSTITUTE($T5,";",REPT(" ",99)),100,99)))+1,99)),0) + IFERROR(VLOOKUP(LEFT(TRIM(MID(SUBSTITUTE($T5,";",REPT(" ",99)),199,99)),FIND(":",TRIM(MID(SUBSTITUTE($T5,";",REPT(" ",99)),199,99)))-1),Materiales!$A$2:$E$502,5,FALSE)*VALUE(MID(TRIM(MID(SUBSTITUTE($T5,";",REPT(" ",99)),199,99)),FIND(":",TRIM(MID(SUBSTITUTE($T5,";",REPT(" ",99)),199,99)))+1,99)),0) + IFERROR(VLOOKUP(LEFT(TRIM(MID(SUBSTITUTE($T5,";",REPT(" ",99)),298,99)),FIND(":",TRIM(MID(SUBSTITUTE($T5,";",REPT(" ",99)),298,99)))-1),Materiales!$A$2:$E$502,5,FALSE)*VALUE(MID(TRIM(MID(SUBSTITUTE($T5,";",REPT(" ",99)),298,99)),FIND(":",TRIM(MID(SUBSTITUTE($T5,";",REPT(" ",99)),298,99)))+1,99)),0) + IFERROR(VLOOKUP(LEFT(TRIM(MID(SUBSTITUTE($T5,";",REPT(" ",99)),397,99)),FIND(":",TRIM(MID(SUBSTITUTE($T5,";",REPT(" ",99)),397,99)))-1),Materiales!$A$2:$E$502,5,FALSE)*VALUE(MID(TRIM(MID(SUBSTITUTE($T5,";",REPT(" ",99)),397,99)),FIND(":",TRIM(MID(SUBSTITUTE($T5,";",REPT(" ",99)),397,99)))+1,99)),0) + IFERROR(VLOOKUP(LEFT(TRIM(MID(SUBSTITUTE($T5,";",REPT(" ",99)),496,99)),FIND(":",TRIM(MID(SUBSTITUTE($T5,";",REPT(" ",99)),496,99)))-1),Materiales!$A$2:$E$502,5,FALSE)*VALUE(MID(TRIM(MID(SUBSTITUTE($T5,";",REPT(" ",99)),496,99)),FIND(":",TRIM(MID(SUBSTITUTE($T5,";",REPT(" ",99)),496,99)))+1,99)),0) + IFERROR(VLOOKUP(LEFT(TRIM(MID(SUBSTITUTE($T5,";",REPT(" ",99)),595,99)),FIND(":",TRIM(MID(SUBSTITUTE($T5,";",REPT(" ",99)),595,99)))-1),Materiales!$A$2:$E$502,5,FALSE)*VALUE(MID(TRIM(MID(SUBSTITUTE($T5,";",REPT(" ",99)),595,99)),FIND(":",TRIM(MID(SUBSTITUTE($T5,";",REPT(" ",99)),595,99)))+1,99)),0) + IFERROR(VLOOKUP(LEFT(TRIM(MID(SUBSTITUTE($T5,";",REPT(" ",99)),694,99)),FIND(":",TRIM(MID(SUBSTITUTE($T5,";",REPT(" ",99)),694,99)))-1),Materiales!$A$2:$E$502,5,FALSE)*VALUE(MID(TRIM(MID(SUBSTITUTE($T5,";",REPT(" ",99)),694,99)),FIND(":",TRIM(MID(SUBSTITUTE($T5,";",REPT(" ",99)),694,99)))+1,99)),0) + IFERROR(VLOOKUP(LEFT(TRIM(MID(SUBSTITUTE($T5,";",REPT(" ",99)),793,99)),FIND(":",TRIM(MID(SUBSTITUTE($T5,";",REPT(" ",99)),793,99)))-1),Materiales!$A$2:$E$502,5,FALSE)*VALUE(MID(TRIM(MID(SUBSTITUTE($T5,";",REPT(" ",99)),793,99)),FIND(":",TRIM(MID(SUBSTITUTE($T5,";",REPT(" ",99)),793,99)))+1,99)),0) + IFERROR(VLOOKUP(LEFT(TRIM(MID(SUBSTITUTE($T5,";",REPT(" ",99)),892,99)),FIND(":",TRIM(MID(SUBSTITUTE($T5,";",REPT(" ",99)),892,99)))-1),Materiales!$A$2:$E$502,5,FALSE)*VALUE(MID(TRIM(MID(SUBSTITUTE($T5,";",REPT(" ",99)),892,99)),FIND(":",TRIM(MID(SUBSTITUTE($T5,";",REPT(" ",99)),892,99)))+1,99)),0)))} -> 330 | W5: {=IF($A5="","",IF($V5="",0,IFERROR(VLOOKUP(LEFT(TRIM(MID(SUBSTITUTE($V5,";",REPT(" ",99)),1,99)),FIND(":",TRIM(MID(SUBSTITUTE($V5,";",REPT(" ",99)),1,99)))-1),Materiales!$A$2:$E$502,5,FALSE)*VALUE(MID(TRIM(MID(SUBSTITUTE($V5,";",REPT(" ",99)),1,99)),FIND(":",TRIM(MID(SUBSTITUTE($V5,";",REPT(" ",99)),1,99)))+1,99)),0) + IFERROR(VLOOKUP(LEFT(TRIM(MID(SUBSTITUTE($V5,";",REPT(" ",99)),100,99)),FIND(":",TRIM(MID(SUBSTITUTE($V5,";",REPT(" ",99)),100,99)))-1),Materiales!$A$2:$E$502,5,FALSE)*VALUE(MID(TRIM(MID(SUBSTITUTE($V5,";",REPT(" ",99)),100,99)),FIND(":",TRIM(MID(SUBSTITUTE($V5,";",REPT(" ",99)),100,99)))+1,99)),0) + IFERROR(VLOOKUP(LEFT(TRIM(MID(SUBSTITUTE($V5,";",REPT(" ",99)),199,99)),FIND(":",TRIM(MID(SUBSTITUTE($V5,";",REPT(" ",99)),199,99)))-1),Materiales!$A$2:$E$502,5,FALSE)*VALUE(MID(TRIM(MID(SUBSTITUTE($V5,";",REPT(" ",99)),199,99)),FIND(":",TRIM(MID(SUBSTITUTE($V5,";",REPT(" ",99)),199,99)))+1,99)),0) + IFERROR(VLOOKUP(LEFT(TRIM(MID(SUBSTITUTE($V5,";",REPT(" ",99)),298,99)),FIND(":",TRIM(MID(SUBSTITUTE($V5,";",REPT(" ",99)),298,99)))-1),Materiales!$A$2:$E$502,5,FALSE)*VALUE(MID(TRIM(MID(SUBSTITUTE($V5,";",REPT(" ",99)),298,99)),FIND(":",TRIM(MID(SUBSTITUTE($V5,";",REPT(" ",99)),298,99)))+1,99)),0) + IFERROR(VLOOKUP(LEFT(TRIM(MID(SUBSTITUTE($V5,";",REPT(" ",99)),397,99)),FIND(":",TRIM(MID(SUBSTITUTE($V5,";",REPT(" ",99)),397,99)))-1),Materiales!$A$2:$E$502,5,FALSE)*VALUE(MID(TRIM(MID(SUBSTITUTE($V5,";",REPT(" ",99)),397,99)),FIND(":",TRIM(MID(SUBSTITUTE($V5,";",REPT(" ",99)),397,99)))+1,99)),0) + IFERROR(VLOOKUP(LEFT(TRIM(MID(SUBSTITUTE($V5,";",REPT(" ",99)),496,99)),FIND(":",TRIM(MID(SUBSTITUTE($V5,";",REPT(" ",99)),496,99)))-1),Materiales!$A$2:$E$502,5,FALSE)*VALUE(MID(TRIM(MID(SUBSTITUTE($V5,";",REPT(" ",99)),496,99)),FIND(":",TRIM(MID(SUBSTITUTE($V5,";",REPT(" ",99)),496,99)))+1,99)),0) + IFERROR(VLOOKUP(LEFT(TRIM(MID(SUBSTITUTE($V5,";",REPT(" ",99)),595,99)),FIND(":",TRIM(MID(SUBSTITUTE($V5,";",REPT(" ",99)),595,99)))-1),Materiales!$A$2:$E$502,5,FALSE)*VALUE(MID(TRIM(MID(SUBSTITUTE($V5,";",REPT(" ",99)),595,99)),FIND(":",TRIM(MID(SUBSTITUTE($V5,";",REPT(" ",99)),595,99)))+1,99)),0) + IFERROR(VLOOKUP(LEFT(TRIM(MID(SUBSTITUTE($V5,";",REPT(" ",99)),694,99)),FIND(":",TRIM(MID(SUBSTITUTE($V5,";",REPT(" ",99)),694,99)))-1),Materiales!$A$2:$E$502,5,FALSE)*VALUE(MID(TRIM(MID(SUBSTITUTE($V5,";",REPT(" ",99)),694,99)),FIND(":",TRIM(MID(SUBSTITUTE($V5,";",REPT(" ",99)),694,99)))+1,99)),0) + IFERROR(VLOOKUP(LEFT(TRIM(MID(SUBSTITUTE($V5,";",REPT(" ",99)),793,99)),FIND(":",TRIM(MID(SUBSTITUTE($V5,";",REPT(" ",99)),793,99)))-1),Materiales!$A$2:$E$502,5,FALSE)*VALUE(MID(TRIM(MID(SUBSTITUTE($V5,";",REPT(" ",99)),793,99)),FIND(":",TRIM(MID(SUBSTITUTE($V5,";",REPT(" ",99)),793,99)))+1,99)),0) + IFERROR(VLOOKUP(LEFT(TRIM(MID(SUBSTITUTE($V5,";",REPT(" ",99)),892,99)),FIND(":",TRIM(MID(SUBSTITUTE($V5,";",REPT(" ",99)),892,99)))-1),Materiales!$A$2:$E$502,5,FALSE)*VALUE(MID(TRIM(MID(SUBSTITUTE($V5,";",REPT(" ",99)),892,99)),FIND(":",TRIM(MID(SUBSTITUTE($V5,";",REPT(" ",99)),892,99)))+1,99)),0)))} -> 0 | X5: =IF($A5="","",SUM($G5,$H5,$K5,$N5,$Q5,$S5,$U5,$W5)) -> 1206.1668 | Y5: 3 | Z5: =X5*Y5 -> 3618.5005 | AA5: 0 | AB5: =AA5+Z5 -> 3618.5005 | AC5: 3500 | AD5: =AB5-X5 -> 2412.3337 | AE5: =AC5-X5 -> 2293.8332 | AF5: =AE5/AD5 -> 0.95087722
A6: Vela Margarita en TUL | B6: CERA_MOLDE | C6: 1 | F6: 22 | G6: {=IF($A6="","",IFERROR($F6*(N($C6)*XLOOKUP($B6,Ceras!$A$2:$A$500,Ceras!$G$2:$G$500,0)+IF($D6="",0,N($E6)*XLOOKUP($D6,Ceras!$A$2:$A$500,Ceras!$G$2:$G$500,0))),"Revisar cera"))} -> 396 | H6: =F6*1.5 -> 33 | I6: PABILO2-4 | J6: 3 | K6: {=IF($A6="","",IFERROR($J6*XLOOKUP($I6,Pabilos!$A$2:$A$500,Pabilos!$H$2:$H$500,0),"Revisar pabilo"))} -> 45 | L6: ES_BEDOYA | M6: =F6/10 -> 2.2 | N6: {=IF($A6="","",IFERROR($M6*XLOOKUP($L6,Esencias!$A$2:$A$501,Esencias!$G$2:$G$501,0),"Revisar esencia"))} -> 309.85915 | O6: COLOR_CAFE | P6: 1 | Q6: {=IF($A6="","",IFERROR(IF($P6="",1,$P6)*XLOOKUP($O6,Colores!$A$2:$A$500,Colores!$H$2:$H$500,0),"Revisar color"))} -> 92.307692 | S6: {=IF($A6="","",IF($R6="",0,IFERROR(VLOOKUP(LEFT(TRIM(MID(SUBSTITUTE($R6,";",REPT(" ",99)),1,99)),FIND(":",TRIM(MID(SUBSTITUTE($R6,";",REPT(" ",99)),1,99)))-1),Materiales!$A$2:$E$502,5,FALSE)*VALUE(MID(TRIM(MID(SUBSTITUTE($R6,";",REPT(" ",99)),1,99)),FIND(":",TRIM(MID(SUBSTITUTE($R6,";",REPT(" ",99)),1,99)))+1,99)),0) + IFERROR(VLOOKUP(LEFT(TRIM(MID(SUBSTITUTE($R6,";",REPT(" ",99)),100,99)),FIND(":",TRIM(MID(SUBSTITUTE($R6,";",REPT(" ",99)),100,99)))-1),Materiales!$A$2:$E$502,5,FALSE)*VALUE(MID(TRIM(MID(SUBSTITUTE($R6,";",REPT(" ",99)),100,99)),FIND(":",TRIM(MID(SUBSTITUTE($R6,";",REPT(" ",99)),100,99)))+1,99)),0) + IFERROR(VLOOKUP(LEFT(TRIM(MID(SUBSTITUTE($R6,";",REPT(" ",99)),199,99)),FIND(":",TRIM(MID(SUBSTITUTE($R6,";",REPT(" ",99)),199,99)))-1),Materiales!$A$2:$E$502,5,FALSE)*VALUE(MID(TRIM(MID(SUBSTITUTE($R6,";",REPT(" ",99)),199,99)),FIND(":",TRIM(MID(SUBSTITUTE($R6,";",REPT(" ",99)),199,99)))+1,99)),0) + IFERROR(VLOOKUP(LEFT(TRIM(MID(SUBSTITUTE($R6,";",REPT(" ",99)),298,99)),FIND(":",TRIM(MID(SUBSTITUTE($R6,";",REPT(" ",99)),298,99)))-1),Materiales!$A$2:$E$502,5,FALSE)*VALUE(MID(TRIM(MID(SUBSTITUTE($R6,";",REPT(" ",99)),298,99)),FIND(":",TRIM(MID(SUBSTITUTE($R6,";",REPT(" ",99)),298,99)))+1,99)),0) + IFERROR(VLOOKUP(LEFT(TRIM(MID(SUBSTITUTE($R6,";",REPT(" ",99)),397,99)),FIND(":",TRIM(MID(SUBSTITUTE($R6,";",REPT(" ",99)),397,99)))-1),Materiales!$A$2:$E$502,5,FALSE)*VALUE(MID(TRIM(MID(SUBSTITUTE($R6,";",REPT(" ",99)),397,99)),FIND(":",TRIM(MID(SUBSTITUTE($R6,";",REPT(" ",99)),397,99)))+1,99)),0) + IFERROR(VLOOKUP(LEFT(TRIM(MID(SUBSTITUTE($R6,";",REPT(" ",99)),496,99)),FIND(":",TRIM(MID(SUBSTITUTE($R6,";",REPT(" ",99)),496,99)))-1),Materiales!$A$2:$E$502,5,FALSE)*VALUE(MID(TRIM(MID(SUBSTITUTE($R6,";",REPT(" ",99)),496,99)),FIND(":",TRIM(MID(SUBSTITUTE($R6,";",REPT(" ",99)),496,99)))+1,99)),0) + IFERROR(VLOOKUP(LEFT(TRIM(MID(SUBSTITUTE($R6,";",REPT(" ",99)),595,99)),FIND(":",TRIM(MID(SUBSTITUTE($R6,";",REPT(" ",99)),595,99)))-1),Materiales!$A$2:$E$502,5,FALSE)*VALUE(MID(TRIM(MID(SUBSTITUTE($R6,";",REPT(" ",99)),595,99)),FIND(":",TRIM(MID(SUBSTITUTE($R6,";",REPT(" ",99)),595,99)))+1,99)),0) + IFERROR(VLOOKUP(LEFT(TRIM(MID(SUBSTITUTE($R6,";",REPT(" ",99)),694,99)),FIND(":",TRIM(MID(SUBSTITUTE($R6,";",REPT(" ",99)),694,99)))-1),Materiales!$A$2:$E$502,5,FALSE)*VALUE(MID(TRIM(MID(SUBSTITUTE($R6,";",REPT(" ",99)),694,99)),FIND(":",TRIM(MID(SUBSTITUTE($R6,";",REPT(" ",99)),694,99)))+1,99)),0) + IFERROR(VLOOKUP(LEFT(TRIM(MID(SUBSTITUTE($R6,";",REPT(" ",99)),793,99)),FIND(":",TRIM(MID(SUBSTITUTE($R6,";",REPT(" ",99)),793,99)))-1),Materiales!$A$2:$E$502,5,FALSE)*VALUE(MID(TRIM(MID(SUBSTITUTE($R6,";",REPT(" ",99)),793,99)),FIND(":",TRIM(MID(SUBSTITUTE($R6,";",REPT(" ",99)),793,99)))+1,99)),0) + IFERROR(VLOOKUP(LEFT(TRIM(MID(SUBSTITUTE($R6,";",REPT(" ",99)),892,99)),FIND(":",TRIM(MID(SUBSTITUTE($R6,";",REPT(" ",99)),892,99)))-1),Materiales!$A$2:$E$502,5,FALSE)*VALUE(MID(TRIM(MID(SUBSTITUTE($R6,";",REPT(" ",99)),892,99)),FIND(":",TRIM(MID(SUBSTITUTE($R6,";",REPT(" ",99)),892,99)))+1,99)),0)))} -> 0 | T6: TUL:1;CINTA:25;FOSFO:1;STICKER :0 | U6: {=IF($A6="","",IF($T6="",0,IFERROR(VLOOKUP(LEFT(TRIM(MID(SUBSTITUTE($T6,";",REPT(" ",99)),1,99)),FIND(":",TRIM(MID(SUBSTITUTE($T6,";",REPT(" ",99)),1,99)))-1),Materiales!$A$2:$E$502,5,FALSE)*VALUE(MID(TRIM(MID(SUBSTITUTE($T6,";",REPT(" ",99)),1,99)),FIND(":",TRIM(MID(SUBSTITUTE($T6,";",REPT(" ",99)),1,99)))+1,99)),0) + IFERROR(VLOOKUP(LEFT(TRIM(MID(SUBSTITUTE($T6,";",REPT(" ",99)),100,99)),FIND(":",TRIM(MID(SUBSTITUTE($T6,";",REPT(" ",99)),100,99)))-1),Materiales!$A$2:$E$502,5,FALSE)*VALUE(MID(TRIM(MID(SUBSTITUTE($T6,";",REPT(" ",99)),100,99)),FIND(":",TRIM(MID(SUBSTITUTE($T6,";",REPT(" ",99)),100,99)))+1,99)),0) + IFERROR(VLOOKUP(LEFT(TRIM(MID(SUBSTITUTE($T6,";",REPT(" ",99)),199,99)),FIND(":",TRIM(MID(SUBSTITUTE($T6,";",REPT(" ",99)),199,99)))-1),Materiales!$A$2:$E$502,5,FALSE)*VALUE(MID(TRIM(MID(SUBSTITUTE($T6,";",REPT(" ",99)),199,99)),FIND(":",TRIM(MID(SUBSTITUTE($T6,";",REPT(" ",99)),199,99)))+1,99)),0) + IFERROR(VLOOKUP(LEFT(TRIM(MID(SUBSTITUTE($T6,";",REPT(" ",99)),298,99)),FIND(":",TRIM(MID(SUBSTITUTE($T6,";",REPT(" ",99)),298,99)))-1),Materiales!$A$2:$E$502,5,FALSE)*VALUE(MID(TRIM(MID(SUBSTITUTE($T6,";",REPT(" ",99)),298,99)),FIND(":",TRIM(MID(SUBSTITUTE($T6,";",REPT(" ",99)),298,99)))+1,99)),0) + IFERROR(VLOOKUP(LEFT(TRIM(MID(SUBSTITUTE($T6,";",REPT(" ",99)),397,99)),FIND(":",TRIM(MID(SUBSTITUTE($T6,";",REPT(" ",99)),397,99)))-1),Materiales!$A$2:$E$502,5,FALSE)*VALUE(MID(TRIM(MID(SUBSTITUTE($T6,";",REPT(" ",99)),397,99)),FIND(":",TRIM(MID(SUBSTITUTE($T6,";",REPT(" ",99)),397,99)))+1,99)),0) + IFERROR(VLOOKUP(LEFT(TRIM(MID(SUBSTITUTE($T6,";",REPT(" ",99)),496,99)),FIND(":",TRIM(MID(SUBSTITUTE($T6,";",REPT(" ",99)),496,99)))-1),Materiales!$A$2:$E$502,5,FALSE)*VALUE(MID(TRIM(MID(SUBSTITUTE($T6,";",REPT(" ",99)),496,99)),FIND(":",TRIM(MID(SUBSTITUTE($T6,";",REPT(" ",99)),496,99)))+1,99)),0) + IFERROR(VLOOKUP(LEFT(TRIM(MID(SUBSTITUTE($T6,";",REPT(" ",99)),595,99)),FIND(":",TRIM(MID(SUBSTITUTE($T6,";",REPT(" ",99)),595,99)))-1),Materiales!$A$2:$E$502,5,FALSE)*VALUE(MID(TRIM(MID(SUBSTITUTE($T6,";",REPT(" ",99)),595,99)),FIND(":",TRIM(MID(SUBSTITUTE($T6,";",REPT(" ",99)),595,99)))+1,99)),0) + IFERROR(VLOOKUP(LEFT(TRIM(MID(SUBSTITUTE($T6,";",REPT(" ",99)),694,99)),FIND(":",TRIM(MID(SUBSTITUTE($T6,";",REPT(" ",99)),694,99)))-1),Materiales!$A$2:$E$502,5,FALSE)*VALUE(MID(TRIM(MID(SUBSTITUTE($T6,";",REPT(" ",99)),694,99)),FIND(":",TRIM(MID(SUBSTITUTE($T6,";",REPT(" ",99)),694,99)))+1,99)),0) + IFERROR(VLOOKUP(LEFT(TRIM(MID(SUBSTITUTE($T6,";",REPT(" ",99)),793,99)),FIND(":",TRIM(MID(SUBSTITUTE($T6,";",REPT(" ",99)),793,99)))-1),Materiales!$A$2:$E$502,5,FALSE)*VALUE(MID(TRIM(MID(SUBSTITUTE($T6,";",REPT(" ",99)),793,99)),FIND(":",TRIM(MID(SUBSTITUTE($T6,";",REPT(" ",99)),793,99)))+1,99)),0) + IFERROR(VLOOKUP(LEFT(TRIM(MID(SUBSTITUTE($T6,";",REPT(" ",99)),892,99)),FIND(":",TRIM(MID(SUBSTITUTE($T6,";",REPT(" ",99)),892,99)))-1),Materiales!$A$2:$E$502,5,FALSE)*VALUE(MID(TRIM(MID(SUBSTITUTE($T6,";",REPT(" ",99)),892,99)),FIND(":",TRIM(MID(SUBSTITUTE($T6,";",REPT(" ",99)),892,99)))+1,99)),0)))} -> 605 | W6: {=IF($A6="","",IF($V6="",0,IFERROR(VLOOKUP(LEFT(TRIM(MID(SUBSTITUTE($V6,";",REPT(" ",99)),1,99)),FIND(":",TRIM(MID(SUBSTITUTE($V6,";",REPT(" ",99)),1,99)))-1),Materiales!$A$2:$E$502,5,FALSE)*VALUE(MID(TRIM(MID(SUBSTITUTE($V6,";",REPT(" ",99)),1,99)),FIND(":",TRIM(MID(SUBSTITUTE($V6,";",REPT(" ",99)),1,99)))+1,99)),0) + IFERROR(VLOOKUP(LEFT(TRIM(MID(SUBSTITUTE($V6,";",REPT(" ",99)),100,99)),FIND(":",TRIM(MID(SUBSTITUTE($V6,";",REPT(" ",99)),100,99)))-1),Materiales!$A$2:$E$502,5,FALSE)*VALUE(MID(TRIM(MID(SUBSTITUTE($V6,";",REPT(" ",99)),100,99)),FIND(":",TRIM(MID(SUBSTITUTE($V6,";",REPT(" ",99)),100,99)))+1,99)),0) + IFERROR(VLOOKUP(LEFT(TRIM(MID(SUBSTITUTE($V6,";",REPT(" ",99)),199,99)),FIND(":",TRIM(MID(SUBSTITUTE($V6,";",REPT(" ",99)),199,99)))-1),Materiales!$A$2:$E$502,5,FALSE)*VALUE(MID(TRIM(MID(SUBSTITUTE($V6,";",REPT(" ",99)),199,99)),FIND(":",TRIM(MID(SUBSTITUTE($V6,";",REPT(" ",99)),199,99)))+1,99)),0) + IFERROR(VLOOKUP(LEFT(TRIM(MID(SUBSTITUTE($V6,";",REPT(" ",99)),298,99)),FIND(":",TRIM(MID(SUBSTITUTE($V6,";",REPT(" ",99)),298,99)))-1),Materiales!$A$2:$E$502,5,FALSE)*VALUE(MID(TRIM(MID(SUBSTITUTE($V6,";",REPT(" ",99)),298,99)),FIND(":",TRIM(MID(SUBSTITUTE($V6,";",REPT(" ",99)),298,99)))+1,99)),0) + IFERROR(VLOOKUP(LEFT(TRIM(MID(SUBSTITUTE($V6,";",REPT(" ",99)),397,99)),FIND(":",TRIM(MID(SUBSTITUTE($V6,";",REPT(" ",99)),397,99)))-1),Materiales!$A$2:$E$502,5,FALSE)*VALUE(MID(TRIM(MID(SUBSTITUTE($V6,";",REPT(" ",99)),397,99)),FIND(":",TRIM(MID(SUBSTITUTE($V6,";",REPT(" ",99)),397,99)))+1,99)),0) + IFERROR(VLOOKUP(LEFT(TRIM(MID(SUBSTITUTE($V6,";",REPT(" ",99)),496,99)),FIND(":",TRIM(MID(SUBSTITUTE($V6,";",REPT(" ",99)),496,99)))-1),Materiales!$A$2:$E$502,5,FALSE)*VALUE(MID(TRIM(MID(SUBSTITUTE($V6,";",REPT(" ",99)),496,99)),FIND(":",TRIM(MID(SUBSTITUTE($V6,";",REPT(" ",99)),496,99)))+1,99)),0) + IFERROR(VLOOKUP(LEFT(TRIM(MID(SUBSTITUTE($V6,";",REPT(" ",99)),595,99)),FIND(":",TRIM(MID(SUBSTITUTE($V6,";",REPT(" ",99)),595,99)))-1),Materiales!$A$2:$E$502,5,FALSE)*VALUE(MID(TRIM(MID(SUBSTITUTE($V6,";",REPT(" ",99)),595,99)),FIND(":",TRIM(MID(SUBSTITUTE($V6,";",REPT(" ",99)),595,99)))+1,99)),0) + IFERROR(VLOOKUP(LEFT(TRIM(MID(SUBSTITUTE($V6,";",REPT(" ",99)),694,99)),FIND(":",TRIM(MID(SUBSTITUTE($V6,";",REPT(" ",99)),694,99)))-1),Materiales!$A$2:$E$502,5,FALSE)*VALUE(MID(TRIM(MID(SUBSTITUTE($V6,";",REPT(" ",99)),694,99)),FIND(":",TRIM(MID(SUBSTITUTE($V6,";",REPT(" ",99)),694,99)))+1,99)),0) + IFERROR(VLOOKUP(LEFT(TRIM(MID(SUBSTITUTE($V6,";",REPT(" ",99)),793,99)),FIND(":",TRIM(MID(SUBSTITUTE($V6,";",REPT(" ",99)),793,99)))-1),Materiales!$A$2:$E$502,5,FALSE)*VALUE(MID(TRIM(MID(SUBSTITUTE($V6,";",REPT(" ",99)),793,99)),FIND(":",TRIM(MID(SUBSTITUTE($V6,";",REPT(" ",99)),793,99)))+1,99)),0) + IFERROR(VLOOKUP(LEFT(TRIM(MID(SUBSTITUTE($V6,";",REPT(" ",99)),892,99)),FIND(":",TRIM(MID(SUBSTITUTE($V6,";",REPT(" ",99)),892,99)))-1),Materiales!$A$2:$E$502,5,FALSE)*VALUE(MID(TRIM(MID(SUBSTITUTE($V6,";",REPT(" ",99)),892,99)),FIND(":",TRIM(MID(SUBSTITUTE($V6,";",REPT(" ",99)),892,99)))+1,99)),0)))} -> 0 | X6: =IF($A6="","",SUM($G6,$H6,$K6,$N6,$Q6,$S6,$U6,$W6)) -> 1481.1668 | Y6: 3 | Z6: =X6*Y6 -> 4443.5005 | AA6: 0 | AB6: =AA6+Z6 -> 4443.5005 | AC6: 4000 | AD6: =AB6-X6 -> 2962.3337 | AE6: =AC6-X6 -> 2518.8332 | AF6: =AE6/AD6 -> 0.85028677
A7: Velon corto con cara de rosas mediano | B7: CERA_MOLDE | C7: 1 | F7: 43 | G7: {=IF($A7="","",IFERROR($F7*(N($C7)*XLOOKUP($B7,Ceras!$A$2:$A$500,Ceras!$G$2:$G$500,0)+IF($D7="",0,N($E7)*XLOOKUP($D7,Ceras!$A$2:$A$500,Ceras!$G$2:$G$500,0))),"Revisar cera"))} -> 774 | H7: =F7*1.5 -> 64.5 | I7: PABILO4-6 | J7: 4 | K7: {=IF($A7="","",IFERROR($J7*XLOOKUP($I7,Pabilos!$A$2:$A$500,Pabilos!$H$2:$H$500,0),"Revisar pabilo"))} -> 72 | L7: ES_BEDOYA | M7: =F7*0.1 -> 4.3 | N7: {=IF($A7="","",IFERROR($M7*XLOOKUP($L7,Esencias!$A$2:$A$501,Esencias!$G$2:$G$501,0),"Revisar esencia"))} -> 605.6338 | O7: COLOR_CAFE | P7: 1 | Q7: {=IF($A7="","",IFERROR(IF($P7="",1,$P7)*XLOOKUP($O7,Colores!$A$2:$A$500,Colores!$H$2:$H$500,0),"Revisar color"))} -> 92.307692 | S7: {=IF($A7="","",IF($R7="",0,IFERROR(VLOOKUP(LEFT(TRIM(MID(SUBSTITUTE($R7,";",REPT(" ",99)),1,99)),FIND(":",TRIM(MID(SUBSTITUTE($R7,";",REPT(" ",99)),1,99)))-1),Materiales!$A$2:$E$502,5,FALSE)*VALUE(MID(TRIM(MID(SUBSTITUTE($R7,";",REPT(" ",99)),1,99)),FIND(":",TRIM(MID(SUBSTITUTE($R7,";",REPT(" ",99)),1,99)))+1,99)),0) + IFERROR(VLOOKUP(LEFT(TRIM(MID(SUBSTITUTE($R7,";",REPT(" ",99)),100,99)),FIND(":",TRIM(MID(SUBSTITUTE($R7,";",REPT(" ",99)),100,99)))-1),Materiales!$A$2:$E$502,5,FALSE)*VALUE(MID(TRIM(MID(SUBSTITUTE($R7,";",REPT(" ",99)),100,99)),FIND(":",TRIM(MID(SUBSTITUTE($R7,";",REPT(" ",99)),100,99)))+1,99)),0) + IFERROR(VLOOKUP(LEFT(TRIM(MID(SUBSTITUTE($R7,";",REPT(" ",99)),199,99)),FIND(":",TRIM(MID(SUBSTITUTE($R7,";",REPT(" ",99)),199,99)))-1),Materiales!$A$2:$E$502,5,FALSE)*VALUE(MID(TRIM(MID(SUBSTITUTE($R7,";",REPT(" ",99)),199,99)),FIND(":",TRIM(MID(SUBSTITUTE($R7,";",REPT(" ",99)),199,99)))+1,99)),0) + IFERROR(VLOOKUP(LEFT(TRIM(MID(SUBSTITUTE($R7,";",REPT(" ",99)),298,99)),FIND(":",TRIM(MID(SUBSTITUTE($R7,";",REPT(" ",99)),298,99)))-1),Materiales!$A$2:$E$502,5,FALSE)*VALUE(MID(TRIM(MID(SUBSTITUTE($R7,";",REPT(" ",99)),298,99)),FIND(":",TRIM(MID(SUBSTITUTE($R7,";",REPT(" ",99)),298,99)))+1,99)),0) + IFERROR(VLOOKUP(LEFT(TRIM(MID(SUBSTITUTE($R7,";",REPT(" ",99)),397,99)),FIND(":",TRIM(MID(SUBSTITUTE($R7,";",REPT(" ",99)),397,99)))-1),Materiales!$A$2:$E$502,5,FALSE)*VALUE(MID(TRIM(MID(SUBSTITUTE($R7,";",REPT(" ",99)),397,99)),FIND(":",TRIM(MID(SUBSTITUTE($R7,";",REPT(" ",99)),397,99)))+1,99)),0) + IFERROR(VLOOKUP(LEFT(TRIM(MID(SUBSTITUTE($R7,";",REPT(" ",99)),496,99)),FIND(":",TRIM(MID(SUBSTITUTE($R7,";",REPT(" ",99)),496,99)))-1),Materiales!$A$2:$E$502,5,FALSE)*VALUE(MID(TRIM(MID(SUBSTITUTE($R7,";",REPT(" ",99)),496,99)),FIND(":",TRIM(MID(SUBSTITUTE($R7,";",REPT(" ",99)),496,99)))+1,99)),0) + IFERROR(VLOOKUP(LEFT(TRIM(MID(SUBSTITUTE($R7,";",REPT(" ",99)),595,99)),FIND(":",TRIM(MID(SUBSTITUTE($R7,";",REPT(" ",99)),595,99)))-1),Materiales!$A$2:$E$502,5,FALSE)*VALUE(MID(TRIM(MID(SUBSTITUTE($R7,";",REPT(" ",99)),595,99)),FIND(":",TRIM(MID(SUBSTITUTE($R7,";",REPT(" ",99)),595,99)))+1,99)),0) + IFERROR(VLOOKUP(LEFT(TRIM(MID(SUBSTITUTE($R7,";",REPT(" ",99)),694,99)),FIND(":",TRIM(MID(SUBSTITUTE($R7,";",REPT(" ",99)),694,99)))-1),Materiales!$A$2:$E$502,5,FALSE)*VALUE(MID(TRIM(MID(SUBSTITUTE($R7,";",REPT(" ",99)),694,99)),FIND(":",TRIM(MID(SUBSTITUTE($R7,";",REPT(" ",99)),694,99)))+1,99)),0) + IFERROR(VLOOKUP(LEFT(TRIM(MID(SUBSTITUTE($R7,";",REPT(" ",99)),793,99)),FIND(":",TRIM(MID(SUBSTITUTE($R7,";",REPT(" ",99)),793,99)))-1),Materiales!$A$2:$E$502,5,FALSE)*VALUE(MID(TRIM(MID(SUBSTITUTE($R7,";",REPT(" ",99)),793,99)),FIND(":",TRIM(MID(SUBSTITUTE($R7,";",REPT(" ",99)),793,99)))+1,99)),0) + IFERROR(VLOOKUP(LEFT(TRIM(MID(SUBSTITUTE($R7,";",REPT(" ",99)),892,99)),FIND(":",TRIM(MID(SUBSTITUTE($R7,";",REPT(" ",99)),892,99)))-1),Materiales!$A$2:$E$502,5,FALSE)*VALUE(MID(TRIM(MID(SUBSTITUTE($R7,";",REPT(" ",99)),892,99)),FIND(":",TRIM(MID(SUBSTITUTE($R7,";",REPT(" ",99)),892,99)))+1,99)),0)))} -> 0 | U7: {=IF($A7="","",IF($T7="",0,IFERROR(VLOOKUP(LEFT(TRIM(MID(SUBSTITUTE($T7,";",REPT(" ",99)),1,99)),FIND(":",TRIM(MID(SUBSTITUTE($T7,";",REPT(" ",99)),1,99)))-1),Materiales!$A$2:$E$502,5,FALSE)*VALUE(MID(TRIM(MID(SUBSTITUTE($T7,";",REPT(" ",99)),1,99)),FIND(":",TRIM(MID(SUBSTITUTE($T7,";",REPT(" ",99)),1,99)))+1,99)),0) + IFERROR(VLOOKUP(LEFT(TRIM(MID(SUBSTITUTE($T7,";",REPT(" ",99)),100,99)),FIND(":",TRIM(MID(SUBSTITUTE($T7,";",REPT(" ",99)),100,99)))-1),Materiales!$A$2:$E$502,5,FALSE)*VALUE(MID(TRIM(MID(SUBSTITUTE($T7,";",REPT(" ",99)),100,99)),FIND(":",TRIM(MID(SUBSTITUTE($T7,";",REPT(" ",99)),100,99)))+1,99)),0) + IFERROR(VLOOKUP(LEFT(TRIM(MID(SUBSTITUTE($T7,";",REPT(" ",99)),199,99)),FIND(":",TRIM(MID(SUBSTITUTE($T7,";",REPT(" ",99)),199,99)))-1),Materiales!$A$2:$E$502,5,FALSE)*VALUE(MID(TRIM(MID(SUBSTITUTE($T7,";",REPT(" ",99)),199,99)),FIND(":",TRIM(MID(SUBSTITUTE($T7,";",REPT(" ",99)),199,99)))+1,99)),0) + IFERROR(VLOOKUP(LEFT(TRIM(MID(SUBSTITUTE($T7,";",REPT(" ",99)),298,99)),FIND(":",TRIM(MID(SUBSTITUTE($T7,";",REPT(" ",99)),298,99)))-1),Materiales!$A$2:$E$502,5,FALSE)*VALUE(MID(TRIM(MID(SUBSTITUTE($T7,";",REPT(" ",99)),298,99)),FIND(":",TRIM(MID(SUBSTITUTE($T7,";",REPT(" ",99)),298,99)))+1,99)),0) + IFERROR(VLOOKUP(LEFT(TRIM(MID(SUBSTITUTE($T7,";",REPT(" ",99)),397,99)),FIND(":",TRIM(MID(SUBSTITUTE($T7,";",REPT(" ",99)),397,99)))-1),Materiales!$A$2:$E$502,5,FALSE)*VALUE(MID(TRIM(MID(SUBSTITUTE($T7,";",REPT(" ",99)),397,99)),FIND(":",TRIM(MID(SUBSTITUTE($T7,";",REPT(" ",99)),397,99)))+1,99)),0) + IFERROR(VLOOKUP(LEFT(TRIM(MID(SUBSTITUTE($T7,";",REPT(" ",99)),496,99)),FIND(":",TRIM(MID(SUBSTITUTE($T7,";",REPT(" ",99)),496,99)))-1),Materiales!$A$2:$E$502,5,FALSE)*VALUE(MID(TRIM(MID(SUBSTITUTE($T7,";",REPT(" ",99)),496,99)),FIND(":",TRIM(MID(SUBSTITUTE($T7,";",REPT(" ",99)),496,99)))+1,99)),0) + IFERROR(VLOOKUP(LEFT(TRIM(MID(SUBSTITUTE($T7,";",REPT(" ",99)),595,99)),FIND(":",TRIM(MID(SUBSTITUTE($T7,";",REPT(" ",99)),595,99)))-1),Materiales!$A$2:$E$502,5,FALSE)*VALUE(MID(TRIM(MID(SUBSTITUTE($T7,";",REPT(" ",99)),595,99)),FIND(":",TRIM(MID(SUBSTITUTE($T7,";",REPT(" ",99)),595,99)))+1,99)),0) + IFERROR(VLOOKUP(LEFT(TRIM(MID(SUBSTITUTE($T7,";",REPT(" ",99)),694,99)),FIND(":",TRIM(MID(SUBSTITUTE($T7,";",REPT(" ",99)),694,99)))-1),Materiales!$A$2:$E$502,5,FALSE)*VALUE(MID(TRIM(MID(SUBSTITUTE($T7,";",REPT(" ",99)),694,99)),FIND(":",TRIM(MID(SUBSTITUTE($T7,";",REPT(" ",99)),694,99)))+1,99)),0) + IFERROR(VLOOKUP(LEFT(TRIM(MID(SUBSTITUTE($T7,";",REPT(" ",99)),793,99)),FIND(":",TRIM(MID(SUBSTITUTE($T7,";",REPT(" ",99)),793,99)))-1),Materiales!$A$2:$E$502,5,FALSE)*VALUE(MID(TRIM(MID(SUBSTITUTE($T7,";",REPT(" ",99)),793,99)),FIND(":",TRIM(MID(SUBSTITUTE($T7,";",REPT(" ",99)),793,99)))+1,99)),0) + IFERROR(VLOOKUP(LEFT(TRIM(MID(SUBSTITUTE($T7,";",REPT(" ",99)),892,99)),FIND(":",TRIM(MID(SUBSTITUTE($T7,";",REPT(" ",99)),892,99)))-1),Materiales!$A$2:$E$502,5,FALSE)*VALUE(MID(TRIM(MID(SUBSTITUTE($T7,";",REPT(" ",99)),892,99)),FIND(":",TRIM(MID(SUBSTITUTE($T7,";",REPT(" ",99)),892,99)))+1,99)),0)))} -> 0 | W7: {=IF($A7="","",IF($V7="",0,IFERROR(VLOOKUP(LEFT(TRIM(MID(SUBSTITUTE($V7,";",REPT(" ",99)),1,99)),FIND(":",TRIM(MID(SUBSTITUTE($V7,";",REPT(" ",99)),1,99)))-1),Materiales!$A$2:$E$502,5,FALSE)*VALUE(MID(TRIM(MID(SUBSTITUTE($V7,";",REPT(" ",99)),1,99)),FIND(":",TRIM(MID(SUBSTITUTE($V7,";",REPT(" ",99)),1,99)))+1,99)),0) + IFERROR(VLOOKUP(LEFT(TRIM(MID(SUBSTITUTE($V7,";",REPT(" ",99)),100,99)),FIND(":",TRIM(MID(SUBSTITUTE($V7,";",REPT(" ",99)),100,99)))-1),Materiales!$A$2:$E$502,5,FALSE)*VALUE(MID(TRIM(MID(SUBSTITUTE($V7,";",REPT(" ",99)),100,99)),FIND(":",TRIM(MID(SUBSTITUTE($V7,";",REPT(" ",99)),100,99)))+1,99)),0) + IFERROR(VLOOKUP(LEFT(TRIM(MID(SUBSTITUTE($V7,";",REPT(" ",99)),199,99)),FIND(":",TRIM(MID(SUBSTITUTE($V7,";",REPT(" ",99)),199,99)))-1),Materiales!$A$2:$E$502,5,FALSE)*VALUE(MID(TRIM(MID(SUBSTITUTE($V7,";",REPT(" ",99)),199,99)),FIND(":",TRIM(MID(SUBSTITUTE($V7,";",REPT(" ",99)),199,99)))+1,99)),0) + IFERROR(VLOOKUP(LEFT(TRIM(MID(SUBSTITUTE($V7,";",REPT(" ",99)),298,99)),FIND(":",TRIM(MID(SUBSTITUTE($V7,";",REPT(" ",99)),298,99)))-1),Materiales!$A$2:$E$502,5,FALSE)*VALUE(MID(TRIM(MID(SUBSTITUTE($V7,";",REPT(" ",99)),298,99)),FIND(":",TRIM(MID(SUBSTITUTE($V7,";",REPT(" ",99)),298,99)))+1,99)),0) + IFERROR(VLOOKUP(LEFT(TRIM(MID(SUBSTITUTE($V7,";",REPT(" ",99)),397,99)),FIND(":",TRIM(MID(SUBSTITUTE($V7,";",REPT(" ",99)),397,99)))-1),Materiales!$A$2:$E$502,5,FALSE)*VALUE(MID(TRIM(MID(SUBSTITUTE($V7,";",REPT(" ",99)),397,99)),FIND(":",TRIM(MID(SUBSTITUTE($V7,";",REPT(" ",99)),397,99)))+1,99)),0) + IFERROR(VLOOKUP(LEFT(TRIM(MID(SUBSTITUTE($V7,";",REPT(" ",99)),496,99)),FIND(":",TRIM(MID(SUBSTITUTE($V7,";",REPT(" ",99)),496,99)))-1),Materiales!$A$2:$E$502,5,FALSE)*VALUE(MID(TRIM(MID(SUBSTITUTE($V7,";",REPT(" ",99)),496,99)),FIND(":",TRIM(MID(SUBSTITUTE($V7,";",REPT(" ",99)),496,99)))+1,99)),0) + IFERROR(VLOOKUP(LEFT(TRIM(MID(SUBSTITUTE($V7,";",REPT(" ",99)),595,99)),FIND(":",TRIM(MID(SUBSTITUTE($V7,";",REPT(" ",99)),595,99)))-1),Materiales!$A$2:$E$502,5,FALSE)*VALUE(MID(TRIM(MID(SUBSTITUTE($V7,";",REPT(" ",99)),595,99)),FIND(":",TRIM(MID(SUBSTITUTE($V7,";",REPT(" ",99)),595,99)))+1,99)),0) + IFERROR(VLOOKUP(LEFT(TRIM(MID(SUBSTITUTE($V7,";",REPT(" ",99)),694,99)),FIND(":",TRIM(MID(SUBSTITUTE($V7,";",REPT(" ",99)),694,99)))-1),Materiales!$A$2:$E$502,5,FALSE)*VALUE(MID(TRIM(MID(SUBSTITUTE($V7,";",REPT(" ",99)),694,99)),FIND(":",TRIM(MID(SUBSTITUTE($V7,";",REPT(" ",99)),694,99)))+1,99)),0) + IFERROR(VLOOKUP(LEFT(TRIM(MID(SUBSTITUTE($V7,";",REPT(" ",99)),793,99)),FIND(":",TRIM(MID(SUBSTITUTE($V7,";",REPT(" ",99)),793,99)))-1),Materiales!$A$2:$E$502,5,FALSE)*VALUE(MID(TRIM(MID(SUBSTITUTE($V7,";",REPT(" ",99)),793,99)),FIND(":",TRIM(MID(SUBSTITUTE($V7,";",REPT(" ",99)),793,99)))+1,99)),0) + IFERROR(VLOOKUP(LEFT(TRIM(MID(SUBSTITUTE($V7,";",REPT(" ",99)),892,99)),FIND(":",TRIM(MID(SUBSTITUTE($V7,";",REPT(" ",99)),892,99)))-1),Materiales!$A$2:$E$502,5,FALSE)*VALUE(MID(TRIM(MID(SUBSTITUTE($V7,";",REPT(" ",99)),892,99)),FIND(":",TRIM(MID(SUBSTITUTE($V7,";",REPT(" ",99)),892,99)))+1,99)),0)))} -> 0 | X7: =IF($A7="","",SUM($G7,$H7,$K7,$N7,$Q7,$S7,$U7,$W7)) -> 1608.4415 | Y7: 3 | Z7: =X7*Y7 -> 4825.3245 | AA7: 0 | AB7: =AA7+Z7 -> 4825.3245 | AC7: 4500 | AD7: =AB7-X7 -> 3216.883 | AE7: =AC7-X7 -> 2891.5585 | AF7: =AE7/AD7 -> 0.89886966
A8: Vela bubble candle sola | B8: CERA_MOLDE | C8: 1 | F8: 142 | G8: {=IF($A8="","",IFERROR($F8*(N($C8)*XLOOKUP($B8,Ceras!$A$2:$A$500,Ceras!$G$2:$G$500,0)+IF($D8="",0,N($E8)*XLOOKUP($D8,Ceras!$A$2:$A$500,Ceras!$G$2:$G$500,0))),"Revisar cera"))} -> 2556 | H8: =F8*1.5 -> 213 | I8: PABILO6-8 | J8: 7 | K8: {=IF($A8="","",IFERROR($J8*XLOOKUP($I8,Pabilos!$A$2:$A$500,Pabilos!$H$2:$H$500,0),"Revisar pabilo"))} -> 140 | L8: ES_BEDOYA | M8: =F8*0.08 -> 11.36 | N8: {=IF($A8="","",IFERROR($M8*XLOOKUP($L8,Esencias!$A$2:$A$501,Esencias!$G$2:$G$501,0),"Revisar esencia"))} -> 1600 | O8: COLOR_ROJO | P8: 1 | Q8: {=IF($A8="","",IFERROR(IF($P8="",1,$P8)*XLOOKUP($O8,Colores!$A$2:$A$500,Colores!$H$2:$H$500,0),"Revisar color"))} -> 92.307692 | S8: {=IF($A8="","",IF($R8="",0,IFERROR(VLOOKUP(LEFT(TRIM(MID(SUBSTITUTE($R8,";",REPT(" ",99)),1,99)),FIND(":",TRIM(MID(SUBSTITUTE($R8,";",REPT(" ",99)),1,99)))-1),Materiales!$A$2:$E$502,5,FALSE)*VALUE(MID(TRIM(MID(SUBSTITUTE($R8,";",REPT(" ",99)),1,99)),FIND(":",TRIM(MID(SUBSTITUTE($R8,";",REPT(" ",99)),1,99)))+1,99)),0) + IFERROR(VLOOKUP(LEFT(TRIM(MID(SUBSTITUTE($R8,";",REPT(" ",99)),100,99)),FIND(":",TRIM(MID(SUBSTITUTE($R8,";",REPT(" ",99)),100,99)))-1),Materiales!$A$2:$E$502,5,FALSE)*VALUE(MID(TRIM(MID(SUBSTITUTE($R8,";",REPT(" ",99)),100,99)),FIND(":",TRIM(MID(SUBSTITUTE($R8,";",REPT(" ",99)),100,99)))+1,99)),0) + IFERROR(VLOOKUP(LEFT(TRIM(MID(SUBSTITUTE($R8,";",REPT(" ",99)),199,99)),FIND(":",TRIM(MID(SUBSTITUTE($R8,";",REPT(" ",99)),199,99)))-1),Materiales!$A$2:$E$502,5,FALSE)*VALUE(MID(TRIM(MID(SUBSTITUTE($R8,";",REPT(" ",99)),199,99)),FIND(":",TRIM(MID(SUBSTITUTE($R8,";",REPT(" ",99)),199,99)))+1,99)),0) + IFERROR(VLOOKUP(LEFT(TRIM(MID(SUBSTITUTE($R8,";",REPT(" ",99)),298,99)),FIND(":",TRIM(MID(SUBSTITUTE($R8,";",REPT(" ",99)),298,99)))-1),Materiales!$A$2:$E$502,5,FALSE)*VALUE(MID(TRIM(MID(SUBSTITUTE($R8,";",REPT(" ",99)),298,99)),FIND(":",TRIM(MID(SUBSTITUTE($R8,";",REPT(" ",99)),298,99)))+1,99)),0) + IFERROR(VLOOKUP(LEFT(TRIM(MID(SUBSTITUTE($R8,";",REPT(" ",99)),397,99)),FIND(":",TRIM(MID(SUBSTITUTE($R8,";",REPT(" ",99)),397,99)))-1),Materiales!$A$2:$E$502,5,FALSE)*VALUE(MID(TRIM(MID(SUBSTITUTE($R8,";",REPT(" ",99)),397,99)),FIND(":",TRIM(MID(SUBSTITUTE($R8,";",REPT(" ",99)),397,99)))+1,99)),0) + IFERROR(VLOOKUP(LEFT(TRIM(MID(SUBSTITUTE($R8,";",REPT(" ",99)),496,99)),FIND(":",TRIM(MID(SUBSTITUTE($R8,";",REPT(" ",99)),496,99)))-1),Materiales!$A$2:$E$502,5,FALSE)*VALUE(MID(TRIM(MID(SUBSTITUTE($R8,";",REPT(" ",99)),496,99)),FIND(":",TRIM(MID(SUBSTITUTE($R8,";",REPT(" ",99)),496,99)))+1,99)),0) + IFERROR(VLOOKUP(LEFT(TRIM(MID(SUBSTITUTE($R8,";",REPT(" ",99)),595,99)),FIND(":",TRIM(MID(SUBSTITUTE($R8,";",REPT(" ",99)),595,99)))-1),Materiales!$A$2:$E$502,5,FALSE)*VALUE(MID(TRIM(MID(SUBSTITUTE($R8,";",REPT(" ",99)),595,99)),FIND(":",TRIM(MID(SUBSTITUTE($R8,";",REPT(" ",99)),595,99)))+1,99)),0) + IFERROR(VLOOKUP(LEFT(TRIM(MID(SUBSTITUTE($R8,";",REPT(" ",99)),694,99)),FIND(":",TRIM(MID(SUBSTITUTE($R8,";",REPT(" ",99)),694,99)))-1),Materiales!$A$2:$E$502,5,FALSE)*VALUE(MID(TRIM(MID(SUBSTITUTE($R8,";",REPT(" ",99)),694,99)),FIND(":",TRIM(MID(SUBSTITUTE($R8,";",REPT(" ",99)),694,99)))+1,99)),0) + IFERROR(VLOOKUP(LEFT(TRIM(MID(SUBSTITUTE($R8,";",REPT(" ",99)),793,99)),FIND(":",TRIM(MID(SUBSTITUTE($R8,";",REPT(" ",99)),793,99)))-1),Materiales!$A$2:$E$502,5,FALSE)*VALUE(MID(TRIM(MID(SUBSTITUTE($R8,";",REPT(" ",99)),793,99)),FIND(":",TRIM(MID(SUBSTITUTE($R8,";",REPT(" ",99)),793,99)))+1,99)),0) + IFERROR(VLOOKUP(LEFT(TRIM(MID(SUBSTITUTE($R8,";",REPT(" ",99)),892,99)),FIND(":",TRIM(MID(SUBSTITUTE($R8,";",REPT(" ",99)),892,99)))-1),Materiales!$A$2:$E$502,5,FALSE)*VALUE(MID(TRIM(MID(SUBSTITUTE($R8,";",REPT(" ",99)),892,99)),FIND(":",TRIM(MID(SUBSTITUTE($R8,";",REPT(" ",99)),892,99)))+1,99)),0)))} -> 0 | U8: {=IF($A8="","",IF($T8="",0,IFERROR(VLOOKUP(LEFT(TRIM(MID(SUBSTITUTE($T8,";",REPT(" ",99)),1,99)),FIND(":",TRIM(MID(SUBSTITUTE($T8,";",REPT(" ",99)),1,99)))-1),Materiales!$A$2:$E$502,5,FALSE)*VALUE(MID(TRIM(MID(SUBSTITUTE($T8,";",REPT(" ",99)),1,99)),FIND(":",TRIM(MID(SUBSTITUTE($T8,";",REPT(" ",99)),1,99)))+1,99)),0) + IFERROR(VLOOKUP(LEFT(TRIM(MID(SUBSTITUTE($T8,";",REPT(" ",99)),100,99)),FIND(":",TRIM(MID(SUBSTITUTE($T8,";",REPT(" ",99)),100,99)))-1),Materiales!$A$2:$E$502,5,FALSE)*VALUE(MID(TRIM(MID(SUBSTITUTE($T8,";",REPT(" ",99)),100,99)),FIND(":",TRIM(MID(SUBSTITUTE($T8,";",REPT(" ",99)),100,99)))+1,99)),0) + IFERROR(VLOOKUP(LEFT(TRIM(MID(SUBSTITUTE($T8,";",REPT(" ",99)),199,99)),FIND(":",TRIM(MID(SUBSTITUTE($T8,";",REPT(" ",99)),199,99)))-1),Materiales!$A$2:$E$502,5,FALSE)*VALUE(MID(TRIM(MID(SUBSTITUTE($T8,";",REPT(" ",99)),199,99)),FIND(":",TRIM(MID(SUBSTITUTE($T8,";",REPT(" ",99)),199,99)))+1,99)),0) + IFERROR(VLOOKUP(LEFT(TRIM(MID(SUBSTITUTE($T8,";",REPT(" ",99)),298,99)),FIND(":",TRIM(MID(SUBSTITUTE($T8,";",REPT(" ",99)),298,99)))-1),Materiales!$A$2:$E$502,5,FALSE)*VALUE(MID(TRIM(MID(SUBSTITUTE($T8,";",REPT(" ",99)),298,99)),FIND(":",TRIM(MID(SUBSTITUTE($T8,";",REPT(" ",99)),298,99)))+1,99)),0) + IFERROR(VLOOKUP(LEFT(TRIM(MID(SUBSTITUTE($T8,";",REPT(" ",99)),397,99)),FIND(":",TRIM(MID(SUBSTITUTE($T8,";",REPT(" ",99)),397,99)))-1),Materiales!$A$2:$E$502,5,FALSE)*VALUE(MID(TRIM(MID(SUBSTITUTE($T8,";",REPT(" ",99)),397,99)),FIND(":",TRIM(MID(SUBSTITUTE($T8,";",REPT(" ",99)),397,99)))+1,99)),0) + IFERROR(VLOOKUP(LEFT(TRIM(MID(SUBSTITUTE($T8,";",REPT(" ",99)),496,99)),FIND(":",TRIM(MID(SUBSTITUTE($T8,";",REPT(" ",99)),496,99)))-1),Materiales!$A$2:$E$502,5,FALSE)*VALUE(MID(TRIM(MID(SUBSTITUTE($T8,";",REPT(" ",99)),496,99)),FIND(":",TRIM(MID(SUBSTITUTE($T8,";",REPT(" ",99)),496,99)))+1,99)),0) + IFERROR(VLOOKUP(LEFT(TRIM(MID(SUBSTITUTE($T8,";",REPT(" ",99)),595,99)),FIND(":",TRIM(MID(SUBSTITUTE($T8,";",REPT(" ",99)),595,99)))-1),Materiales!$A$2:$E$502,5,FALSE)*VALUE(MID(TRIM(MID(SUBSTITUTE($T8,";",REPT(" ",99)),595,99)),FIND(":",TRIM(MID(SUBSTITUTE($T8,";",REPT(" ",99)),595,99)))+1,99)),0) + IFERROR(VLOOKUP(LEFT(TRIM(MID(SUBSTITUTE($T8,";",REPT(" ",99)),694,99)),FIND(":",TRIM(MID(SUBSTITUTE($T8,";",REPT(" ",99)),694,99)))-1),Materiales!$A$2:$E$502,5,FALSE)*VALUE(MID(TRIM(MID(SUBSTITUTE($T8,";",REPT(" ",99)),694,99)),FIND(":",TRIM(MID(SUBSTITUTE($T8,";",REPT(" ",99)),694,99)))+1,99)),0) + IFERROR(VLOOKUP(LEFT(TRIM(MID(SUBSTITUTE($T8,";",REPT(" ",99)),793,99)),FIND(":",TRIM(MID(SUBSTITUTE($T8,";",REPT(" ",99)),793,99)))-1),Materiales!$A$2:$E$502,5,FALSE)*VALUE(MID(TRIM(MID(SUBSTITUTE($T8,";",REPT(" ",99)),793,99)),FIND(":",TRIM(MID(SUBSTITUTE($T8,";",REPT(" ",99)),793,99)))+1,99)),0) + IFERROR(VLOOKUP(LEFT(TRIM(MID(SUBSTITUTE($T8,";",REPT(" ",99)),892,99)),FIND(":",TRIM(MID(SUBSTITUTE($T8,";",REPT(" ",99)),892,99)))-1),Materiales!$A$2:$E$502,5,FALSE)*VALUE(MID(TRIM(MID(SUBSTITUTE($T8,";",REPT(" ",99)),892,99)),FIND(":",TRIM(MID(SUBSTITUTE($T8,";",REPT(" ",99)),892,99)))+1,99)),0)))} -> 0 | V8: ACEITE:1 | W8: {=IF($A8="","",IF($V8="",0,IFERROR(VLOOKUP(LEFT(TRIM(MID(SUBSTITUTE($V8,";",REPT(" ",99)),1,99)),FIND(":",TRIM(MID(SUBSTITUTE($V8,";",REPT(" ",99)),1,99)))-1),Materiales!$A$2:$E$502,5,FALSE)*VALUE(MID(TRIM(MID(SUBSTITUTE($V8,";",REPT(" ",99)),1,99)),FIND(":",TRIM(MID(SUBSTITUTE($V8,";",REPT(" ",99)),1,99)))+1,99)),0) + IFERROR(VLOOKUP(LEFT(TRIM(MID(SUBSTITUTE($V8,";",REPT(" ",99)),100,99)),FIND(":",TRIM(MID(SUBSTITUTE($V8,";",REPT(" ",99)),100,99)))-1),Materiales!$A$2:$E$502,5,FALSE)*VALUE(MID(TRIM(MID(SUBSTITUTE($V8,";",REPT(" ",99)),100,99)),FIND(":",TRIM(MID(SUBSTITUTE($V8,";",REPT(" ",99)),100,99)))+1,99)),0) + IFERROR(VLOOKUP(LEFT(TRIM(MID(SUBSTITUTE($V8,";",REPT(" ",99)),199,99)),FIND(":",TRIM(MID(SUBSTITUTE($V8,";",REPT(" ",99)),199,99)))-1),Materiales!$A$2:$E$502,5,FALSE)*VALUE(MID(TRIM(MID(SUBSTITUTE($V8,";",REPT(" ",99)),199,99)),FIND(":",TRIM(MID(SUBSTITUTE($V8,";",REPT(" ",99)),199,99)))+1,99)),0) + IFERROR(VLOOKUP(LEFT(TRIM(MID(SUBSTITUTE($V8,";",REPT(" ",99)),298,99)),FIND(":",TRIM(MID(SUBSTITUTE($V8,";",REPT(" ",99)),298,99)))-1),Materiales!$A$2:$E$502,5,FALSE)*VALUE(MID(TRIM(MID(SUBSTITUTE($V8,";",REPT(" ",99)),298,99)),FIND(":",TRIM(MID(SUBSTITUTE($V8,";",REPT(" ",99)),298,99)))+1,99)),0) + IFERROR(VLOOKUP(LEFT(TRIM(MID(SUBSTITUTE($V8,";",REPT(" ",99)),397,99)),FIND(":",TRIM(MID(SUBSTITUTE($V8,";",REPT(" ",99)),397,99)))-1),Materiales!$A$2:$E$502,5,FALSE)*VALUE(MID(TRIM(MID(SUBSTITUTE($V8,";",REPT(" ",99)),397,99)),FIND(":",TRIM(MID(SUBSTITUTE($V8,";",REPT(" ",99)),397,99)))+1,99)),0) + IFERROR(VLOOKUP(LEFT(TRIM(MID(SUBSTITUTE($V8,";",REPT(" ",99)),496,99)),FIND(":",TRIM(MID(SUBSTITUTE($V8,";",REPT(" ",99)),496,99)))-1),Materiales!$A$2:$E$502,5,FALSE)*VALUE(MID(TRIM(MID(SUBSTITUTE($V8,";",REPT(" ",99)),496,99)),FIND(":",TRIM(MID(SUBSTITUTE($V8,";",REPT(" ",99)),496,99)))+1,99)),0) + IFERROR(VLOOKUP(LEFT(TRIM(MID(SUBSTITUTE($V8,";",REPT(" ",99)),595,99)),FIND(":",TRIM(MID(SUBSTITUTE($V8,";",REPT(" ",99)),595,99)))-1),Materiales!$A$2:$E$502,5,FALSE)*VALUE(MID(TRIM(MID(SUBSTITUTE($V8,";",REPT(" ",99)),595,99)),FIND(":",TRIM(MID(SUBSTITUTE($V8,";",REPT(" ",99)),595,99)))+1,99)),0) + IFERROR(VLOOKUP(LEFT(TRIM(MID(SUBSTITUTE($V8,";",REPT(" ",99)),694,99)),FIND(":",TRIM(MID(SUBSTITUTE($V8,";",REPT(" ",99)),694,99)))-1),Materiales!$A$2:$E$502,5,FALSE)*VALUE(MID(TRIM(MID(SUBSTITUTE($V8,";",REPT(" ",99)),694,99)),FIND(":",TRIM(MID(SUBSTITUTE($V8,";",REPT(" ",99)),694,99)))+1,99)),0) + IFERROR(VLOOKUP(LEFT(TRIM(MID(SUBSTITUTE($V8,";",REPT(" ",99)),793,99)),FIND(":",TRIM(MID(SUBSTITUTE($V8,";",REPT(" ",99)),793,99)))-1),Materiales!$A$2:$E$502,5,FALSE)*VALUE(MID(TRIM(MID(SUBSTITUTE($V8,";",REPT(" ",99)),793,99)),FIND(":",TRIM(MID(SUBSTITUTE($V8,";",REPT(" ",99)),793,99)))+1,99)),0) + IFERROR(VLOOKUP(LEFT(TRIM(MID(SUBSTITUTE($V8,";",REPT(" ",99)),892,99)),FIND(":",TRIM(MID(SUBSTITUTE($V8,";",REPT(" ",99)),892,99)))-1),Materiales!$A$2:$E$502,5,FALSE)*VALUE(MID(TRIM(MID(SUBSTITUTE($V8,";",REPT(" ",99)),892,99)),FIND(":",TRIM(MID(SUBSTITUTE($V8,";",REPT(" ",99)),892,99)))+1,99)),0)))} -> 100 | X8: =IF($A8="","",SUM($G8,$H8,$K8,$N8,$Q8,$S8,$U8,$W8)) -> 4701.3077 | Y8: 3 | Z8: =X8*Y8 -> 14103.923 | AA8: 0 | AB8: =AA8+Z8 -> 14103.923 | AC8: 14000 | AD8: =AB8-X8 -> 9402.6154 | AE8: =AC8-X8 -> 9298.6923 | AF8: =AE8/AD8 -> 0.98894743
A9: Vela ramo de tulipanes | B9: CERA_MOLDE | C9: 1 | F9: 81 | G9: {=IF($A9="","",IFERROR($F9*(N($C9)*XLOOKUP($B9,Ceras!$A$2:$A$500,Ceras!$G$2:$G$500,0)+IF($D9="",0,N($E9)*XLOOKUP($D9,Ceras!$A$2:$A$500,Ceras!$G$2:$G$500,0))),"Revisar cera"))} -> 1458 | H9: =F9*1.5 -> 121.5 | I9: PABILO4-6 | J9: 13 | K9: {=IF($A9="","",IFERROR($J9*XLOOKUP($I9,Pabilos!$A$2:$A$500,Pabilos!$H$2:$H$500,0),"Revisar pabilo"))} -> 234 | L9: ES_BEDOYA | M9: =F9/10 -> 8.1 | N9: {=IF($A9="","",IFERROR($M9*XLOOKUP($L9,Esencias!$A$2:$A$501,Esencias!$G$2:$G$501,0),"Revisar esencia"))} -> 1140.8451 | O9: COLOR_CAFE | P9: 1 | Q9: {=IF($A9="","",IFERROR(IF($P9="",1,$P9)*XLOOKUP($O9,Colores!$A$2:$A$500,Colores!$H$2:$H$500,0),"Revisar color"))} -> 92.307692 | S9: {=IF($A9="","",IF($R9="",0,IFERROR(VLOOKUP(LEFT(TRIM(MID(SUBSTITUTE($R9,";",REPT(" ",99)),1,99)),FIND(":",TRIM(MID(SUBSTITUTE($R9,";",REPT(" ",99)),1,99)))-1),Materiales!$A$2:$E$502,5,FALSE)*VALUE(MID(TRIM(MID(SUBSTITUTE($R9,";",REPT(" ",99)),1,99)),FIND(":",TRIM(MID(SUBSTITUTE($R9,";",REPT(" ",99)),1,99)))+1,99)),0) + IFERROR(VLOOKUP(LEFT(TRIM(MID(SUBSTITUTE($R9,";",REPT(" ",99)),100,99)),FIND(":",TRIM(MID(SUBSTITUTE($R9,";",REPT(" ",99)),100,99)))-1),Materiales!$A$2:$E$502,5,FALSE)*VALUE(MID(TRIM(MID(SUBSTITUTE($R9,";",REPT(" ",99)),100,99)),FIND(":",TRIM(MID(SUBSTITUTE($R9,";",REPT(" ",99)),100,99)))+1,99)),0) + IFERROR(VLOOKUP(LEFT(TRIM(MID(SUBSTITUTE($R9,";",REPT(" ",99)),199,99)),FIND(":",TRIM(MID(SUBSTITUTE($R9,";",REPT(" ",99)),199,99)))-1),Materiales!$A$2:$E$502,5,FALSE)*VALUE(MID(TRIM(MID(SUBSTITUTE($R9,";",REPT(" ",99)),199,99)),FIND(":",TRIM(MID(SUBSTITUTE($R9,";",REPT(" ",99)),199,99)))+1,99)),0) + IFERROR(VLOOKUP(LEFT(TRIM(MID(SUBSTITUTE($R9,";",REPT(" ",99)),298,99)),FIND(":",TRIM(MID(SUBSTITUTE($R9,";",REPT(" ",99)),298,99)))-1),Materiales!$A$2:$E$502,5,FALSE)*VALUE(MID(TRIM(MID(SUBSTITUTE($R9,";",REPT(" ",99)),298,99)),FIND(":",TRIM(MID(SUBSTITUTE($R9,";",REPT(" ",99)),298,99)))+1,99)),0) + IFERROR(VLOOKUP(LEFT(TRIM(MID(SUBSTITUTE($R9,";",REPT(" ",99)),397,99)),FIND(":",TRIM(MID(SUBSTITUTE($R9,";",REPT(" ",99)),397,99)))-1),Materiales!$A$2:$E$502,5,FALSE)*VALUE(MID(TRIM(MID(SUBSTITUTE($R9,";",REPT(" ",99)),397,99)),FIND(":",TRIM(MID(SUBSTITUTE($R9,";",REPT(" ",99)),397,99)))+1,99)),0) + IFERROR(VLOOKUP(LEFT(TRIM(MID(SUBSTITUTE($R9,";",REPT(" ",99)),496,99)),FIND(":",TRIM(MID(SUBSTITUTE($R9,";",REPT(" ",99)),496,99)))-1),Materiales!$A$2:$E$502,5,FALSE)*VALUE(MID(TRIM(MID(SUBSTITUTE($R9,";",REPT(" ",99)),496,99)),FIND(":",TRIM(MID(SUBSTITUTE($R9,";",REPT(" ",99)),496,99)))+1,99)),0) + IFERROR(VLOOKUP(LEFT(TRIM(MID(SUBSTITUTE($R9,";",REPT(" ",99)),595,99)),FIND(":",TRIM(MID(SUBSTITUTE($R9,";",REPT(" ",99)),595,99)))-1),Materiales!$A$2:$E$502,5,FALSE)*VALUE(MID(TRIM(MID(SUBSTITUTE($R9,";",REPT(" ",99)),595,99)),FIND(":",TRIM(MID(SUBSTITUTE($R9,";",REPT(" ",99)),595,99)))+1,99)),0) + IFERROR(VLOOKUP(LEFT(TRIM(MID(SUBSTITUTE($R9,";",REPT(" ",99)),694,99)),FIND(":",TRIM(MID(SUBSTITUTE($R9,";",REPT(" ",99)),694,99)))-1),Materiales!$A$2:$E$502,5,FALSE)*VALUE(MID(TRIM(MID(SUBSTITUTE($R9,";",REPT(" ",99)),694,99)),FIND(":",TRIM(MID(SUBSTITUTE($R9,";",REPT(" ",99)),694,99)))+1,99)),0) + IFERROR(VLOOKUP(LEFT(TRIM(MID(SUBSTITUTE($R9,";",REPT(" ",99)),793,99)),FIND(":",TRIM(MID(SUBSTITUTE($R9,";",REPT(" ",99)),793,99)))-1),Materiales!$A$2:$E$502,5,FALSE)*VALUE(MID(TRIM(MID(SUBSTITUTE($R9,";",REPT(" ",99)),793,99)),FIND(":",TRIM(MID(SUBSTITUTE($R9,";",REPT(" ",99)),793,99)))+1,99)),0) + IFERROR(VLOOKUP(LEFT(TRIM(MID(SUBSTITUTE($R9,";",REPT(" ",99)),892,99)),FIND(":",TRIM(MID(SUBSTITUTE($R9,";",REPT(" ",99)),892,99)))-1),Materiales!$A$2:$E$502,5,FALSE)*VALUE(MID(TRIM(MID(SUBSTITUTE($R9,";",REPT(" ",99)),892,99)),FIND(":",TRIM(MID(SUBSTITUTE($R9,";",REPT(" ",99)),892,99)))+1,99)),0)))} -> 0 | U9: {=IF($A9="","",IF($T9="",0,IFERROR(VLOOKUP(LEFT(TRIM(MID(SUBSTITUTE($T9,";",REPT(" ",99)),1,99)),FIND(":",TRIM(MID(SUBSTITUTE($T9,";",REPT(" ",99)),1,99)))-1),Materiales!$A$2:$E$502,5,FALSE)*VALUE(MID(TRIM(MID(SUBSTITUTE($T9,";",REPT(" ",99)),1,99)),FIND(":",TRIM(MID(SUBSTITUTE($T9,";",REPT(" ",99)),1,99)))+1,99)),0) + IFERROR(VLOOKUP(LEFT(TRIM(MID(SUBSTITUTE($T9,";",REPT(" ",99)),100,99)),FIND(":",TRIM(MID(SUBSTITUTE($T9,";",REPT(" ",99)),100,99)))-1),Materiales!$A$2:$E$502,5,FALSE)*VALUE(MID(TRIM(MID(SUBSTITUTE($T9,";",REPT(" ",99)),100,99)),FIND(":",TRIM(MID(SUBSTITUTE($T9,";",REPT(" ",99)),100,99)))+1,99)),0) + IFERROR(VLOOKUP(LEFT(TRIM(MID(SUBSTITUTE($T9,";",REPT(" ",99)),199,99)),FIND(":",TRIM(MID(SUBSTITUTE($T9,";",REPT(" ",99)),199,99)))-1),Materiales!$A$2:$E$502,5,FALSE)*VALUE(MID(TRIM(MID(SUBSTITUTE($T9,";",REPT(" ",99)),199,99)),FIND(":",TRIM(MID(SUBSTITUTE($T9,";",REPT(" ",99)),199,99)))+1,99)),0) + IFERROR(VLOOKUP(LEFT(TRIM(MID(SUBSTITUTE($T9,";",REPT(" ",99)),298,99)),FIND(":",TRIM(MID(SUBSTITUTE($T9,";",REPT(" ",99)),298,99)))-1),Materiales!$A$2:$E$502,5,FALSE)*VALUE(MID(TRIM(MID(SUBSTITUTE($T9,";",REPT(" ",99)),298,99)),FIND(":",TRIM(MID(SUBSTITUTE($T9,";",REPT(" ",99)),298,99)))+1,99)),0) + IFERROR(VLOOKUP(LEFT(TRIM(MID(SUBSTITUTE($T9,";",REPT(" ",99)),397,99)),FIND(":",TRIM(MID(SUBSTITUTE($T9,";",REPT(" ",99)),397,99)))-1),Materiales!$A$2:$E$502,5,FALSE)*VALUE(MID(TRIM(MID(SUBSTITUTE($T9,";",REPT(" ",99)),397,99)),FIND(":",TRIM(MID(SUBSTITUTE($T9,";",REPT(" ",99)),397,99)))+1,99)),0) + IFERROR(VLOOKUP(LEFT(TRIM(MID(SUBSTITUTE($T9,";",REPT(" ",99)),496,99)),FIND(":",TRIM(MID(SUBSTITUTE($T9,";",REPT(" ",99)),496,99)))-1),Materiales!$A$2:$E$502,5,FALSE)*VALUE(MID(TRIM(MID(SUBSTITUTE($T9,";",REPT(" ",99)),496,99)),FIND(":",TRIM(MID(SUBSTITUTE($T9,";",REPT(" ",99)),496,99)))+1,99)),0) + IFERROR(VLOOKUP(LEFT(TRIM(MID(SUBSTITUTE($T9,";",REPT(" ",99)),595,99)),FIND(":",TRIM(MID(SUBSTITUTE($T9,";",REPT(" ",99)),595,99)))-1),Materiales!$A$2:$E$502,5,FALSE)*VALUE(MID(TRIM(MID(SUBSTITUTE($T9,";",REPT(" ",99)),595,99)),FIND(":",TRIM(MID(SUBSTITUTE($T9,";",REPT(" ",99)),595,99)))+1,99)),0) + IFERROR(VLOOKUP(LEFT(TRIM(MID(SUBSTITUTE($T9,";",REPT(" ",99)),694,99)),FIND(":",TRIM(MID(SUBSTITUTE($T9,";",REPT(" ",99)),694,99)))-1),Materiales!$A$2:$E$502,5,FALSE)*VALUE(MID(TRIM(MID(SUBSTITUTE($T9,";",REPT(" ",99)),694,99)),FIND(":",TRIM(MID(SUBSTITUTE($T9,";",REPT(" ",99)),694,99)))+1,99)),0) + IFERROR(VLOOKUP(LEFT(TRIM(MID(SUBSTITUTE($T9,";",REPT(" ",99)),793,99)),FIND(":",TRIM(MID(SUBSTITUTE($T9,";",REPT(" ",99)),793,99)))-1),Materiales!$A$2:$E$502,5,FALSE)*VALUE(MID(TRIM(MID(SUBSTITUTE($T9,";",REPT(" ",99)),793,99)),FIND(":",TRIM(MID(SUBSTITUTE($T9,";",REPT(" ",99)),793,99)))+1,99)),0) + IFERROR(VLOOKUP(LEFT(TRIM(MID(SUBSTITUTE($T9,";",REPT(" ",99)),892,99)),FIND(":",TRIM(MID(SUBSTITUTE($T9,";",REPT(" ",99)),892,99)))-1),Materiales!$A$2:$E$502,5,FALSE)*VALUE(MID(TRIM(MID(SUBSTITUTE($T9,";",REPT(" ",99)),892,99)),FIND(":",TRIM(MID(SUBSTITUTE($T9,";",REPT(" ",99)),892,99)))+1,99)),0)))} -> 0 | W9: {=IF($A9="","",IF($V9="",0,IFERROR(VLOOKUP(LEFT(TRIM(MID(SUBSTITUTE($V9,";",REPT(" ",99)),1,99)),FIND(":",TRIM(MID(SUBSTITUTE($V9,";",REPT(" ",99)),1,99)))-1),Materiales!$A$2:$E$502,5,FALSE)*VALUE(MID(TRIM(MID(SUBSTITUTE($V9,";",REPT(" ",99)),1,99)),FIND(":",TRIM(MID(SUBSTITUTE($V9,";",REPT(" ",99)),1,99)))+1,99)),0) + IFERROR(VLOOKUP(LEFT(TRIM(MID(SUBSTITUTE($V9,";",REPT(" ",99)),100,99)),FIND(":",TRIM(MID(SUBSTITUTE($V9,";",REPT(" ",99)),100,99)))-1),Materiales!$A$2:$E$502,5,FALSE)*VALUE(MID(TRIM(MID(SUBSTITUTE($V9,";",REPT(" ",99)),100,99)),FIND(":",TRIM(MID(SUBSTITUTE($V9,";",REPT(" ",99)),100,99)))+1,99)),0) + IFERROR(VLOOKUP(LEFT(TRIM(MID(SUBSTITUTE($V9,";",REPT(" ",99)),199,99)),FIND(":",TRIM(MID(SUBSTITUTE($V9,";",REPT(" ",99)),199,99)))-1),Materiales!$A$2:$E$502,5,FALSE)*VALUE(MID(TRIM(MID(SUBSTITUTE($V9,";",REPT(" ",99)),199,99)),FIND(":",TRIM(MID(SUBSTITUTE($V9,";",REPT(" ",99)),199,99)))+1,99)),0) + IFERROR(VLOOKUP(LEFT(TRIM(MID(SUBSTITUTE($V9,";",REPT(" ",99)),298,99)),FIND(":",TRIM(MID(SUBSTITUTE($V9,";",REPT(" ",99)),298,99)))-1),Materiales!$A$2:$E$502,5,FALSE)*VALUE(MID(TRIM(MID(SUBSTITUTE($V9,";",REPT(" ",99)),298,99)),FIND(":",TRIM(MID(SUBSTITUTE($V9,";",REPT(" ",99)),298,99)))+1,99)),0) + IFERROR(VLOOKUP(LEFT(TRIM(MID(SUBSTITUTE($V9,";",REPT(" ",99)),397,99)),FIND(":",TRIM(MID(SUBSTITUTE($V9,";",REPT(" ",99)),397,99)))-1),Materiales!$A$2:$E$502,5,FALSE)*VALUE(MID(TRIM(MID(SUBSTITUTE($V9,";",REPT(" ",99)),397,99)),FIND(":",TRIM(MID(SUBSTITUTE($V9,";",REPT(" ",99)),397,99)))+1,99)),0) + IFERROR(VLOOKUP(LEFT(TRIM(MID(SUBSTITUTE($V9,";",REPT(" ",99)),496,99)),FIND(":",TRIM(MID(SUBSTITUTE($V9,";",REPT(" ",99)),496,99)))-1),Materiales!$A$2:$E$502,5,FALSE)*VALUE(MID(TRIM(MID(SUBSTITUTE($V9,";",REPT(" ",99)),496,99)),FIND(":",TRIM(MID(SUBSTITUTE($V9,";",REPT(" ",99)),496,99)))+1,99)),0) + IFERROR(VLOOKUP(LEFT(TRIM(MID(SUBSTITUTE($V9,";",REPT(" ",99)),595,99)),FIND(":",TRIM(MID(SUBSTITUTE($V9,";",REPT(" ",99)),595,99)))-1),Materiales!$A$2:$E$502,5,FALSE)*VALUE(MID(TRIM(MID(SUBSTITUTE($V9,";",REPT(" ",99)),595,99)),FIND(":",TRIM(MID(SUBSTITUTE($V9,";",REPT(" ",99)),595,99)))+1,99)),0) + IFERROR(VLOOKUP(LEFT(TRIM(MID(SUBSTITUTE($V9,";",REPT(" ",99)),694,99)),FIND(":",TRIM(MID(SUBSTITUTE($V9,";",REPT(" ",99)),694,99)))-1),Materiales!$A$2:$E$502,5,FALSE)*VALUE(MID(TRIM(MID(SUBSTITUTE($V9,";",REPT(" ",99)),694,99)),FIND(":",TRIM(MID(SUBSTITUTE($V9,";",REPT(" ",99)),694,99)))+1,99)),0) + IFERROR(VLOOKUP(LEFT(TRIM(MID(SUBSTITUTE($V9,";",REPT(" ",99)),793,99)),FIND(":",TRIM(MID(SUBSTITUTE($V9,";",REPT(" ",99)),793,99)))-1),Materiales!$A$2:$E$502,5,FALSE)*VALUE(MID(TRIM(MID(SUBSTITUTE($V9,";",REPT(" ",99)),793,99)),FIND(":",TRIM(MID(SUBSTITUTE($V9,";",REPT(" ",99)),793,99)))+1,99)),0) + IFERROR(VLOOKUP(LEFT(TRIM(MID(SUBSTITUTE($V9,";",REPT(" ",99)),892,99)),FIND(":",TRIM(MID(SUBSTITUTE($V9,";",REPT(" ",99)),892,99)))-1),Materiales!$A$2:$E$502,5,FALSE)*VALUE(MID(TRIM(MID(SUBSTITUTE($V9,";",REPT(" ",99)),892,99)),FIND(":",TRIM(MID(SUBSTITUTE($V9,";",REPT(" ",99)),892,99)))+1,99)),0)))} -> 0 | X9: =IF($A9="","",SUM($G9,$H9,$K9,$N9,$Q9,$S9,$U9,$W9)) -> 3046.6528 | Y9: 3 | Z9: =X9*Y9 -> 9139.9583 | AA9: 0 | AB9: =AA9+Z9 -> 9139.9583 | AC9: 12000 | AD9: =AB9-X9 -> 6093.3055 | AE9: =AC9-X9 -> 8953.3472 | AF9: =AE9/AD9 -> 1.4693744
A10: Vela Oso floreado | B10: CERA_MOLDE | C10: 1 | F10: 57 | G10: {=IF($A10="","",IFERROR($F10*(N($C10)*XLOOKUP($B10,Ceras!$A$2:$A$500,Ceras!$G$2:$G$500,0)+IF($D10="",0,N($E10)*XLOOKUP($D10,Ceras!$A$2:$A$500,Ceras!$G$2:$G$500,0))),"Revisar cera"))} -> 1026 | H10: =F10*1.5 -> 85.5 | I10: PABILO4-6 | J10: 7 | K10: {=IF($A10="","",IFERROR($J10*XLOOKUP($I10,Pabilos!$A$2:$A$500,Pabilos!$H$2:$H$500,0),"Revisar pabilo"))} -> 126 | L10: ES_BEDOYA | M10: =F10/10 -> 5.7 | N10: {=IF($A10="","",IFERROR($M10*XLOOKUP($L10,Esencias!$A$2:$A$501,Esencias!$G$2:$G$501,0),"Revisar esencia"))} -> 802.8169 | O10: COLOR_CAFE | P10: 1 | Q10: {=IF($A10="","",IFERROR(IF($P10="",1,$P10)*XLOOKUP($O10,Colores!$A$2:$A$500,Colores!$H$2:$H$500,0),"Revisar color"))} -> 92.307692 | S10: {=IF($A10="","",IF($R10="",0,IFERROR(VLOOKUP(LEFT(TRIM(MID(SUBSTITUTE($R10,";",REPT(" ",99)),1,99)),FIND(":",TRIM(MID(SUBSTITUTE($R10,";",REPT(" ",99)),1,99)))-1),Materiales!$A$2:$E$502,5,FALSE)*VALUE(MID(TRIM(MID(SUBSTITUTE($R10,";",REPT(" ",99)),1,99)),FIND(":",TRIM(MID(SUBSTITUTE($R10,";",REPT(" ",99)),1,99)))+1,99)),0) + IFERROR(VLOOKUP(LEFT(TRIM(MID(SUBSTITUTE($R10,";",REPT(" ",99)),100,99)),FIND(":",TRIM(MID(SUBSTITUTE($R10,";",REPT(" ",99)),100,99)))-1),Materiales!$A$2:$E$502,5,FALSE)*VALUE(MID(TRIM(MID(SUBSTITUTE($R10,";",REPT(" ",99)),100,99)),FIND(":",TRIM(MID(SUBSTITUTE($R10,";",REPT(" ",99)),100,99)))+1,99)),0) + IFERROR(VLOOKUP(LEFT(TRIM(MID(SUBSTITUTE($R10,";",REPT(" ",99)),199,99)),FIND(":",TRIM(MID(SUBSTITUTE($R10,";",REPT(" ",99)),199,99)))-1),Materiales!$A$2:$E$502,5,FALSE)*VALUE(MID(TRIM(MID(SUBSTITUTE($R10,";",REPT(" ",99)),199,99)),FIND(":",TRIM(MID(SUBSTITUTE($R10,";",REPT(" ",99)),199,99)))+1,99)),0) + IFERROR(VLOOKUP(LEFT(TRIM(MID(SUBSTITUTE($R10,";",REPT(" ",99)),298,99)),FIND(":",TRIM(MID(SUBSTITUTE($R10,";",REPT(" ",99)),298,99)))-1),Materiales!$A$2:$E$502,5,FALSE)*VALUE(MID(TRIM(MID(SUBSTITUTE($R10,";",REPT(" ",99)),298,99)),FIND(":",TRIM(MID(SUBSTITUTE($R10,";",REPT(" ",99)),298,99)))+1,99)),0) + IFERROR(VLOOKUP(LEFT(TRIM(MID(SUBSTITUTE($R10,";",REPT(" ",99)),397,99)),FIND(":",TRIM(MID(SUBSTITUTE($R10,";",REPT(" ",99)),397,99)))-1),Materiales!$A$2:$E$502,5,FALSE)*VALUE(MID(TRIM(MID(SUBSTITUTE($R10,";",REPT(" ",99)),397,99)),FIND(":",TRIM(MID(SUBSTITUTE($R10,";",REPT(" ",99)),397,99)))+1,99)),0) + IFERROR(VLOOKUP(LEFT(TRIM(MID(SUBSTITUTE($R10,";",REPT(" ",99)),496,99)),FIND(":",TRIM(MID(SUBSTITUTE($R10,";",REPT(" ",99)),496,99)))-1),Materiales!$A$2:$E$502,5,FALSE)*VALUE(MID(TRIM(MID(SUBSTITUTE($R10,";",REPT(" ",99)),496,99)),FIND(":",TRIM(MID(SUBSTITUTE($R10,";",REPT(" ",99)),496,99)))+1,99)),0) + IFERROR(VLOOKUP(LEFT(TRIM(MID(SUBSTITUTE($R10,";",REPT(" ",99)),595,99)),FIND(":",TRIM(MID(SUBSTITUTE($R10,";",REPT(" ",99)),595,99)))-1),Materiales!$A$2:$E$502,5,FALSE)*VALUE(MID(TRIM(MID(SUBSTITUTE($R10,";",REPT(" ",99)),595,99)),FIND(":",TRIM(MID(SUBSTITUTE($R10,";",REPT(" ",99)),595,99)))+1,99)),0) + IFERROR(VLOOKUP(LEFT(TRIM(MID(SUBSTITUTE($R10,";",REPT(" ",99)),694,99)),FIND(":",TRIM(MID(SUBSTITUTE($R10,";",REPT(" ",99)),694,99)))-1),Materiales!$A$2:$E$502,5,FALSE)*VALUE(MID(TRIM(MID(SUBSTITUTE($R10,";",REPT(" ",99)),694,99)),FIND(":",TRIM(MID(SUBSTITUTE($R10,";",REPT(" ",99)),694,99)))+1,99)),0) + IFERROR(VLOOKUP(LEFT(TRIM(MID(SUBSTITUTE($R10,";",REPT(" ",99)),793,99)),FIND(":",TRIM(MID(SUBSTITUTE($R10,";",REPT(" ",99)),793,99)))-1),Materiales!$A$2:$E$502,5,FALSE)*VALUE(MID(TRIM(MID(SUBSTITUTE($R10,";",REPT(" ",99)),793,99)),FIND(":",TRIM(MID(SUBSTITUTE($R10,";",REPT(" ",99)),793,99)))+1,99)),0) + IFERROR(VLOOKUP(LEFT(TRIM(MID(SUBSTITUTE($R10,";",REPT(" ",99)),892,99)),FIND(":",TRIM(MID(SUBSTITUTE($R10,";",REPT(" ",99)),892,99)))-1),Materiales!$A$2:$E$502,5,FALSE)*VALUE(MID(TRIM(MID(SUBSTITUTE($R10,";",REPT(" ",99)),892,99)),FIND(":",TRIM(MID(SUBSTITUTE($R10,";",REPT(" ",99)),892,99)))+1,99)),0)))} -> 0 | U10: {=IF($A10="","",IF($T10="",0,IFERROR(VLOOKUP(LEFT(TRIM(MID(SUBSTITUTE($T10,";",REPT(" ",99)),1,99)),FIND(":",TRIM(MID(SUBSTITUTE($T10,";",REPT(" ",99)),1,99)))-1),Materiales!$A$2:$E$502,5,FALSE)*VALUE(MID(TRIM(MID(SUBSTITUTE($T10,";",REPT(" ",99)),1,99)),FIND(":",TRIM(MID(SUBSTITUTE($T10,";",REPT(" ",99)),1,99)))+1,99)),0) + IFERROR(VLOOKUP(LEFT(TRIM(MID(SUBSTITUTE($T10,";",REPT(" ",99)),100,99)),FIND(":",TRIM(MID(SUBSTITUTE($T10,";",REPT(" ",99)),100,99)))-1),Materiales!$A$2:$E$502,5,FALSE)*VALUE(MID(TRIM(MID(SUBSTITUTE($T10,";",REPT(" ",99)),100,99)),FIND(":",TRIM(MID(SUBSTITUTE($T10,";",REPT(" ",99)),100,99)))+1,99)),0) + IFERROR(VLOOKUP(LEFT(TRIM(MID(SUBSTITUTE($T10,";",REPT(" ",99)),199,99)),FIND(":",TRIM(MID(SUBSTITUTE($T10,";",REPT(" ",99)),199,99)))-1),Materiales!$A$2:$E$502,5,FALSE)*VALUE(MID(TRIM(MID(SUBSTITUTE($T10,";",REPT(" ",99)),199,99)),FIND(":",TRIM(MID(SUBSTITUTE($T10,";",REPT(" ",99)),199,99)))+1,99)),0) + IFERROR(VLOOKUP(LEFT(TRIM(MID(SUBSTITUTE($T10,";",REPT(" ",99)),298,99)),FIND(":",TRIM(MID(SUBSTITUTE($T10,";",REPT(" ",99)),298,99)))-1),Materiales!$A$2:$E$502,5,FALSE)*VALUE(MID(TRIM(MID(SUBSTITUTE($T10,";",REPT(" ",99)),298,99)),FIND(":",TRIM(MID(SUBSTITUTE($T10,";",REPT(" ",99)),298,99)))+1,99)),0) + IFERROR(VLOOKUP(LEFT(TRIM(MID(SUBSTITUTE($T10,";",REPT(" ",99)),397,99)),FIND(":",TRIM(MID(SUBSTITUTE($T10,";",REPT(" ",99)),397,99)))-1),Materiales!$A$2:$E$502,5,FALSE)*VALUE(MID(TRIM(MID(SUBSTITUTE($T10,";",REPT(" ",99)),397,99)),FIND(":",TRIM(MID(SUBSTITUTE($T10,";",REPT(" ",99)),397,99)))+1,99)),0) + IFERROR(VLOOKUP(LEFT(TRIM(MID(SUBSTITUTE($T10,";",REPT(" ",99)),496,99)),FIND(":",TRIM(MID(SUBSTITUTE($T10,";",REPT(" ",99)),496,99)))-1),Materiales!$A$2:$E$502,5,FALSE)*VALUE(MID(TRIM(MID(SUBSTITUTE($T10,";",REPT(" ",99)),496,99)),FIND(":",TRIM(MID(SUBSTITUTE($T10,";",REPT(" ",99)),496,99)))+1,99)),0) + IFERROR(VLOOKUP(LEFT(TRIM(MID(SUBSTITUTE($T10,";",REPT(" ",99)),595,99)),FIND(":",TRIM(MID(SUBSTITUTE($T10,";",REPT(" ",99)),595,99)))-1),Materiales!$A$2:$E$502,5,FALSE)*VALUE(MID(TRIM(MID(SUBSTITUTE($T10,";",REPT(" ",99)),595,99)),FIND(":",TRIM(MID(SUBSTITUTE($T10,";",REPT(" ",99)),595,99)))+1,99)),0) + IFERROR(VLOOKUP(LEFT(TRIM(MID(SUBSTITUTE($T10,";",REPT(" ",99)),694,99)),FIND(":",TRIM(MID(SUBSTITUTE($T10,";",REPT(" ",99)),694,99)))-1),Materiales!$A$2:$E$502,5,FALSE)*VALUE(MID(TRIM(MID(SUBSTITUTE($T10,";",REPT(" ",99)),694,99)),FIND(":",TRIM(MID(SUBSTITUTE($T10,";",REPT(" ",99)),694,99)))+1,99)),0) + IFERROR(VLOOKUP(LEFT(TRIM(MID(SUBSTITUTE($T10,";",REPT(" ",99)),793,99)),FIND(":",TRIM(MID(SUBSTITUTE($T10,";",REPT(" ",99)),793,99)))-1),Materiales!$A$2:$E$502,5,FALSE)*VALUE(MID(TRIM(MID(SUBSTITUTE($T10,";",REPT(" ",99)),793,99)),FIND(":",TRIM(MID(SUBSTITUTE($T10,";",REPT(" ",99)),793,99)))+1,99)),0) + IFERROR(VLOOKUP(LEFT(TRIM(MID(SUBSTITUTE($T10,";",REPT(" ",99)),892,99)),FIND(":",TRIM(MID(SUBSTITUTE($T10,";",REPT(" ",99)),892,99)))-1),Materiales!$A$2:$E$502,5,FALSE)*VALUE(MID(TRIM(MID(SUBSTITUTE($T10,";",REPT(" ",99)),892,99)),FIND(":",TRIM(MID(SUBSTITUTE($T10,";",REPT(" ",99)),892,99)))+1,99)),0)))} -> 0 | W10: {=IF($A10="","",IF($V10="",0,IFERROR(VLOOKUP(LEFT(TRIM(MID(SUBSTITUTE($V10,";",REPT(" ",99)),1,99)),FIND(":",TRIM(MID(SUBSTITUTE($V10,";",REPT(" ",99)),1,99)))-1),Materiales!$A$2:$E$502,5,FALSE)*VALUE(MID(TRIM(MID(SUBSTITUTE($V10,";",REPT(" ",99)),1,99)),FIND(":",TRIM(MID(SUBSTITUTE($V10,";",REPT(" ",99)),1,99)))+1,99)),0) + IFERROR(VLOOKUP(LEFT(TRIM(MID(SUBSTITUTE($V10,";",REPT(" ",99)),100,99)),FIND(":",TRIM(MID(SUBSTITUTE($V10,";",REPT(" ",99)),100,99)))-1),Materiales!$A$2:$E$502,5,FALSE)*VALUE(MID(TRIM(MID(SUBSTITUTE($V10,";",REPT(" ",99)),100,99)),FIND(":",TRIM(MID(SUBSTITUTE($V10,";",REPT(" ",99)),100,99)))+1,99)),0) + IFERROR(VLOOKUP(LEFT(TRIM(MID(SUBSTITUTE($V10,";",REPT(" ",99)),199,99)),FIND(":",TRIM(MID(SUBSTITUTE($V10,";",REPT(" ",99)),199,99)))-1),Materiales!$A$2:$E$502,5,FALSE)*VALUE(MID(TRIM(MID(SUBSTITUTE($V10,";",REPT(" ",99)),199,99)),FIND(":",TRIM(MID(SUBSTITUTE($V10,";",REPT(" ",99)),199,99)))+1,99)),0) + IFERROR(VLOOKUP(LEFT(TRIM(MID(SUBSTITUTE($V10,";",REPT(" ",99)),298,99)),FIND(":",TRIM(MID(SUBSTITUTE($V10,";",REPT(" ",99)),298,99)))-1),Materiales!$A$2:$E$502,5,FALSE)*VALUE(MID(TRIM(MID(SUBSTITUTE($V10,";",REPT(" ",99)),298,99)),FIND(":",TRIM(MID(SUBSTITUTE($V10,";",REPT(" ",99)),298,99)))+1,99)),0) + IFERROR(VLOOKUP(LEFT(TRIM(MID(SUBSTITUTE($V10,";",REPT(" ",99)),397,99)),FIND(":",TRIM(MID(SUBSTITUTE($V10,";",REPT(" ",99)),397,99)))-1),Materiales!$A$2:$E$502,5,FALSE)*VALUE(MID(TRIM(MID(SUBSTITUTE($V10,";",REPT(" ",99)),397,99)),FIND(":",TRIM(MID(SUBSTITUTE($V10,";",REPT(" ",99)),397,99)))+1,99)),0) + IFERROR(VLOOKUP(LEFT(TRIM(MID(SUBSTITUTE($V10,";",REPT(" ",99)),496,99)),FIND(":",TRIM(MID(SUBSTITUTE($V10,";",REPT(" ",99)),496,99)))-1),Materiales!$A$2:$E$502,5,FALSE)*VALUE(MID(TRIM(MID(SUBSTITUTE($V10,";",REPT(" ",99)),496,99)),FIND(":",TRIM(MID(SUBSTITUTE($V10,";",REPT(" ",99)),496,99)))+1,99)),0) + IFERROR(VLOOKUP(LEFT(TRIM(MID(SUBSTITUTE($V10,";",REPT(" ",99)),595,99)),FIND(":",TRIM(MID(SUBSTITUTE($V10,";",REPT(" ",99)),595,99)))-1),Materiales!$A$2:$E$502,5,FALSE)*VALUE(MID(TRIM(MID(SUBSTITUTE($V10,";",REPT(" ",99)),595,99)),FIND(":",TRIM(MID(SUBSTITUTE($V10,";",REPT(" ",99)),595,99)))+1,99)),0) + IFERROR(VLOOKUP(LEFT(TRIM(MID(SUBSTITUTE($V10,";",REPT(" ",99)),694,99)),FIND(":",TRIM(MID(SUBSTITUTE($V10,";",REPT(" ",99)),694,99)))-1),Materiales!$A$2:$E$502,5,FALSE)*VALUE(MID(TRIM(MID(SUBSTITUTE($V10,";",REPT(" ",99)),694,99)),FIND(":",TRIM(MID(SUBSTITUTE($V10,";",REPT(" ",99)),694,99)))+1,99)),0) + IFERROR(VLOOKUP(LEFT(TRIM(MID(SUBSTITUTE($V10,";",REPT(" ",99)),793,99)),FIND(":",TRIM(MID(SUBSTITUTE($V10,";",REPT(" ",99)),793,99)))-1),Materiales!$A$2:$E$502,5,FALSE)*VALUE(MID(TRIM(MID(SUBSTITUTE($V10,";",REPT(" ",99)),793,99)),FIND(":",TRIM(MID(SUBSTITUTE($V10,";",REPT(" ",99)),793,99)))+1,99)),0) + IFERROR(VLOOKUP(LEFT(TRIM(MID(SUBSTITUTE($V10,";",REPT(" ",99)),892,99)),FIND(":",TRIM(MID(SUBSTITUTE($V10,";",REPT(" ",99)),892,99)))-1),Materiales!$A$2:$E$502,5,FALSE)*VALUE(MID(TRIM(MID(SUBSTITUTE($V10,";",REPT(" ",99)),892,99)),FIND(":",TRIM(MID(SUBSTITUTE($V10,";",REPT(" ",99)),892,99)))+1,99)),0)))} -> 0 | X10: =IF($A10="","",SUM($G10,$H10,$K10,$N10,$Q10,$S10,$U10,$W10)) -> 2132.6246 | Y10: 3 | Z10: =X10*Y10 -> 6397.8738 | AA10: 0 | AB10: =AA10+Z10 -> 6397.8738 | AC10: 10000 | AD10: =AB10-X10 -> 4265.2492 | AE10: =AC10-X10 -> 7867.3754 | AF10: =AE10/AD10 -> 1.8445289
A11: Vela Oso xs | B11: CERA_MOLDE | C11: 1 | F11: 15 | G11: {=IF($A11="","",IFERROR($F11*(N($C11)*XLOOKUP($B11,Ceras!$A$2:$A$500,Ceras!$G$2:$G$500,0)+IF($D11="",0,N($E11)*XLOOKUP($D11,Ceras!$A$2:$A$500,Ceras!$G$2:$G$500,0))),"Revisar cera"))} -> 270 | H11: =F11*1.5 -> 22.5 | I11: PABILO4-6 | J11: 6 | K11: {=IF($A11="","",IFERROR($J11*XLOOKUP($I11,Pabilos!$A$2:$A$500,Pabilos!$H$2:$H$500,0),"Revisar pabilo"))} -> 108 | L11: ES_BEDOYA | M11: =F11/10 -> 1.5 | N11: {=IF($A11="","",IFERROR($M11*XLOOKUP($L11,Esencias!$A$2:$A$501,Esencias!$G$2:$G$501,0),"Revisar esencia"))} -> 211.26761 | O11: COLOR_CAFE | P11: 0.5 | Q11: {=IF($A11="","",IFERROR(IF($P11="",1,$P11)*XLOOKUP($O11,Colores!$A$2:$A$500,Colores!$H$2:$H$500,0),"Revisar color"))} -> 46.153846 | S11: {=IF($A11="","",IF($R11="",0,IFERROR(VLOOKUP(LEFT(TRIM(MID(SUBSTITUTE($R11,";",REPT(" ",99)),1,99)),FIND(":",TRIM(MID(SUBSTITUTE($R11,";",REPT(" ",99)),1,99)))-1),Materiales!$A$2:$E$502,5,FALSE)*VALUE(MID(TRIM(MID(SUBSTITUTE($R11,";",REPT(" ",99)),1,99)),FIND(":",TRIM(MID(SUBSTITUTE($R11,";",REPT(" ",99)),1,99)))+1,99)),0) + IFERROR(VLOOKUP(LEFT(TRIM(MID(SUBSTITUTE($R11,";",REPT(" ",99)),100,99)),FIND(":",TRIM(MID(SUBSTITUTE($R11,";",REPT(" ",99)),100,99)))-1),Materiales!$A$2:$E$502,5,FALSE)*VALUE(MID(TRIM(MID(SUBSTITUTE($R11,";",REPT(" ",99)),100,99)),FIND(":",TRIM(MID(SUBSTITUTE($R11,";",REPT(" ",99)),100,99)))+1,99)),0) + IFERROR(VLOOKUP(LEFT(TRIM(MID(SUBSTITUTE($R11,";",REPT(" ",99)),199,99)),FIND(":",TRIM(MID(SUBSTITUTE($R11,";",REPT(" ",99)),199,99)))-1),Materiales!$A$2:$E$502,5,FALSE)*VALUE(MID(TRIM(MID(SUBSTITUTE($R11,";",REPT(" ",99)),199,99)),FIND(":",TRIM(MID(SUBSTITUTE($R11,";",REPT(" ",99)),199,99)))+1,99)),0) + IFERROR(VLOOKUP(LEFT(TRIM(MID(SUBSTITUTE($R11,";",REPT(" ",99)),298,99)),FIND(":",TRIM(MID(SUBSTITUTE($R11,";",REPT(" ",99)),298,99)))-1),Materiales!$A$2:$E$502,5,FALSE)*VALUE(MID(TRIM(MID(SUBSTITUTE($R11,";",REPT(" ",99)),298,99)),FIND(":",TRIM(MID(SUBSTITUTE($R11,";",REPT(" ",99)),298,99)))+1,99)),0) + IFERROR(VLOOKUP(LEFT(TRIM(MID(SUBSTITUTE($R11,";",REPT(" ",99)),397,99)),FIND(":",TRIM(MID(SUBSTITUTE($R11,";",REPT(" ",99)),397,99)))-1),Materiales!$A$2:$E$502,5,FALSE)*VALUE(MID(TRIM(MID(SUBSTITUTE($R11,";",REPT(" ",99)),397,99)),FIND(":",TRIM(MID(SUBSTITUTE($R11,";",REPT(" ",99)),397,99)))+1,99)),0) + IFERROR(VLOOKUP(LEFT(TRIM(MID(SUBSTITUTE($R11,";",REPT(" ",99)),496,99)),FIND(":",TRIM(MID(SUBSTITUTE($R11,";",REPT(" ",99)),496,99)))-1),Materiales!$A$2:$E$502,5,FALSE)*VALUE(MID(TRIM(MID(SUBSTITUTE($R11,";",REPT(" ",99)),496,99)),FIND(":",TRIM(MID(SUBSTITUTE($R11,";",REPT(" ",99)),496,99)))+1,99)),0) + IFERROR(VLOOKUP(LEFT(TRIM(MID(SUBSTITUTE($R11,";",REPT(" ",99)),595,99)),FIND(":",TRIM(MID(SUBSTITUTE($R11,";",REPT(" ",99)),595,99)))-1),Materiales!$A$2:$E$502,5,FALSE)*VALUE(MID(TRIM(MID(SUBSTITUTE($R11,";",REPT(" ",99)),595,99)),FIND(":",TRIM(MID(SUBSTITUTE($R11,";",REPT(" ",99)),595,99)))+1,99)),0) + IFERROR(VLOOKUP(LEFT(TRIM(MID(SUBSTITUTE($R11,";",REPT(" ",99)),694,99)),FIND(":",TRIM(MID(SUBSTITUTE($R11,";",REPT(" ",99)),694,99)))-1),Materiales!$A$2:$E$502,5,FALSE)*VALUE(MID(TRIM(MID(SUBSTITUTE($R11,";",REPT(" ",99)),694,99)),FIND(":",TRIM(MID(SUBSTITUTE($R11,";",REPT(" ",99)),694,99)))+1,99)),0) + IFERROR(VLOOKUP(LEFT(TRIM(MID(SUBSTITUTE($R11,";",REPT(" ",99)),793,99)),FIND(":",TRIM(MID(SUBSTITUTE($R11,";",REPT(" ",99)),793,99)))-1),Materiales!$A$2:$E$502,5,FALSE)*VALUE(MID(TRIM(MID(SUBSTITUTE($R11,";",REPT(" ",99)),793,99)),FIND(":",TRIM(MID(SUBSTITUTE($R11,";",REPT(" ",99)),793,99)))+1,99)),0) + IFERROR(VLOOKUP(LEFT(TRIM(MID(SUBSTITUTE($R11,";",REPT(" ",99)),892,99)),FIND(":",TRIM(MID(SUBSTITUTE($R11,";",REPT(" ",99)),892,99)))-1),Materiales!$A$2:$E$502,5,FALSE)*VALUE(MID(TRIM(MID(SUBSTITUTE($R11,";",REPT(" ",99)),892,99)),FIND(":",TRIM(MID(SUBSTITUTE($R11,";",REPT(" ",99)),892,99)))+1,99)),0)))} -> 0 | U11: {=IF($A11="","",IF($T11="",0,IFERROR(VLOOKUP(LEFT(TRIM(MID(SUBSTITUTE($T11,";",REPT(" ",99)),1,99)),FIND(":",TRIM(MID(SUBSTITUTE($T11,";",REPT(" ",99)),1,99)))-1),Materiales!$A$2:$E$502,5,FALSE)*VALUE(MID(TRIM(MID(SUBSTITUTE($T11,";",REPT(" ",99)),1,99)),FIND(":",TRIM(MID(SUBSTITUTE($T11,";",REPT(" ",99)),1,99)))+1,99)),0) + IFERROR(VLOOKUP(LEFT(TRIM(MID(SUBSTITUTE($T11,";",REPT(" ",99)),100,99)),FIND(":",TRIM(MID(SUBSTITUTE($T11,";",REPT(" ",99)),100,99)))-1),Materiales!$A$2:$E$502,5,FALSE)*VALUE(MID(TRIM(MID(SUBSTITUTE($T11,";",REPT(" ",99)),100,99)),FIND(":",TRIM(MID(SUBSTITUTE($T11,";",REPT(" ",99)),100,99)))+1,99)),0) + IFERROR(VLOOKUP(LEFT(TRIM(MID(SUBSTITUTE($T11,";",REPT(" ",99)),199,99)),FIND(":",TRIM(MID(SUBSTITUTE($T11,";",REPT(" ",99)),199,99)))-1),Materiales!$A$2:$E$502,5,FALSE)*VALUE(MID(TRIM(MID(SUBSTITUTE($T11,";",REPT(" ",99)),199,99)),FIND(":",TRIM(MID(SUBSTITUTE($T11,";",REPT(" ",99)),199,99)))+1,99)),0) + IFERROR(VLOOKUP(LEFT(TRIM(MID(SUBSTITUTE($T11,";",REPT(" ",99)),298,99)),FIND(":",TRIM(MID(SUBSTITUTE($T11,";",REPT(" ",99)),298,99)))-1),Materiales!$A$2:$E$502,5,FALSE)*VALUE(MID(TRIM(MID(SUBSTITUTE($T11,";",REPT(" ",99)),298,99)),FIND(":",TRIM(MID(SUBSTITUTE($T11,";",REPT(" ",99)),298,99)))+1,99)),0) + IFERROR(VLOOKUP(LEFT(TRIM(MID(SUBSTITUTE($T11,";",REPT(" ",99)),397,99)),FIND(":",TRIM(MID(SUBSTITUTE($T11,";",REPT(" ",99)),397,99)))-1),Materiales!$A$2:$E$502,5,FALSE)*VALUE(MID(TRIM(MID(SUBSTITUTE($T11,";",REPT(" ",99)),397,99)),FIND(":",TRIM(MID(SUBSTITUTE($T11,";",REPT(" ",99)),397,99)))+1,99)),0) + IFERROR(VLOOKUP(LEFT(TRIM(MID(SUBSTITUTE($T11,";",REPT(" ",99)),496,99)),FIND(":",TRIM(MID(SUBSTITUTE($T11,";",REPT(" ",99)),496,99)))-1),Materiales!$A$2:$E$502,5,FALSE)*VALUE(MID(TRIM(MID(SUBSTITUTE($T11,";",REPT(" ",99)),496,99)),FIND(":",TRIM(MID(SUBSTITUTE($T11,";",REPT(" ",99)),496,99)))+1,99)),0) + IFERROR(VLOOKUP(LEFT(TRIM(MID(SUBSTITUTE($T11,";",REPT(" ",99)),595,99)),FIND(":",TRIM(MID(SUBSTITUTE($T11,";",REPT(" ",99)),595,99)))-1),Materiales!$A$2:$E$502,5,FALSE)*VALUE(MID(TRIM(MID(SUBSTITUTE($T11,";",REPT(" ",99)),595,99)),FIND(":",TRIM(MID(SUBSTITUTE($T11,";",REPT(" ",99)),595,99)))+1,99)),0) + IFERROR(VLOOKUP(LEFT(TRIM(MID(SUBSTITUTE($T11,";",REPT(" ",99)),694,99)),FIND(":",TRIM(MID(SUBSTITUTE($T11,";",REPT(" ",99)),694,99)))-1),Materiales!$A$2:$E$502,5,FALSE)*VALUE(MID(TRIM(MID(SUBSTITUTE($T11,";",REPT(" ",99)),694,99)),FIND(":",TRIM(MID(SUBSTITUTE($T11,";",REPT(" ",99)),694,99)))+1,99)),0) + IFERROR(VLOOKUP(LEFT(TRIM(MID(SUBSTITUTE($T11,";",REPT(" ",99)),793,99)),FIND(":",TRIM(MID(SUBSTITUTE($T11,";",REPT(" ",99)),793,99)))-1),Materiales!$A$2:$E$502,5,FALSE)*VALUE(MID(TRIM(MID(SUBSTITUTE($T11,";",REPT(" ",99)),793,99)),FIND(":",TRIM(MID(SUBSTITUTE($T11,";",REPT(" ",99)),793,99)))+1,99)),0) + IFERROR(VLOOKUP(LEFT(TRIM(MID(SUBSTITUTE($T11,";",REPT(" ",99)),892,99)),FIND(":",TRIM(MID(SUBSTITUTE($T11,";",REPT(" ",99)),892,99)))-1),Materiales!$A$2:$E$502,5,FALSE)*VALUE(MID(TRIM(MID(SUBSTITUTE($T11,";",REPT(" ",99)),892,99)),FIND(":",TRIM(MID(SUBSTITUTE($T11,";",REPT(" ",99)),892,99)))+1,99)),0)))} -> 0 | W11: {=IF($A11="","",IF($V11="",0,IFERROR(VLOOKUP(LEFT(TRIM(MID(SUBSTITUTE($V11,";",REPT(" ",99)),1,99)),FIND(":",TRIM(MID(SUBSTITUTE($V11,";",REPT(" ",99)),1,99)))-1),Materiales!$A$2:$E$502,5,FALSE)*VALUE(MID(TRIM(MID(SUBSTITUTE($V11,";",REPT(" ",99)),1,99)),FIND(":",TRIM(MID(SUBSTITUTE($V11,";",REPT(" ",99)),1,99)))+1,99)),0) + IFERROR(VLOOKUP(LEFT(TRIM(MID(SUBSTITUTE($V11,";",REPT(" ",99)),100,99)),FIND(":",TRIM(MID(SUBSTITUTE($V11,";",REPT(" ",99)),100,99)))-1),Materiales!$A$2:$E$502,5,FALSE)*VALUE(MID(TRIM(MID(SUBSTITUTE($V11,";",REPT(" ",99)),100,99)),FIND(":",TRIM(MID(SUBSTITUTE($V11,";",REPT(" ",99)),100,99)))+1,99)),0) + IFERROR(VLOOKUP(LEFT(TRIM(MID(SUBSTITUTE($V11,";",REPT(" ",99)),199,99)),FIND(":",TRIM(MID(SUBSTITUTE($V11,";",REPT(" ",99)),199,99)))-1),Materiales!$A$2:$E$502,5,FALSE)*VALUE(MID(TRIM(MID(SUBSTITUTE($V11,";",REPT(" ",99)),199,99)),FIND(":",TRIM(MID(SUBSTITUTE($V11,";",REPT(" ",99)),199,99)))+1,99)),0) + IFERROR(VLOOKUP(LEFT(TRIM(MID(SUBSTITUTE($V11,";",REPT(" ",99)),298,99)),FIND(":",TRIM(MID(SUBSTITUTE($V11,";",REPT(" ",99)),298,99)))-1),Materiales!$A$2:$E$502,5,FALSE)*VALUE(MID(TRIM(MID(SUBSTITUTE($V11,";",REPT(" ",99)),298,99)),FIND(":",TRIM(MID(SUBSTITUTE($V11,";",REPT(" ",99)),298,99)))+1,99)),0) + IFERROR(VLOOKUP(LEFT(TRIM(MID(SUBSTITUTE($V11,";",REPT(" ",99)),397,99)),FIND(":",TRIM(MID(SUBSTITUTE($V11,";",REPT(" ",99)),397,99)))-1),Materiales!$A$2:$E$502,5,FALSE)*VALUE(MID(TRIM(MID(SUBSTITUTE($V11,";",REPT(" ",99)),397,99)),FIND(":",TRIM(MID(SUBSTITUTE($V11,";",REPT(" ",99)),397,99)))+1,99)),0) + IFERROR(VLOOKUP(LEFT(TRIM(MID(SUBSTITUTE($V11,";",REPT(" ",99)),496,99)),FIND(":",TRIM(MID(SUBSTITUTE($V11,";",REPT(" ",99)),496,99)))-1),Materiales!$A$2:$E$502,5,FALSE)*VALUE(MID(TRIM(MID(SUBSTITUTE($V11,";",REPT(" ",99)),496,99)),FIND(":",TRIM(MID(SUBSTITUTE($V11,";",REPT(" ",99)),496,99)))+1,99)),0) + IFERROR(VLOOKUP(LEFT(TRIM(MID(SUBSTITUTE($V11,";",REPT(" ",99)),595,99)),FIND(":",TRIM(MID(SUBSTITUTE($V11,";",REPT(" ",99)),595,99)))-1),Materiales!$A$2:$E$502,5,FALSE)*VALUE(MID(TRIM(MID(SUBSTITUTE($V11,";",REPT(" ",99)),595,99)),FIND(":",TRIM(MID(SUBSTITUTE($V11,";",REPT(" ",99)),595,99)))+1,99)),0) + IFERROR(VLOOKUP(LEFT(TRIM(MID(SUBSTITUTE($V11,";",REPT(" ",99)),694,99)),FIND(":",TRIM(MID(SUBSTITUTE($V11,";",REPT(" ",99)),694,99)))-1),Materiales!$A$2:$E$502,5,FALSE)*VALUE(MID(TRIM(MID(SUBSTITUTE($V11,";",REPT(" ",99)),694,99)),FIND(":",TRIM(MID(SUBSTITUTE($V11,";",REPT(" ",99)),694,99)))+1,99)),0) + IFERROR(VLOOKUP(LEFT(TRIM(MID(SUBSTITUTE($V11,";",REPT(" ",99)),793,99)),FIND(":",TRIM(MID(SUBSTITUTE($V11,";",REPT(" ",99)),793,99)))-1),Materiales!$A$2:$E$502,5,FALSE)*VALUE(MID(TRIM(MID(SUBSTITUTE($V11,";",REPT(" ",99)),793,99)),FIND(":",TRIM(MID(SUBSTITUTE($V11,";",REPT(" ",99)),793,99)))+1,99)),0) + IFERROR(VLOOKUP(LEFT(TRIM(MID(SUBSTITUTE($V11,";",REPT(" ",99)),892,99)),FIND(":",TRIM(MID(SUBSTITUTE($V11,";",REPT(" ",99)),892,99)))-1),Materiales!$A$2:$E$502,5,FALSE)*VALUE(MID(TRIM(MID(SUBSTITUTE($V11,";",REPT(" ",99)),892,99)),FIND(":",TRIM(MID(SUBSTITUTE($V11,";",REPT(" ",99)),892,99)))+1,99)),0)))} -> 0 | X11: =IF($A11="","",SUM($G11,$H11,$K11,$N11,$Q11,$S11,$U11,$W11)) -> 657.92145 | Y11: 3 | Z11: =X11*Y11 -> 1973.7644 | AA11: 0 | AB11: =AA11+Z11 -> 1973.7644 | AC11: 4000 | AD11: =AB11-X11 -> 1315.8429 | AE11: =AC11-X11 -> 3342.0785 | AF11: =AE11/AD11 -> 2.5398766
A12: Vela Repollo | B12: CERA_MOLDE | C12: 1 | F12: 18 | G12: {=IF($A12="","",IFERROR($F12*(N($C12)*XLOOKUP($B12,Ceras!$A$2:$A$500,Ceras!$G$2:$G$500,0)+IF($D12="",0,N($E12)*XLOOKUP($D12,Ceras!$A$2:$A$500,Ceras!$G$2:$G$500,0))),"Revisar cera"))} -> 324 | H12: =F12*1.5 -> 27 | I12: PABILO4-6 | J12: 4 | K12: {=IF($A12="","",IFERROR($J12*XLOOKUP($I12,Pabilos!$A$2:$A$500,Pabilos!$H$2:$H$500,0),"Revisar pabilo"))} -> 72 | L12: ES_BEDOYA | M12: =F12/10 -> 1.8 | N12: {=IF($A12="","",IFERROR($M12*XLOOKUP($L12,Esencias!$A$2:$A$501,Esencias!$G$2:$G$501,0),"Revisar esencia"))} -> 253.52113 | O12: COLOR_CAFE | P12: 0.5 | Q12: {=IF($A12="","",IFERROR(IF($P12="",1,$P12)*XLOOKUP($O12,Colores!$A$2:$A$500,Colores!$H$2:$H$500,0),"Revisar color"))} -> 46.153846 | S12: {=IF($A12="","",IF($R12="",0,IFERROR(VLOOKUP(LEFT(TRIM(MID(SUBSTITUTE($R12,";",REPT(" ",99)),1,99)),FIND(":",TRIM(MID(SUBSTITUTE($R12,";",REPT(" ",99)),1,99)))-1),Materiales!$A$2:$E$502,5,FALSE)*VALUE(MID(TRIM(MID(SUBSTITUTE($R12,";",REPT(" ",99)),1,99)),FIND(":",TRIM(MID(SUBSTITUTE($R12,";",REPT(" ",99)),1,99)))+1,99)),0) + IFERROR(VLOOKUP(LEFT(TRIM(MID(SUBSTITUTE($R12,";",REPT(" ",99)),100,99)),FIND(":",TRIM(MID(SUBSTITUTE($R12,";",REPT(" ",99)),100,99)))-1),Materiales!$A$2:$E$502,5,FALSE)*VALUE(MID(TRIM(MID(SUBSTITUTE($R12,";",REPT(" ",99)),100,99)),FIND(":",TRIM(MID(SUBSTITUTE($R12,";",REPT(" ",99)),100,99)))+1,99)),0) + IFERROR(VLOOKUP(LEFT(TRIM(MID(SUBSTITUTE($R12,";",REPT(" ",99)),199,99)),FIND(":",TRIM(MID(SUBSTITUTE($R12,";",REPT(" ",99)),199,99)))-1),Materiales!$A$2:$E$502,5,FALSE)*VALUE(MID(TRIM(MID(SUBSTITUTE($R12,";",REPT(" ",99)),199,99)),FIND(":",TRIM(MID(SUBSTITUTE($R12,";",REPT(" ",99)),199,99)))+1,99)),0) + IFERROR(VLOOKUP(LEFT(TRIM(MID(SUBSTITUTE($R12,";",REPT(" ",99)),298,99)),FIND(":",TRIM(MID(SUBSTITUTE($R12,";",REPT(" ",99)),298,99)))-1),Materiales!$A$2:$E$502,5,FALSE)*VALUE(MID(TRIM(MID(SUBSTITUTE($R12,";",REPT(" ",99)),298,99)),FIND(":",TRIM(MID(SUBSTITUTE($R12,";",REPT(" ",99)),298,99)))+1,99)),0) + IFERROR(VLOOKUP(LEFT(TRIM(MID(SUBSTITUTE($R12,";",REPT(" ",99)),397,99)),FIND(":",TRIM(MID(SUBSTITUTE($R12,";",REPT(" ",99)),397,99)))-1),Materiales!$A$2:$E$502,5,FALSE)*VALUE(MID(TRIM(MID(SUBSTITUTE($R12,";",REPT(" ",99)),397,99)),FIND(":",TRIM(MID(SUBSTITUTE($R12,";",REPT(" ",99)),397,99)))+1,99)),0) + IFERROR(VLOOKUP(LEFT(TRIM(MID(SUBSTITUTE($R12,";",REPT(" ",99)),496,99)),FIND(":",TRIM(MID(SUBSTITUTE($R12,";",REPT(" ",99)),496,99)))-1),Materiales!$A$2:$E$502,5,FALSE)*VALUE(MID(TRIM(MID(SUBSTITUTE($R12,";",REPT(" ",99)),496,99)),FIND(":",TRIM(MID(SUBSTITUTE($R12,";",REPT(" ",99)),496,99)))+1,99)),0) + IFERROR(VLOOKUP(LEFT(TRIM(MID(SUBSTITUTE($R12,";",REPT(" ",99)),595,99)),FIND(":",TRIM(MID(SUBSTITUTE($R12,";",REPT(" ",99)),595,99)))-1),Materiales!$A$2:$E$502,5,FALSE)*VALUE(MID(TRIM(MID(SUBSTITUTE($R12,";",REPT(" ",99)),595,99)),FIND(":",TRIM(MID(SUBSTITUTE($R12,";",REPT(" ",99)),595,99)))+1,99)),0) + IFERROR(VLOOKUP(LEFT(TRIM(MID(SUBSTITUTE($R12,";",REPT(" ",99)),694,99)),FIND(":",TRIM(MID(SUBSTITUTE($R12,";",REPT(" ",99)),694,99)))-1),Materiales!$A$2:$E$502,5,FALSE)*VALUE(MID(TRIM(MID(SUBSTITUTE($R12,";",REPT(" ",99)),694,99)),FIND(":",TRIM(MID(SUBSTITUTE($R12,";",REPT(" ",99)),694,99)))+1,99)),0) + IFERROR(VLOOKUP(LEFT(TRIM(MID(SUBSTITUTE($R12,";",REPT(" ",99)),793,99)),FIND(":",TRIM(MID(SUBSTITUTE($R12,";",REPT(" ",99)),793,99)))-1),Materiales!$A$2:$E$502,5,FALSE)*VALUE(MID(TRIM(MID(SUBSTITUTE($R12,";",REPT(" ",99)),793,99)),FIND(":",TRIM(MID(SUBSTITUTE($R12,";",REPT(" ",99)),793,99)))+1,99)),0) + IFERROR(VLOOKUP(LEFT(TRIM(MID(SUBSTITUTE($R12,";",REPT(" ",99)),892,99)),FIND(":",TRIM(MID(SUBSTITUTE($R12,";",REPT(" ",99)),892,99)))-1),Materiales!$A$2:$E$502,5,FALSE)*VALUE(MID(TRIM(MID(SUBSTITUTE($R12,";",REPT(" ",99)),892,99)),FIND(":",TRIM(MID(SUBSTITUTE($R12,";",REPT(" ",99)),892,99)))+1,99)),0)))} -> 0 | U12: {=IF($A12="","",IF($T12="",0,IFERROR(VLOOKUP(LEFT(TRIM(MID(SUBSTITUTE($T12,";",REPT(" ",99)),1,99)),FIND(":",TRIM(MID(SUBSTITUTE($T12,";",REPT(" ",99)),1,99)))-1),Materiales!$A$2:$E$502,5,FALSE)*VALUE(MID(TRIM(MID(SUBSTITUTE($T12,";",REPT(" ",99)),1,99)),FIND(":",TRIM(MID(SUBSTITUTE($T12,";",REPT(" ",99)),1,99)))+1,99)),0) + IFERROR(VLOOKUP(LEFT(TRIM(MID(SUBSTITUTE($T12,";",REPT(" ",99)),100,99)),FIND(":",TRIM(MID(SUBSTITUTE($T12,";",REPT(" ",99)),100,99)))-1),Materiales!$A$2:$E$502,5,FALSE)*VALUE(MID(TRIM(MID(SUBSTITUTE($T12,";",REPT(" ",99)),100,99)),FIND(":",TRIM(MID(SUBSTITUTE($T12,";",REPT(" ",99)),100,99)))+1,99)),0) + IFERROR(VLOOKUP(LEFT(TRIM(MID(SUBSTITUTE($T12,";",REPT(" ",99)),199,99)),FIND(":",TRIM(MID(SUBSTITUTE($T12,";",REPT(" ",99)),199,99)))-1),Materiales!$A$2:$E$502,5,FALSE)*VALUE(MID(TRIM(MID(SUBSTITUTE($T12,";",REPT(" ",99)),199,99)),FIND(":",TRIM(MID(SUBSTITUTE($T12,";",REPT(" ",99)),199,99)))+1,99)),0) + IFERROR(VLOOKUP(LEFT(TRIM(MID(SUBSTITUTE($T12,";",REPT(" ",99)),298,99)),FIND(":",TRIM(MID(SUBSTITUTE($T12,";",REPT(" ",99)),298,99)))-1),Materiales!$A$2:$E$502,5,FALSE)*VALUE(MID(TRIM(MID(SUBSTITUTE($T12,";",REPT(" ",99)),298,99)),FIND(":",TRIM(MID(SUBSTITUTE($T12,";",REPT(" ",99)),298,99)))+1,99)),0) + IFERROR(VLOOKUP(LEFT(TRIM(MID(SUBSTITUTE($T12,";",REPT(" ",99)),397,99)),FIND(":",TRIM(MID(SUBSTITUTE($T12,";",REPT(" ",99)),397,99)))-1),Materiales!$A$2:$E$502,5,FALSE)*VALUE(MID(TRIM(MID(SUBSTITUTE($T12,";",REPT(" ",99)),397,99)),FIND(":",TRIM(MID(SUBSTITUTE($T12,";",REPT(" ",99)),397,99)))+1,99)),0) + IFERROR(VLOOKUP(LEFT(TRIM(MID(SUBSTITUTE($T12,";",REPT(" ",99)),496,99)),FIND(":",TRIM(MID(SUBSTITUTE($T12,";",REPT(" ",99)),496,99)))-1),Materiales!$A$2:$E$502,5,FALSE)*VALUE(MID(TRIM(MID(SUBSTITUTE($T12,";",REPT(" ",99)),496,99)),FIND(":",TRIM(MID(SUBSTITUTE($T12,";",REPT(" ",99)),496,99)))+1,99)),0) + IFERROR(VLOOKUP(LEFT(TRIM(MID(SUBSTITUTE($T12,";",REPT(" ",99)),595,99)),FIND(":",TRIM(MID(SUBSTITUTE($T12,";",REPT(" ",99)),595,99)))-1),Materiales!$A$2:$E$502,5,FALSE)*VALUE(MID(TRIM(MID(SUBSTITUTE($T12,";",REPT(" ",99)),595,99)),FIND(":",TRIM(MID(SUBSTITUTE($T12,";",REPT(" ",99)),595,99)))+1,99)),0) + IFERROR(VLOOKUP(LEFT(TRIM(MID(SUBSTITUTE($T12,";",REPT(" ",99)),694,99)),FIND(":",TRIM(MID(SUBSTITUTE($T12,";",REPT(" ",99)),694,99)))-1),Materiales!$A$2:$E$502,5,FALSE)*VALUE(MID(TRIM(MID(SUBSTITUTE($T12,";",REPT(" ",99)),694,99)),FIND(":",TRIM(MID(SUBSTITUTE($T12,";",REPT(" ",99)),694,99)))+1,99)),0) + IFERROR(VLOOKUP(LEFT(TRIM(MID(SUBSTITUTE($T12,";",REPT(" ",99)),793,99)),FIND(":",TRIM(MID(SUBSTITUTE($T12,";",REPT(" ",99)),793,99)))-1),Materiales!$A$2:$E$502,5,FALSE)*VALUE(MID(TRIM(MID(SUBSTITUTE($T12,";",REPT(" ",99)),793,99)),FIND(":",TRIM(MID(SUBSTITUTE($T12,";",REPT(" ",99)),793,99)))+1,99)),0) + IFERROR(VLOOKUP(LEFT(TRIM(MID(SUBSTITUTE($T12,";",REPT(" ",99)),892,99)),FIND(":",TRIM(MID(SUBSTITUTE($T12,";",REPT(" ",99)),892,99)))-1),Materiales!$A$2:$E$502,5,FALSE)*VALUE(MID(TRIM(MID(SUBSTITUTE($T12,";",REPT(" ",99)),892,99)),FIND(":",TRIM(MID(SUBSTITUTE($T12,";",REPT(" ",99)),892,99)))+1,99)),0)))} -> 0 | W12: {=IF($A12="","",IF($V12="",0,IFERROR(VLOOKUP(LEFT(TRIM(MID(SUBSTITUTE($V12,";",REPT(" ",99)),1,99)),FIND(":",TRIM(MID(SUBSTITUTE($V12,";",REPT(" ",99)),1,99)))-1),Materiales!$A$2:$E$502,5,FALSE)*VALUE(MID(TRIM(MID(SUBSTITUTE($V12,";",REPT(" ",99)),1,99)),FIND(":",TRIM(MID(SUBSTITUTE($V12,";",REPT(" ",99)),1,99)))+1,99)),0) + IFERROR(VLOOKUP(LEFT(TRIM(MID(SUBSTITUTE($V12,";",REPT(" ",99)),100,99)),FIND(":",TRIM(MID(SUBSTITUTE($V12,";",REPT(" ",99)),100,99)))-1),Materiales!$A$2:$E$502,5,FALSE)*VALUE(MID(TRIM(MID(SUBSTITUTE($V12,";",REPT(" ",99)),100,99)),FIND(":",TRIM(MID(SUBSTITUTE($V12,";",REPT(" ",99)),100,99)))+1,99)),0) + IFERROR(VLOOKUP(LEFT(TRIM(MID(SUBSTITUTE($V12,";",REPT(" ",99)),199,99)),FIND(":",TRIM(MID(SUBSTITUTE($V12,";",REPT(" ",99)),199,99)))-1),Materiales!$A$2:$E$502,5,FALSE)*VALUE(MID(TRIM(MID(SUBSTITUTE($V12,";",REPT(" ",99)),199,99)),FIND(":",TRIM(MID(SUBSTITUTE($V12,";",REPT(" ",99)),199,99)))+1,99)),0) + IFERROR(VLOOKUP(LEFT(TRIM(MID(SUBSTITUTE($V12,";",REPT(" ",99)),298,99)),FIND(":",TRIM(MID(SUBSTITUTE($V12,";",REPT(" ",99)),298,99)))-1),Materiales!$A$2:$E$502,5,FALSE)*VALUE(MID(TRIM(MID(SUBSTITUTE($V12,";",REPT(" ",99)),298,99)),FIND(":",TRIM(MID(SUBSTITUTE($V12,";",REPT(" ",99)),298,99)))+1,99)),0) + IFERROR(VLOOKUP(LEFT(TRIM(MID(SUBSTITUTE($V12,";",REPT(" ",99)),397,99)),FIND(":",TRIM(MID(SUBSTITUTE($V12,";",REPT(" ",99)),397,99)))-1),Materiales!$A$2:$E$502,5,FALSE)*VALUE(MID(TRIM(MID(SUBSTITUTE($V12,";",REPT(" ",99)),397,99)),FIND(":",TRIM(MID(SUBSTITUTE($V12,";",REPT(" ",99)),397,99)))+1,99)),0) + IFERROR(VLOOKUP(LEFT(TRIM(MID(SUBSTITUTE($V12,";",REPT(" ",99)),496,99)),FIND(":",TRIM(MID(SUBSTITUTE($V12,";",REPT(" ",99)),496,99)))-1),Materiales!$A$2:$E$502,5,FALSE)*VALUE(MID(TRIM(MID(SUBSTITUTE($V12,";",REPT(" ",99)),496,99)),FIND(":",TRIM(MID(SUBSTITUTE($V12,";",REPT(" ",99)),496,99)))+1,99)),0) + IFERROR(VLOOKUP(LEFT(TRIM(MID(SUBSTITUTE($V12,";",REPT(" ",99)),595,99)),FIND(":",TRIM(MID(SUBSTITUTE($V12,";",REPT(" ",99)),595,99)))-1),Materiales!$A$2:$E$502,5,FALSE)*VALUE(MID(TRIM(MID(SUBSTITUTE($V12,";",REPT(" ",99)),595,99)),FIND(":",TRIM(MID(SUBSTITUTE($V12,";",REPT(" ",99)),595,99)))+1,99)),0) + IFERROR(VLOOKUP(LEFT(TRIM(MID(SUBSTITUTE($V12,";",REPT(" ",99)),694,99)),FIND(":",TRIM(MID(SUBSTITUTE($V12,";",REPT(" ",99)),694,99)))-1),Materiales!$A$2:$E$502,5,FALSE)*VALUE(MID(TRIM(MID(SUBSTITUTE($V12,";",REPT(" ",99)),694,99)),FIND(":",TRIM(MID(SUBSTITUTE($V12,";",REPT(" ",99)),694,99)))+1,99)),0) + IFERROR(VLOOKUP(LEFT(TRIM(MID(SUBSTITUTE($V12,";",REPT(" ",99)),793,99)),FIND(":",TRIM(MID(SUBSTITUTE($V12,";",REPT(" ",99)),793,99)))-1),Materiales!$A$2:$E$502,5,FALSE)*VALUE(MID(TRIM(MID(SUBSTITUTE($V12,";",REPT(" ",99)),793,99)),FIND(":",TRIM(MID(SUBSTITUTE($V12,";",REPT(" ",99)),793,99)))+1,99)),0) + IFERROR(VLOOKUP(LEFT(TRIM(MID(SUBSTITUTE($V12,";",REPT(" ",99)),892,99)),FIND(":",TRIM(MID(SUBSTITUTE($V12,";",REPT(" ",99)),892,99)))-1),Materiales!$A$2:$E$502,5,FALSE)*VALUE(MID(TRIM(MID(SUBSTITUTE($V12,";",REPT(" ",99)),892,99)),FIND(":",TRIM(MID(SUBSTITUTE($V12,";",REPT(" ",99)),892,99)))+1,99)),0)))} -> 0 | X12: =IF($A12="","",SUM($G12,$H12,$K12,$N12,$Q12,$S12,$U12,$W12)) -> 722.67497 | Y12: 3 | Z12: =X12*Y12 -> 2168.0249 | AA12: 0 | AB12: =AA12+Z12 -> 2168.0249 | AC12: 2000 | AD12: =AB12-X12 -> 1445.3499 | AE12: =AC12-X12 -> 1277.325 | AF12: =AE12/AD12 -> 0.88374793
A13: Vela cactus mediana | B13: CERA_MOLDE | C13: 1 | F13: 36 | G13: {=IF($A13="","",IFERROR($F13*(N($C13)*XLOOKUP($B13,Ceras!$A$2:$A$500,Ceras!$G$2:$G$500,0)+IF($D13="",0,N($E13)*XLOOKUP($D13,Ceras!$A$2:$A$500,Ceras!$G$2:$G$500,0))),"Revisar cera"))} -> 648 | H13: =F13*1.5 -> 54 | I13: PABILO4-6 | J13: 4.5 | K13: {=IF($A13="","",IFERROR($J13*XLOOKUP($I13,Pabilos!$A$2:$A$500,Pabilos!$H$2:$H$500,0),"Revisar pabilo"))} -> 81 | L13: ES_BEDOYA | M13: =F13/10 -> 3.6 | N13: {=IF($A13="","",IFERROR($M13*XLOOKUP($L13,Esencias!$A$2:$A$501,Esencias!$G$2:$G$501,0),"Revisar esencia"))} -> 507.04225 | O13: COLOR_CAFE | P13: 0.5 | Q13: {=IF($A13="","",IFERROR(IF($P13="",1,$P13)*XLOOKUP($O13,Colores!$A$2:$A$500,Colores!$H$2:$H$500,0),"Revisar color"))} -> 46.153846 | S13: {=IF($A13="","",IF($R13="",0,IFERROR(VLOOKUP(LEFT(TRIM(MID(SUBSTITUTE($R13,";",REPT(" ",99)),1,99)),FIND(":",TRIM(MID(SUBSTITUTE($R13,";",REPT(" ",99)),1,99)))-1),Materiales!$A$2:$E$502,5,FALSE)*VALUE(MID(TRIM(MID(SUBSTITUTE($R13,";",REPT(" ",99)),1,99)),FIND(":",TRIM(MID(SUBSTITUTE($R13,";",REPT(" ",99)),1,99)))+1,99)),0) + IFERROR(VLOOKUP(LEFT(TRIM(MID(SUBSTITUTE($R13,";",REPT(" ",99)),100,99)),FIND(":",TRIM(MID(SUBSTITUTE($R13,";",REPT(" ",99)),100,99)))-1),Materiales!$A$2:$E$502,5,FALSE)*VALUE(MID(TRIM(MID(SUBSTITUTE($R13,";",REPT(" ",99)),100,99)),FIND(":",TRIM(MID(SUBSTITUTE($R13,";",REPT(" ",99)),100,99)))+1,99)),0) + IFERROR(VLOOKUP(LEFT(TRIM(MID(SUBSTITUTE($R13,";",REPT(" ",99)),199,99)),FIND(":",TRIM(MID(SUBSTITUTE($R13,";",REPT(" ",99)),199,99)))-1),Materiales!$A$2:$E$502,5,FALSE)*VALUE(MID(TRIM(MID(SUBSTITUTE($R13,";",REPT(" ",99)),199,99)),FIND(":",TRIM(MID(SUBSTITUTE($R13,";",REPT(" ",99)),199,99)))+1,99)),0) + IFERROR(VLOOKUP(LEFT(TRIM(MID(SUBSTITUTE($R13,";",REPT(" ",99)),298,99)),FIND(":",TRIM(MID(SUBSTITUTE($R13,";",REPT(" ",99)),298,99)))-1),Materiales!$A$2:$E$502,5,FALSE)*VALUE(MID(TRIM(MID(SUBSTITUTE($R13,";",REPT(" ",99)),298,99)),FIND(":",TRIM(MID(SUBSTITUTE($R13,";",REPT(" ",99)),298,99)))+1,99)),0) + IFERROR(VLOOKUP(LEFT(TRIM(MID(SUBSTITUTE($R13,";",REPT(" ",99)),397,99)),FIND(":",TRIM(MID(SUBSTITUTE($R13,";",REPT(" ",99)),397,99)))-1),Materiales!$A$2:$E$502,5,FALSE)*VALUE(MID(TRIM(MID(SUBSTITUTE($R13,";",REPT(" ",99)),397,99)),FIND(":",TRIM(MID(SUBSTITUTE($R13,";",REPT(" ",99)),397,99)))+1,99)),0) + IFERROR(VLOOKUP(LEFT(TRIM(MID(SUBSTITUTE($R13,";",REPT(" ",99)),496,99)),FIND(":",TRIM(MID(SUBSTITUTE($R13,";",REPT(" ",99)),496,99)))-1),Materiales!$A$2:$E$502,5,FALSE)*VALUE(MID(TRIM(MID(SUBSTITUTE($R13,";",REPT(" ",99)),496,99)),FIND(":",TRIM(MID(SUBSTITUTE($R13,";",REPT(" ",99)),496,99)))+1,99)),0) + IFERROR(VLOOKUP(LEFT(TRIM(MID(SUBSTITUTE($R13,";",REPT(" ",99)),595,99)),FIND(":",TRIM(MID(SUBSTITUTE($R13,";",REPT(" ",99)),595,99)))-1),Materiales!$A$2:$E$502,5,FALSE)*VALUE(MID(TRIM(MID(SUBSTITUTE($R13,";",REPT(" ",99)),595,99)),FIND(":",TRIM(MID(SUBSTITUTE($R13,";",REPT(" ",99)),595,99)))+1,99)),0) + IFERROR(VLOOKUP(LEFT(TRIM(MID(SUBSTITUTE($R13,";",REPT(" ",99)),694,99)),FIND(":",TRIM(MID(SUBSTITUTE($R13,";",REPT(" ",99)),694,99)))-1),Materiales!$A$2:$E$502,5,FALSE)*VALUE(MID(TRIM(MID(SUBSTITUTE($R13,";",REPT(" ",99)),694,99)),FIND(":",TRIM(MID(SUBSTITUTE($R13,";",REPT(" ",99)),694,99)))+1,99)),0) + IFERROR(VLOOKUP(LEFT(TRIM(MID(SUBSTITUTE($R13,";",REPT(" ",99)),793,99)),FIND(":",TRIM(MID(SUBSTITUTE($R13,";",REPT(" ",99)),793,99)))-1),Materiales!$A$2:$E$502,5,FALSE)*VALUE(MID(TRIM(MID(SUBSTITUTE($R13,";",REPT(" ",99)),793,99)),FIND(":",TRIM(MID(SUBSTITUTE($R13,";",REPT(" ",99)),793,99)))+1,99)),0) + IFERROR(VLOOKUP(LEFT(TRIM(MID(SUBSTITUTE($R13,";",REPT(" ",99)),892,99)),FIND(":",TRIM(MID(SUBSTITUTE($R13,";",REPT(" ",99)),892,99)))-1),Materiales!$A$2:$E$502,5,FALSE)*VALUE(MID(TRIM(MID(SUBSTITUTE($R13,";",REPT(" ",99)),892,99)),FIND(":",TRIM(MID(SUBSTITUTE($R13,";",REPT(" ",99)),892,99)))+1,99)),0)))} -> 0 | U13: {=IF($A13="","",IF($T13="",0,IFERROR(VLOOKUP(LEFT(TRIM(MID(SUBSTITUTE($T13,";",REPT(" ",99)),1,99)),FIND(":",TRIM(MID(SUBSTITUTE($T13,";",REPT(" ",99)),1,99)))-1),Materiales!$A$2:$E$502,5,FALSE)*VALUE(MID(TRIM(MID(SUBSTITUTE($T13,";",REPT(" ",99)),1,99)),FIND(":",TRIM(MID(SUBSTITUTE($T13,";",REPT(" ",99)),1,99)))+1,99)),0) + IFERROR(VLOOKUP(LEFT(TRIM(MID(SUBSTITUTE($T13,";",REPT(" ",99)),100,99)),FIND(":",TRIM(MID(SUBSTITUTE($T13,";",REPT(" ",99)),100,99)))-1),Materiales!$A$2:$E$502,5,FALSE)*VALUE(MID(TRIM(MID(SUBSTITUTE($T13,";",REPT(" ",99)),100,99)),FIND(":",TRIM(MID(SUBSTITUTE($T13,";",REPT(" ",99)),100,99)))+1,99)),0) + IFERROR(VLOOKUP(LEFT(TRIM(MID(SUBSTITUTE($T13,";",REPT(" ",99)),199,99)),FIND(":",TRIM(MID(SUBSTITUTE($T13,";",REPT(" ",99)),199,99)))-1),Materiales!$A$2:$E$502,5,FALSE)*VALUE(MID(TRIM(MID(SUBSTITUTE($T13,";",REPT(" ",99)),199,99)),FIND(":",TRIM(MID(SUBSTITUTE($T13,";",REPT(" ",99)),199,99)))+1,99)),0) + IFERROR(VLOOKUP(LEFT(TRIM(MID(SUBSTITUTE($T13,";",REPT(" ",99)),298,99)),FIND(":",TRIM(MID(SUBSTITUTE($T13,";",REPT(" ",99)),298,99)))-1),Materiales!$A$2:$E$502,5,FALSE)*VALUE(MID(TRIM(MID(SUBSTITUTE($T13,";",REPT(" ",99)),298,99)),FIND(":",TRIM(MID(SUBSTITUTE($T13,";",REPT(" ",99)),298,99)))+1,99)),0) + IFERROR(VLOOKUP(LEFT(TRIM(MID(SUBSTITUTE($T13,";",REPT(" ",99)),397,99)),FIND(":",TRIM(MID(SUBSTITUTE($T13,";",REPT(" ",99)),397,99)))-1),Materiales!$A$2:$E$502,5,FALSE)*VALUE(MID(TRIM(MID(SUBSTITUTE($T13,";",REPT(" ",99)),397,99)),FIND(":",TRIM(MID(SUBSTITUTE($T13,";",REPT(" ",99)),397,99)))+1,99)),0) + IFERROR(VLOOKUP(LEFT(TRIM(MID(SUBSTITUTE($T13,";",REPT(" ",99)),496,99)),FIND(":",TRIM(MID(SUBSTITUTE($T13,";",REPT(" ",99)),496,99)))-1),Materiales!$A$2:$E$502,5,FALSE)*VALUE(MID(TRIM(MID(SUBSTITUTE($T13,";",REPT(" ",99)),496,99)),FIND(":",TRIM(MID(SUBSTITUTE($T13,";",REPT(" ",99)),496,99)))+1,99)),0) + IFERROR(VLOOKUP(LEFT(TRIM(MID(SUBSTITUTE($T13,";",REPT(" ",99)),595,99)),FIND(":",TRIM(MID(SUBSTITUTE($T13,";",REPT(" ",99)),595,99)))-1),Materiales!$A$2:$E$502,5,FALSE)*VALUE(MID(TRIM(MID(SUBSTITUTE($T13,";",REPT(" ",99)),595,99)),FIND(":",TRIM(MID(SUBSTITUTE($T13,";",REPT(" ",99)),595,99)))+1,99)),0) + IFERROR(VLOOKUP(LEFT(TRIM(MID(SUBSTITUTE($T13,";",REPT(" ",99)),694,99)),FIND(":",TRIM(MID(SUBSTITUTE($T13,";",REPT(" ",99)),694,99)))-1),Materiales!$A$2:$E$502,5,FALSE)*VALUE(MID(TRIM(MID(SUBSTITUTE($T13,";",REPT(" ",99)),694,99)),FIND(":",TRIM(MID(SUBSTITUTE($T13,";",REPT(" ",99)),694,99)))+1,99)),0) + IFERROR(VLOOKUP(LEFT(TRIM(MID(SUBSTITUTE($T13,";",REPT(" ",99)),793,99)),FIND(":",TRIM(MID(SUBSTITUTE($T13,";",REPT(" ",99)),793,99)))-1),Materiales!$A$2:$E$502,5,FALSE)*VALUE(MID(TRIM(MID(SUBSTITUTE($T13,";",REPT(" ",99)),793,99)),FIND(":",TRIM(MID(SUBSTITUTE($T13,";",REPT(" ",99)),793,99)))+1,99)),0) + IFERROR(VLOOKUP(LEFT(TRIM(MID(SUBSTITUTE($T13,";",REPT(" ",99)),892,99)),FIND(":",TRIM(MID(SUBSTITUTE($T13,";",REPT(" ",99)),892,99)))-1),Materiales!$A$2:$E$502,5,FALSE)*VALUE(MID(TRIM(MID(SUBSTITUTE($T13,";",REPT(" ",99)),892,99)),FIND(":",TRIM(MID(SUBSTITUTE($T13,";",REPT(" ",99)),892,99)))+1,99)),0)))} -> 0 | W13: {=IF($A13="","",IF($V13="",0,IFERROR(VLOOKUP(LEFT(TRIM(MID(SUBSTITUTE($V13,";",REPT(" ",99)),1,99)),FIND(":",TRIM(MID(SUBSTITUTE($V13,";",REPT(" ",99)),1,99)))-1),Materiales!$A$2:$E$502,5,FALSE)*VALUE(MID(TRIM(MID(SUBSTITUTE($V13,";",REPT(" ",99)),1,99)),FIND(":",TRIM(MID(SUBSTITUTE($V13,";",REPT(" ",99)),1,99)))+1,99)),0) + IFERROR(VLOOKUP(LEFT(TRIM(MID(SUBSTITUTE($V13,";",REPT(" ",99)),100,99)),FIND(":",TRIM(MID(SUBSTITUTE($V13,";",REPT(" ",99)),100,99)))-1),Materiales!$A$2:$E$502,5,FALSE)*VALUE(MID(TRIM(MID(SUBSTITUTE($V13,";",REPT(" ",99)),100,99)),FIND(":",TRIM(MID(SUBSTITUTE($V13,";",REPT(" ",99)),100,99)))+1,99)),0) + IFERROR(VLOOKUP(LEFT(TRIM(MID(SUBSTITUTE($V13,";",REPT(" ",99)),199,99)),FIND(":",TRIM(MID(SUBSTITUTE($V13,";",REPT(" ",99)),199,99)))-1),Materiales!$A$2:$E$502,5,FALSE)*VALUE(MID(TRIM(MID(SUBSTITUTE($V13,";",REPT(" ",99)),199,99)),FIND(":",TRIM(MID(SUBSTITUTE($V13,";",REPT(" ",99)),199,99)))+1,99)),0) + IFERROR(VLOOKUP(LEFT(TRIM(MID(SUBSTITUTE($V13,";",REPT(" ",99)),298,99)),FIND(":",TRIM(MID(SUBSTITUTE($V13,";",REPT(" ",99)),298,99)))-1),Materiales!$A$2:$E$502,5,FALSE)*VALUE(MID(TRIM(MID(SUBSTITUTE($V13,";",REPT(" ",99)),298,99)),FIND(":",TRIM(MID(SUBSTITUTE($V13,";",REPT(" ",99)),298,99)))+1,99)),0) + IFERROR(VLOOKUP(LEFT(TRIM(MID(SUBSTITUTE($V13,";",REPT(" ",99)),397,99)),FIND(":",TRIM(MID(SUBSTITUTE($V13,";",REPT(" ",99)),397,99)))-1),Materiales!$A$2:$E$502,5,FALSE)*VALUE(MID(TRIM(MID(SUBSTITUTE($V13,";",REPT(" ",99)),397,99)),FIND(":",TRIM(MID(SUBSTITUTE($V13,";",REPT(" ",99)),397,99)))+1,99)),0) + IFERROR(VLOOKUP(LEFT(TRIM(MID(SUBSTITUTE($V13,";",REPT(" ",99)),496,99)),FIND(":",TRIM(MID(SUBSTITUTE($V13,";",REPT(" ",99)),496,99)))-1),Materiales!$A$2:$E$502,5,FALSE)*VALUE(MID(TRIM(MID(SUBSTITUTE($V13,";",REPT(" ",99)),496,99)),FIND(":",TRIM(MID(SUBSTITUTE($V13,";",REPT(" ",99)),496,99)))+1,99)),0) + IFERROR(VLOOKUP(LEFT(TRIM(MID(SUBSTITUTE($V13,";",REPT(" ",99)),595,99)),FIND(":",TRIM(MID(SUBSTITUTE($V13,";",REPT(" ",99)),595,99)))-1),Materiales!$A$2:$E$502,5,FALSE)*VALUE(MID(TRIM(MID(SUBSTITUTE($V13,";",REPT(" ",99)),595,99)),FIND(":",TRIM(MID(SUBSTITUTE($V13,";",REPT(" ",99)),595,99)))+1,99)),0) + IFERROR(VLOOKUP(LEFT(TRIM(MID(SUBSTITUTE($V13,";",REPT(" ",99)),694,99)),FIND(":",TRIM(MID(SUBSTITUTE($V13,";",REPT(" ",99)),694,99)))-1),Materiales!$A$2:$E$502,5,FALSE)*VALUE(MID(TRIM(MID(SUBSTITUTE($V13,";",REPT(" ",99)),694,99)),FIND(":",TRIM(MID(SUBSTITUTE($V13,";",REPT(" ",99)),694,99)))+1,99)),0) + IFERROR(VLOOKUP(LEFT(TRIM(MID(SUBSTITUTE($V13,";",REPT(" ",99)),793,99)),FIND(":",TRIM(MID(SUBSTITUTE($V13,";",REPT(" ",99)),793,99)))-1),Materiales!$A$2:$E$502,5,FALSE)*VALUE(MID(TRIM(MID(SUBSTITUTE($V13,";",REPT(" ",99)),793,99)),FIND(":",TRIM(MID(SUBSTITUTE($V13,";",REPT(" ",99)),793,99)))+1,99)),0) + IFERROR(VLOOKUP(LEFT(TRIM(MID(SUBSTITUTE($V13,";",REPT(" ",99)),892,99)),FIND(":",TRIM(MID(SUBSTITUTE($V13,";",REPT(" ",99)),892,99)))-1),Materiales!$A$2:$E$502,5,FALSE)*VALUE(MID(TRIM(MID(SUBSTITUTE($V13,";",REPT(" ",99)),892,99)),FIND(":",TRIM(MID(SUBSTITUTE($V13,";",REPT(" ",99)),892,99)))+1,99)),0)))} -> 0 | X13: =IF($A13="","",SUM($G13,$H13,$K13,$N13,$Q13,$S13,$U13,$W13)) -> 1336.1961 | Y13: 3 | Z13: =X13*Y13 -> 4008.5883 | AA13: 0 | AB13: =AA13+Z13 -> 4008.5883 | AC13: 4000 | AD13: =AB13-X13 -> 2672.3922 | AE13: =AC13-X13 -> 2663.8039 | AF13: =AE13/AD13 -> 0.99678629
A14: Vela Peonia XS | B14: CERA_MOLDE | C14: 1 | F14: 13 | G14: {=IF($A14="","",IFERROR($F14*(N($C14)*XLOOKUP($B14,Ceras!$A$2:$A$500,Ceras!$G$2:$G$500,0)+IF($D14="",0,N($E14)*XLOOKUP($D14,Ceras!$A$2:$A$500,Ceras!$G$2:$G$500,0))),"Revisar cera"))} -> 234 | H14: =F14*1.5 -> 19.5 | I14: PABILO4-6 | J14: 4 | K14: {=IF($A14="","",IFERROR($J14*XLOOKUP($I14,Pabilos!$A$2:$A$500,Pabilos!$H$2:$H$500,0),"Revisar pabilo"))} -> 72 | L14: ES_BEDOYA | M14: =F14/10 -> 1.3 | N14: {=IF($A14="","",IFERROR($M14*XLOOKUP($L14,Esencias!$A$2:$A$501,Esencias!$G$2:$G$501,0),"Revisar esencia"))} -> 183.09859 | O14: COLOR_CAFE | P14: 0.5 | Q14: {=IF($A14="","",IFERROR(IF($P14="",1,$P14)*XLOOKUP($O14,Colores!$A$2:$A$500,Colores!$H$2:$H$500,0),"Revisar color"))} -> 46.153846 | S14: {=IF($A14="","",IF($R14="",0,IFERROR(VLOOKUP(LEFT(TRIM(MID(SUBSTITUTE($R14,";",REPT(" ",99)),1,99)),FIND(":",TRIM(MID(SUBSTITUTE($R14,";",REPT(" ",99)),1,99)))-1),Materiales!$A$2:$E$502,5,FALSE)*VALUE(MID(TRIM(MID(SUBSTITUTE($R14,";",REPT(" ",99)),1,99)),FIND(":",TRIM(MID(SUBSTITUTE($R14,";",REPT(" ",99)),1,99)))+1,99)),0) + IFERROR(VLOOKUP(LEFT(TRIM(MID(SUBSTITUTE($R14,";",REPT(" ",99)),100,99)),FIND(":",TRIM(MID(SUBSTITUTE($R14,";",REPT(" ",99)),100,99)))-1),Materiales!$A$2:$E$502,5,FALSE)*VALUE(MID(TRIM(MID(SUBSTITUTE($R14,";",REPT(" ",99)),100,99)),FIND(":",TRIM(MID(SUBSTITUTE($R14,";",REPT(" ",99)),100,99)))+1,99)),0) + IFERROR(VLOOKUP(LEFT(TRIM(MID(SUBSTITUTE($R14,";",REPT(" ",99)),199,99)),FIND(":",TRIM(MID(SUBSTITUTE($R14,";",REPT(" ",99)),199,99)))-1),Materiales!$A$2:$E$502,5,FALSE)*VALUE(MID(TRIM(MID(SUBSTITUTE($R14,";",REPT(" ",99)),199,99)),FIND(":",TRIM(MID(SUBSTITUTE($R14,";",REPT(" ",99)),199,99)))+1,99)),0) + IFERROR(VLOOKUP(LEFT(TRIM(MID(SUBSTITUTE($R14,";",REPT(" ",99)),298,99)),FIND(":",TRIM(MID(SUBSTITUTE($R14,";",REPT(" ",99)),298,99)))-1),Materiales!$A$2:$E$502,5,FALSE)*VALUE(MID(TRIM(MID(SUBSTITUTE($R14,";",REPT(" ",99)),298,99)),FIND(":",TRIM(MID(SUBSTITUTE($R14,";",REPT(" ",99)),298,99)))+1,99)),0) + IFERROR(VLOOKUP(LEFT(TRIM(MID(SUBSTITUTE($R14,";",REPT(" ",99)),397,99)),FIND(":",TRIM(MID(SUBSTITUTE($R14,";",REPT(" ",99)),397,99)))-1),Materiales!$A$2:$E$502,5,FALSE)*VALUE(MID(TRIM(MID(SUBSTITUTE($R14,";",REPT(" ",99)),397,99)),FIND(":",TRIM(MID(SUBSTITUTE($R14,";",REPT(" ",99)),397,99)))+1,99)),0) + IFERROR(VLOOKUP(LEFT(TRIM(MID(SUBSTITUTE($R14,";",REPT(" ",99)),496,99)),FIND(":",TRIM(MID(SUBSTITUTE($R14,";",REPT(" ",99)),496,99)))-1),Materiales!$A$2:$E$502,5,FALSE)*VALUE(MID(TRIM(MID(SUBSTITUTE($R14,";",REPT(" ",99)),496,99)),FIND(":",TRIM(MID(SUBSTITUTE($R14,";",REPT(" ",99)),496,99)))+1,99)),0) + IFERROR(VLOOKUP(LEFT(TRIM(MID(SUBSTITUTE($R14,";",REPT(" ",99)),595,99)),FIND(":",TRIM(MID(SUBSTITUTE($R14,";",REPT(" ",99)),595,99)))-1),Materiales!$A$2:$E$502,5,FALSE)*VALUE(MID(TRIM(MID(SUBSTITUTE($R14,";",REPT(" ",99)),595,99)),FIND(":",TRIM(MID(SUBSTITUTE($R14,";",REPT(" ",99)),595,99)))+1,99)),0) + IFERROR(VLOOKUP(LEFT(TRIM(MID(SUBSTITUTE($R14,";",REPT(" ",99)),694,99)),FIND(":",TRIM(MID(SUBSTITUTE($R14,";",REPT(" ",99)),694,99)))-1),Materiales!$A$2:$E$502,5,FALSE)*VALUE(MID(TRIM(MID(SUBSTITUTE($R14,";",REPT(" ",99)),694,99)),FIND(":",TRIM(MID(SUBSTITUTE($R14,";",REPT(" ",99)),694,99)))+1,99)),0) + IFERROR(VLOOKUP(LEFT(TRIM(MID(SUBSTITUTE($R14,";",REPT(" ",99)),793,99)),FIND(":",TRIM(MID(SUBSTITUTE($R14,";",REPT(" ",99)),793,99)))-1),Materiales!$A$2:$E$502,5,FALSE)*VALUE(MID(TRIM(MID(SUBSTITUTE($R14,";",REPT(" ",99)),793,99)),FIND(":",TRIM(MID(SUBSTITUTE($R14,";",REPT(" ",99)),793,99)))+1,99)),0) + IFERROR(VLOOKUP(LEFT(TRIM(MID(SUBSTITUTE($R14,";",REPT(" ",99)),892,99)),FIND(":",TRIM(MID(SUBSTITUTE($R14,";",REPT(" ",99)),892,99)))-1),Materiales!$A$2:$E$502,5,FALSE)*VALUE(MID(TRIM(MID(SUBSTITUTE($R14,";",REPT(" ",99)),892,99)),FIND(":",TRIM(MID(SUBSTITUTE($R14,";",REPT(" ",99)),892,99)))+1,99)),0)))} -> 0 | U14: {=IF($A14="","",IF($T14="",0,IFERROR(VLOOKUP(LEFT(TRIM(MID(SUBSTITUTE($T14,";",REPT(" ",99)),1,99)),FIND(":",TRIM(MID(SUBSTITUTE($T14,";",REPT(" ",99)),1,99)))-1),Materiales!$A$2:$E$502,5,FALSE)*VALUE(MID(TRIM(MID(SUBSTITUTE($T14,";",REPT(" ",99)),1,99)),FIND(":",TRIM(MID(SUBSTITUTE($T14,";",REPT(" ",99)),1,99)))+1,99)),0) + IFERROR(VLOOKUP(LEFT(TRIM(MID(SUBSTITUTE($T14,";",REPT(" ",99)),100,99)),FIND(":",TRIM(MID(SUBSTITUTE($T14,";",REPT(" ",99)),100,99)))-1),Materiales!$A$2:$E$502,5,FALSE)*VALUE(MID(TRIM(MID(SUBSTITUTE($T14,";",REPT(" ",99)),100,99)),FIND(":",TRIM(MID(SUBSTITUTE($T14,";",REPT(" ",99)),100,99)))+1,99)),0) + IFERROR(VLOOKUP(LEFT(TRIM(MID(SUBSTITUTE($T14,";",REPT(" ",99)),199,99)),FIND(":",TRIM(MID(SUBSTITUTE($T14,";",REPT(" ",99)),199,99)))-1),Materiales!$A$2:$E$502,5,FALSE)*VALUE(MID(TRIM(MID(SUBSTITUTE($T14,";",REPT(" ",99)),199,99)),FIND(":",TRIM(MID(SUBSTITUTE($T14,";",REPT(" ",99)),199,99)))+1,99)),0) + IFERROR(VLOOKUP(LEFT(TRIM(MID(SUBSTITUTE($T14,";",REPT(" ",99)),298,99)),FIND(":",TRIM(MID(SUBSTITUTE($T14,";",REPT(" ",99)),298,99)))-1),Materiales!$A$2:$E$502,5,FALSE)*VALUE(MID(TRIM(MID(SUBSTITUTE($T14,";",REPT(" ",99)),298,99)),FIND(":",TRIM(MID(SUBSTITUTE($T14,";",REPT(" ",99)),298,99)))+1,99)),0) + IFERROR(VLOOKUP(LEFT(TRIM(MID(SUBSTITUTE($T14,";",REPT(" ",99)),397,99)),FIND(":",TRIM(MID(SUBSTITUTE($T14,";",REPT(" ",99)),397,99)))-1),Materiales!$A$2:$E$502,5,FALSE)*VALUE(MID(TRIM(MID(SUBSTITUTE($T14,";",REPT(" ",99)),397,99)),FIND(":",TRIM(MID(SUBSTITUTE($T14,";",REPT(" ",99)),397,99)))+1,99)),0) + IFERROR(VLOOKUP(LEFT(TRIM(MID(SUBSTITUTE($T14,";",REPT(" ",99)),496,99)),FIND(":",TRIM(MID(SUBSTITUTE($T14,";",REPT(" ",99)),496,99)))-1),Materiales!$A$2:$E$502,5,FALSE)*VALUE(MID(TRIM(MID(SUBSTITUTE($T14,";",REPT(" ",99)),496,99)),FIND(":",TRIM(MID(SUBSTITUTE($T14,";",REPT(" ",99)),496,99)))+1,99)),0) + IFERROR(VLOOKUP(LEFT(TRIM(MID(SUBSTITUTE($T14,";",REPT(" ",99)),595,99)),FIND(":",TRIM(MID(SUBSTITUTE($T14,";",REPT(" ",99)),595,99)))-1),Materiales!$A$2:$E$502,5,FALSE)*VALUE(MID(TRIM(MID(SUBSTITUTE($T14,";",REPT(" ",99)),595,99)),FIND(":",TRIM(MID(SUBSTITUTE($T14,";",REPT(" ",99)),595,99)))+1,99)),0) + IFERROR(VLOOKUP(LEFT(TRIM(MID(SUBSTITUTE($T14,";",REPT(" ",99)),694,99)),FIND(":",TRIM(MID(SUBSTITUTE($T14,";",REPT(" ",99)),694,99)))-1),Materiales!$A$2:$E$502,5,FALSE)*VALUE(MID(TRIM(MID(SUBSTITUTE($T14,";",REPT(" ",99)),694,99)),FIND(":",TRIM(MID(SUBSTITUTE($T14,";",REPT(" ",99)),694,99)))+1,99)),0) + IFERROR(VLOOKUP(LEFT(TRIM(MID(SUBSTITUTE($T14,";",REPT(" ",99)),793,99)),FIND(":",TRIM(MID(SUBSTITUTE($T14,";",REPT(" ",99)),793,99)))-1),Materiales!$A$2:$E$502,5,FALSE)*VALUE(MID(TRIM(MID(SUBSTITUTE($T14,";",REPT(" ",99)),793,99)),FIND(":",TRIM(MID(SUBSTITUTE($T14,";",REPT(" ",99)),793,99)))+1,99)),0) + IFERROR(VLOOKUP(LEFT(TRIM(MID(SUBSTITUTE($T14,";",REPT(" ",99)),892,99)),FIND(":",TRIM(MID(SUBSTITUTE($T14,";",REPT(" ",99)),892,99)))-1),Materiales!$A$2:$E$502,5,FALSE)*VALUE(MID(TRIM(MID(SUBSTITUTE($T14,";",REPT(" ",99)),892,99)),FIND(":",TRIM(MID(SUBSTITUTE($T14,";",REPT(" ",99)),892,99)))+1,99)),0)))} -> 0 | W14: {=IF($A14="","",IF($V14="",0,IFERROR(VLOOKUP(LEFT(TRIM(MID(SUBSTITUTE($V14,";",REPT(" ",99)),1,99)),FIND(":",TRIM(MID(SUBSTITUTE($V14,";",REPT(" ",99)),1,99)))-1),Materiales!$A$2:$E$502,5,FALSE)*VALUE(MID(TRIM(MID(SUBSTITUTE($V14,";",REPT(" ",99)),1,99)),FIND(":",TRIM(MID(SUBSTITUTE($V14,";",REPT(" ",99)),1,99)))+1,99)),0) + IFERROR(VLOOKUP(LEFT(TRIM(MID(SUBSTITUTE($V14,";",REPT(" ",99)),100,99)),FIND(":",TRIM(MID(SUBSTITUTE($V14,";",REPT(" ",99)),100,99)))-1),Materiales!$A$2:$E$502,5,FALSE)*VALUE(MID(TRIM(MID(SUBSTITUTE($V14,";",REPT(" ",99)),100,99)),FIND(":",TRIM(MID(SUBSTITUTE($V14,";",REPT(" ",99)),100,99)))+1,99)),0) + IFERROR(VLOOKUP(LEFT(TRIM(MID(SUBSTITUTE($V14,";",REPT(" ",99)),199,99)),FIND(":",TRIM(MID(SUBSTITUTE($V14,";",REPT(" ",99)),199,99)))-1),Materiales!$A$2:$E$502,5,FALSE)*VALUE(MID(TRIM(MID(SUBSTITUTE($V14,";",REPT(" ",99)),199,99)),FIND(":",TRIM(MID(SUBSTITUTE($V14,";",REPT(" ",99)),199,99)))+1,99)),0) + IFERROR(VLOOKUP(LEFT(TRIM(MID(SUBSTITUTE($V14,";",REPT(" ",99)),298,99)),FIND(":",TRIM(MID(SUBSTITUTE($V14,";",REPT(" ",99)),298,99)))-1),Materiales!$A$2:$E$502,5,FALSE)*VALUE(MID(TRIM(MID(SUBSTITUTE($V14,";",REPT(" ",99)),298,99)),FIND(":",TRIM(MID(SUBSTITUTE($V14,";",REPT(" ",99)),298,99)))+1,99)),0) + IFERROR(VLOOKUP(LEFT(TRIM(MID(SUBSTITUTE($V14,";",REPT(" ",99)),397,99)),FIND(":",TRIM(MID(SUBSTITUTE($V14,";",REPT(" ",99)),397,99)))-1),Materiales!$A$2:$E$502,5,FALSE)*VALUE(MID(TRIM(MID(SUBSTITUTE($V14,";",REPT(" ",99)),397,99)),FIND(":",TRIM(MID(SUBSTITUTE($V14,";",REPT(" ",99)),397,99)))+1,99)),0) + IFERROR(VLOOKUP(LEFT(TRIM(MID(SUBSTITUTE($V14,";",REPT(" ",99)),496,99)),FIND(":",TRIM(MID(SUBSTITUTE($V14,";",REPT(" ",99)),496,99)))-1),Materiales!$A$2:$E$502,5,FALSE)*VALUE(MID(TRIM(MID(SUBSTITUTE($V14,";",REPT(" ",99)),496,99)),FIND(":",TRIM(MID(SUBSTITUTE($V14,";",REPT(" ",99)),496,99)))+1,99)),0) + IFERROR(VLOOKUP(LEFT(TRIM(MID(SUBSTITUTE($V14,";",REPT(" ",99)),595,99)),FIND(":",TRIM(MID(SUBSTITUTE($V14,";",REPT(" ",99)),595,99)))-1),Materiales!$A$2:$E$502,5,FALSE)*VALUE(MID(TRIM(MID(SUBSTITUTE($V14,";",REPT(" ",99)),595,99)),FIND(":",TRIM(MID(SUBSTITUTE($V14,";",REPT(" ",99)),595,99)))+1,99)),0) + IFERROR(VLOOKUP(LEFT(TRIM(MID(SUBSTITUTE($V14,";",REPT(" ",99)),694,99)),FIND(":",TRIM(MID(SUBSTITUTE($V14,";",REPT(" ",99)),694,99)))-1),Materiales!$A$2:$E$502,5,FALSE)*VALUE(MID(TRIM(MID(SUBSTITUTE($V14,";",REPT(" ",99)),694,99)),FIND(":",TRIM(MID(SUBSTITUTE($V14,";",REPT(" ",99)),694,99)))+1,99)),0) + IFERROR(VLOOKUP(LEFT(TRIM(MID(SUBSTITUTE($V14,";",REPT(" ",99)),793,99)),FIND(":",TRIM(MID(SUBSTITUTE($V14,";",REPT(" ",99)),793,99)))-1),Materiales!$A$2:$E$502,5,FALSE)*VALUE(MID(TRIM(MID(SUBSTITUTE($V14,";",REPT(" ",99)),793,99)),FIND(":",TRIM(MID(SUBSTITUTE($V14,";",REPT(" ",99)),793,99)))+1,99)),0) + IFERROR(VLOOKUP(LEFT(TRIM(MID(SUBSTITUTE($V14,";",REPT(" ",99)),892,99)),FIND(":",TRIM(MID(SUBSTITUTE($V14,";",REPT(" ",99)),892,99)))-1),Materiales!$A$2:$E$502,5,FALSE)*VALUE(MID(TRIM(MID(SUBSTITUTE($V14,";",REPT(" ",99)),892,99)),FIND(":",TRIM(MID(SUBSTITUTE($V14,";",REPT(" ",99)),892,99)))+1,99)),0)))} -> 0 | X14: =IF($A14="","",SUM($G14,$H14,$K14,$N14,$Q14,$S14,$U14,$W14)) -> 554.75244 | Y14: 3 | Z14: =X14*Y14 -> 1664.2573 | AA14: 0 | AB14: =AA14+Z14 -> 1664.2573 | AC14: 2000 | AD14: =AB14-X14 -> 1109.5049 | AE14: =AC14-X14 -> 1445.2476 | AF14: =AE14/AD14 -> 1.3026059
A15: Vela Peonia S | B15: CERA_MOLDE | C15: 1 | F15: 29 | G15: {=IF($A15="","",IFERROR($F15*(N($C15)*XLOOKUP($B15,Ceras!$A$2:$A$500,Ceras!$G$2:$G$500,0)+IF($D15="",0,N($E15)*XLOOKUP($D15,Ceras!$A$2:$A$500,Ceras!$G$2:$G$500,0))),"Revisar cera"))} -> 522 | H15: =F15*1.5 -> 43.5 | I15: PABILO4-6 | J15: 4 | K15: {=IF($A15="","",IFERROR($J15*XLOOKUP($I15,Pabilos!$A$2:$A$500,Pabilos!$H$2:$H$500,0),"Revisar pabilo"))} -> 72 | L15: ES_BEDOYA | M15: =F15/10 -> 2.9 | N15: {=IF($A15="","",IFERROR($M15*XLOOKUP($L15,Esencias!$A$2:$A$501,Esencias!$G$2:$G$501,0),"Revisar esencia"))} -> 408.4507 | O15: COLOR_CAFE | P15: 1 | Q15: {=IF($A15="","",IFERROR(IF($P15="",1,$P15)*XLOOKUP($O15,Colores!$A$2:$A$500,Colores!$H$2:$H$500,0),"Revisar color"))} -> 92.307692 | S15: {=IF($A15="","",IF($R15="",0,IFERROR(VLOOKUP(LEFT(TRIM(MID(SUBSTITUTE($R15,";",REPT(" ",99)),1,99)),FIND(":",TRIM(MID(SUBSTITUTE($R15,";",REPT(" ",99)),1,99)))-1),Materiales!$A$2:$E$502,5,FALSE)*VALUE(MID(TRIM(MID(SUBSTITUTE($R15,";",REPT(" ",99)),1,99)),FIND(":",TRIM(MID(SUBSTITUTE($R15,";",REPT(" ",99)),1,99)))+1,99)),0) + IFERROR(VLOOKUP(LEFT(TRIM(MID(SUBSTITUTE($R15,";",REPT(" ",99)),100,99)),FIND(":",TRIM(MID(SUBSTITUTE($R15,";",REPT(" ",99)),100,99)))-1),Materiales!$A$2:$E$502,5,FALSE)*VALUE(MID(TRIM(MID(SUBSTITUTE($R15,";",REPT(" ",99)),100,99)),FIND(":",TRIM(MID(SUBSTITUTE($R15,";",REPT(" ",99)),100,99)))+1,99)),0) + IFERROR(VLOOKUP(LEFT(TRIM(MID(SUBSTITUTE($R15,";",REPT(" ",99)),199,99)),FIND(":",TRIM(MID(SUBSTITUTE($R15,";",REPT(" ",99)),199,99)))-1),Materiales!$A$2:$E$502,5,FALSE)*VALUE(MID(TRIM(MID(SUBSTITUTE($R15,";",REPT(" ",99)),199,99)),FIND(":",TRIM(MID(SUBSTITUTE($R15,";",REPT(" ",99)),199,99)))+1,99)),0) + IFERROR(VLOOKUP(LEFT(TRIM(MID(SUBSTITUTE($R15,";",REPT(" ",99)),298,99)),FIND(":",TRIM(MID(SUBSTITUTE($R15,";",REPT(" ",99)),298,99)))-1),Materiales!$A$2:$E$502,5,FALSE)*VALUE(MID(TRIM(MID(SUBSTITUTE($R15,";",REPT(" ",99)),298,99)),FIND(":",TRIM(MID(SUBSTITUTE($R15,";",REPT(" ",99)),298,99)))+1,99)),0) + IFERROR(VLOOKUP(LEFT(TRIM(MID(SUBSTITUTE($R15,";",REPT(" ",99)),397,99)),FIND(":",TRIM(MID(SUBSTITUTE($R15,";",REPT(" ",99)),397,99)))-1),Materiales!$A$2:$E$502,5,FALSE)*VALUE(MID(TRIM(MID(SUBSTITUTE($R15,";",REPT(" ",99)),397,99)),FIND(":",TRIM(MID(SUBSTITUTE($R15,";",REPT(" ",99)),397,99)))+1,99)),0) + IFERROR(VLOOKUP(LEFT(TRIM(MID(SUBSTITUTE($R15,";",REPT(" ",99)),496,99)),FIND(":",TRIM(MID(SUBSTITUTE($R15,";",REPT(" ",99)),496,99)))-1),Materiales!$A$2:$E$502,5,FALSE)*VALUE(MID(TRIM(MID(SUBSTITUTE($R15,";",REPT(" ",99)),496,99)),FIND(":",TRIM(MID(SUBSTITUTE($R15,";",REPT(" ",99)),496,99)))+1,99)),0) + IFERROR(VLOOKUP(LEFT(TRIM(MID(SUBSTITUTE($R15,";",REPT(" ",99)),595,99)),FIND(":",TRIM(MID(SUBSTITUTE($R15,";",REPT(" ",99)),595,99)))-1),Materiales!$A$2:$E$502,5,FALSE)*VALUE(MID(TRIM(MID(SUBSTITUTE($R15,";",REPT(" ",99)),595,99)),FIND(":",TRIM(MID(SUBSTITUTE($R15,";",REPT(" ",99)),595,99)))+1,99)),0) + IFERROR(VLOOKUP(LEFT(TRIM(MID(SUBSTITUTE($R15,";",REPT(" ",99)),694,99)),FIND(":",TRIM(MID(SUBSTITUTE($R15,";",REPT(" ",99)),694,99)))-1),Materiales!$A$2:$E$502,5,FALSE)*VALUE(MID(TRIM(MID(SUBSTITUTE($R15,";",REPT(" ",99)),694,99)),FIND(":",TRIM(MID(SUBSTITUTE($R15,";",REPT(" ",99)),694,99)))+1,99)),0) + IFERROR(VLOOKUP(LEFT(TRIM(MID(SUBSTITUTE($R15,";",REPT(" ",99)),793,99)),FIND(":",TRIM(MID(SUBSTITUTE($R15,";",REPT(" ",99)),793,99)))-1),Materiales!$A$2:$E$502,5,FALSE)*VALUE(MID(TRIM(MID(SUBSTITUTE($R15,";",REPT(" ",99)),793,99)),FIND(":",TRIM(MID(SUBSTITUTE($R15,";",REPT(" ",99)),793,99)))+1,99)),0) + IFERROR(VLOOKUP(LEFT(TRIM(MID(SUBSTITUTE($R15,";",REPT(" ",99)),892,99)),FIND(":",TRIM(MID(SUBSTITUTE($R15,";",REPT(" ",99)),892,99)))-1),Materiales!$A$2:$E$502,5,FALSE)*VALUE(MID(TRIM(MID(SUBSTITUTE($R15,";",REPT(" ",99)),892,99)),FIND(":",TRIM(MID(SUBSTITUTE($R15,";",REPT(" ",99)),892,99)))+1,99)),0)))} -> 0 | U15: {=IF($A15="","",IF($T15="",0,IFERROR(VLOOKUP(LEFT(TRIM(MID(SUBSTITUTE($T15,";",REPT(" ",99)),1,99)),FIND(":",TRIM(MID(SUBSTITUTE($T15,";",REPT(" ",99)),1,99)))-1),Materiales!$A$2:$E$502,5,FALSE)*VALUE(MID(TRIM(MID(SUBSTITUTE($T15,";",REPT(" ",99)),1,99)),FIND(":",TRIM(MID(SUBSTITUTE($T15,";",REPT(" ",99)),1,99)))+1,99)),0) + IFERROR(VLOOKUP(LEFT(TRIM(MID(SUBSTITUTE($T15,";",REPT(" ",99)),100,99)),FIND(":",TRIM(MID(SUBSTITUTE($T15,";",REPT(" ",99)),100,99)))-1),Materiales!$A$2:$E$502,5,FALSE)*VALUE(MID(TRIM(MID(SUBSTITUTE($T15,";",REPT(" ",99)),100,99)),FIND(":",TRIM(MID(SUBSTITUTE($T15,";",REPT(" ",99)),100,99)))+1,99)),0) + IFERROR(VLOOKUP(LEFT(TRIM(MID(SUBSTITUTE($T15,";",REPT(" ",99)),199,99)),FIND(":",TRIM(MID(SUBSTITUTE($T15,";",REPT(" ",99)),199,99)))-1),Materiales!$A$2:$E$502,5,FALSE)*VALUE(MID(TRIM(MID(SUBSTITUTE($T15,";",REPT(" ",99)),199,99)),FIND(":",TRIM(MID(SUBSTITUTE($T15,";",REPT(" ",99)),199,99)))+1,99)),0) + IFERROR(VLOOKUP(LEFT(TRIM(MID(SUBSTITUTE($T15,";",REPT(" ",99)),298,99)),FIND(":",TRIM(MID(SUBSTITUTE($T15,";",REPT(" ",99)),298,99)))-1),Materiales!$A$2:$E$502,5,FALSE)*VALUE(MID(TRIM(MID(SUBSTITUTE($T15,";",REPT(" ",99)),298,99)),FIND(":",TRIM(MID(SUBSTITUTE($T15,";",REPT(" ",99)),298,99)))+1,99)),0) + IFERROR(VLOOKUP(LEFT(TRIM(MID(SUBSTITUTE($T15,";",REPT(" ",99)),397,99)),FIND(":",TRIM(MID(SUBSTITUTE($T15,";",REPT(" ",99)),397,99)))-1),Materiales!$A$2:$E$502,5,FALSE)*VALUE(MID(TRIM(MID(SUBSTITUTE($T15,";",REPT(" ",99)),397,99)),FIND(":",TRIM(MID(SUBSTITUTE($T15,";",REPT(" ",99)),397,99)))+1,99)),0) + IFERROR(VLOOKUP(LEFT(TRIM(MID(SUBSTITUTE($T15,";",REPT(" ",99)),496,99)),FIND(":",TRIM(MID(SUBSTITUTE($T15,";",REPT(" ",99)),496,99)))-1),Materiales!$A$2:$E$502,5,FALSE)*VALUE(MID(TRIM(MID(SUBSTITUTE($T15,";",REPT(" ",99)),496,99)),FIND(":",TRIM(MID(SUBSTITUTE($T15,";",REPT(" ",99)),496,99)))+1,99)),0) + IFERROR(VLOOKUP(LEFT(TRIM(MID(SUBSTITUTE($T15,";",REPT(" ",99)),595,99)),FIND(":",TRIM(MID(SUBSTITUTE($T15,";",REPT(" ",99)),595,99)))-1),Materiales!$A$2:$E$502,5,FALSE)*VALUE(MID(TRIM(MID(SUBSTITUTE($T15,";",REPT(" ",99)),595,99)),FIND(":",TRIM(MID(SUBSTITUTE($T15,";",REPT(" ",99)),595,99)))+1,99)),0) + IFERROR(VLOOKUP(LEFT(TRIM(MID(SUBSTITUTE($T15,";",REPT(" ",99)),694,99)),FIND(":",TRIM(MID(SUBSTITUTE($T15,";",REPT(" ",99)),694,99)))-1),Materiales!$A$2:$E$502,5,FALSE)*VALUE(MID(TRIM(MID(SUBSTITUTE($T15,";",REPT(" ",99)),694,99)),FIND(":",TRIM(MID(SUBSTITUTE($T15,";",REPT(" ",99)),694,99)))+1,99)),0) + IFERROR(VLOOKUP(LEFT(TRIM(MID(SUBSTITUTE($T15,";",REPT(" ",99)),793,99)),FIND(":",TRIM(MID(SUBSTITUTE($T15,";",REPT(" ",99)),793,99)))-1),Materiales!$A$2:$E$502,5,FALSE)*VALUE(MID(TRIM(MID(SUBSTITUTE($T15,";",REPT(" ",99)),793,99)),FIND(":",TRIM(MID(SUBSTITUTE($T15,";",REPT(" ",99)),793,99)))+1,99)),0) + IFERROR(VLOOKUP(LEFT(TRIM(MID(SUBSTITUTE($T15,";",REPT(" ",99)),892,99)),FIND(":",TRIM(MID(SUBSTITUTE($T15,";",REPT(" ",99)),892,99)))-1),Materiales!$A$2:$E$502,5,FALSE)*VALUE(MID(TRIM(MID(SUBSTITUTE($T15,";",REPT(" ",99)),892,99)),FIND(":",TRIM(MID(SUBSTITUTE($T15,";",REPT(" ",99)),892,99)))+1,99)),0)))} -> 0 | W15: {=IF($A15="","",IF($V15="",0,IFERROR(VLOOKUP(LEFT(TRIM(MID(SUBSTITUTE($V15,";",REPT(" ",99)),1,99)),FIND(":",TRIM(MID(SUBSTITUTE($V15,";",REPT(" ",99)),1,99)))-1),Materiales!$A$2:$E$502,5,FALSE)*VALUE(MID(TRIM(MID(SUBSTITUTE($V15,";",REPT(" ",99)),1,99)),FIND(":",TRIM(MID(SUBSTITUTE($V15,";",REPT(" ",99)),1,99)))+1,99)),0) + IFERROR(VLOOKUP(LEFT(TRIM(MID(SUBSTITUTE($V15,";",REPT(" ",99)),100,99)),FIND(":",TRIM(MID(SUBSTITUTE($V15,";",REPT(" ",99)),100,99)))-1),Materiales!$A$2:$E$502,5,FALSE)*VALUE(MID(TRIM(MID(SUBSTITUTE($V15,";",REPT(" ",99)),100,99)),FIND(":",TRIM(MID(SUBSTITUTE($V15,";",REPT(" ",99)),100,99)))+1,99)),0) + IFERROR(VLOOKUP(LEFT(TRIM(MID(SUBSTITUTE($V15,";",REPT(" ",99)),199,99)),FIND(":",TRIM(MID(SUBSTITUTE($V15,";",REPT(" ",99)),199,99)))-1),Materiales!$A$2:$E$502,5,FALSE)*VALUE(MID(TRIM(MID(SUBSTITUTE($V15,";",REPT(" ",99)),199,99)),FIND(":",TRIM(MID(SUBSTITUTE($V15,";",REPT(" ",99)),199,99)))+1,99)),0) + IFERROR(VLOOKUP(LEFT(TRIM(MID(SUBSTITUTE($V15,";",REPT(" ",99)),298,99)),FIND(":",TRIM(MID(SUBSTITUTE($V15,";",REPT(" ",99)),298,99)))-1),Materiales!$A$2:$E$502,5,FALSE)*VALUE(MID(TRIM(MID(SUBSTITUTE($V15,";",REPT(" ",99)),298,99)),FIND(":",TRIM(MID(SUBSTITUTE($V15,";",REPT(" ",99)),298,99)))+1,99)),0) + IFERROR(VLOOKUP(LEFT(TRIM(MID(SUBSTITUTE($V15,";",REPT(" ",99)),397,99)),FIND(":",TRIM(MID(SUBSTITUTE($V15,";",REPT(" ",99)),397,99)))-1),Materiales!$A$2:$E$502,5,FALSE)*VALUE(MID(TRIM(MID(SUBSTITUTE($V15,";",REPT(" ",99)),397,99)),FIND(":",TRIM(MID(SUBSTITUTE($V15,";",REPT(" ",99)),397,99)))+1,99)),0) + IFERROR(VLOOKUP(LEFT(TRIM(MID(SUBSTITUTE($V15,";",REPT(" ",99)),496,99)),FIND(":",TRIM(MID(SUBSTITUTE($V15,";",REPT(" ",99)),496,99)))-1),Materiales!$A$2:$E$502,5,FALSE)*VALUE(MID(TRIM(MID(SUBSTITUTE($V15,";",REPT(" ",99)),496,99)),FIND(":",TRIM(MID(SUBSTITUTE($V15,";",REPT(" ",99)),496,99)))+1,99)),0) + IFERROR(VLOOKUP(LEFT(TRIM(MID(SUBSTITUTE($V15,";",REPT(" ",99)),595,99)),FIND(":",TRIM(MID(SUBSTITUTE($V15,";",REPT(" ",99)),595,99)))-1),Materiales!$A$2:$E$502,5,FALSE)*VALUE(MID(TRIM(MID(SUBSTITUTE($V15,";",REPT(" ",99)),595,99)),FIND(":",TRIM(MID(SUBSTITUTE($V15,";",REPT(" ",99)),595,99)))+1,99)),0) + IFERROR(VLOOKUP(LEFT(TRIM(MID(SUBSTITUTE($V15,";",REPT(" ",99)),694,99)),FIND(":",TRIM(MID(SUBSTITUTE($V15,";",REPT(" ",99)),694,99)))-1),Materiales!$A$2:$E$502,5,FALSE)*VALUE(MID(TRIM(MID(SUBSTITUTE($V15,";",REPT(" ",99)),694,99)),FIND(":",TRIM(MID(SUBSTITUTE($V15,";",REPT(" ",99)),694,99)))+1,99)),0) + IFERROR(VLOOKUP(LEFT(TRIM(MID(SUBSTITUTE($V15,";",REPT(" ",99)),793,99)),FIND(":",TRIM(MID(SUBSTITUTE($V15,";",REPT(" ",99)),793,99)))-1),Materiales!$A$2:$E$502,5,FALSE)*VALUE(MID(TRIM(MID(SUBSTITUTE($V15,";",REPT(" ",99)),793,99)),FIND(":",TRIM(MID(SUBSTITUTE($V15,";",REPT(" ",99)),793,99)))+1,99)),0) + IFERROR(VLOOKUP(LEFT(TRIM(MID(SUBSTITUTE($V15,";",REPT(" ",99)),892,99)),FIND(":",TRIM(MID(SUBSTITUTE($V15,";",REPT(" ",99)),892,99)))-1),Materiales!$A$2:$E$502,5,FALSE)*VALUE(MID(TRIM(MID(SUBSTITUTE($V15,";",REPT(" ",99)),892,99)),FIND(":",TRIM(MID(SUBSTITUTE($V15,";",REPT(" ",99)),892,99)))+1,99)),0)))} -> 0 | X15: =IF($A15="","",SUM($G15,$H15,$K15,$N15,$Q15,$S15,$U15,$W15)) -> 1138.2584 | Y15: 3 | Z15: =X15*Y15 -> 3414.7752 | AA15: 0 | AB15: =AA15+Z15 -> 3414.7752 | AC15: 3500 | AD15: =AB15-X15 -> 2276.5168 | AE15: =AC15-X15 -> 2361.7416 | AF15: =AE15/AD15 -> 1.0374365
A16: Vela Peonia M | B16: CERA_MOLDE | C16: 1 | F16: 79 | G16: {=IF($A16="","",IFERROR($F16*(N($C16)*XLOOKUP($B16,Ceras!$A$2:$A$500,Ceras!$G$2:$G$500,0)+IF($D16="",0,N($E16)*XLOOKUP($D16,Ceras!$A$2:$A$500,Ceras!$G$2:$G$500,0))),"Revisar cera"))} -> 1422 | H16: =F16*1.5 -> 118.5 | I16: PABILO4-6 | J16: 4.5 | K16: {=IF($A16="","",IFERROR($J16*XLOOKUP($I16,Pabilos!$A$2:$A$500,Pabilos!$H$2:$H$500,0),"Revisar pabilo"))} -> 81 | L16: ES_BEDOYA | M16: =F16/10 -> 7.9 | N16: {=IF($A16="","",IFERROR($M16*XLOOKUP($L16,Esencias!$A$2:$A$501,Esencias!$G$2:$G$501,0),"Revisar esencia"))} -> 1112.6761 | O16: COLOR_CAFE | P16: 1 | Q16: {=IF($A16="","",IFERROR(IF($P16="",1,$P16)*XLOOKUP($O16,Colores!$A$2:$A$500,Colores!$H$2:$H$500,0),"Revisar color"))} -> 92.307692 | S16: {=IF($A16="","",IF($R16="",0,IFERROR(VLOOKUP(LEFT(TRIM(MID(SUBSTITUTE($R16,";",REPT(" ",99)),1,99)),FIND(":",TRIM(MID(SUBSTITUTE($R16,";",REPT(" ",99)),1,99)))-1),Materiales!$A$2:$E$502,5,FALSE)*VALUE(MID(TRIM(MID(SUBSTITUTE($R16,";",REPT(" ",99)),1,99)),FIND(":",TRIM(MID(SUBSTITUTE($R16,";",REPT(" ",99)),1,99)))+1,99)),0) + IFERROR(VLOOKUP(LEFT(TRIM(MID(SUBSTITUTE($R16,";",REPT(" ",99)),100,99)),FIND(":",TRIM(MID(SUBSTITUTE($R16,";",REPT(" ",99)),100,99)))-1),Materiales!$A$2:$E$502,5,FALSE)*VALUE(MID(TRIM(MID(SUBSTITUTE($R16,";",REPT(" ",99)),100,99)),FIND(":",TRIM(MID(SUBSTITUTE($R16,";",REPT(" ",99)),100,99)))+1,99)),0) + IFERROR(VLOOKUP(LEFT(TRIM(MID(SUBSTITUTE($R16,";",REPT(" ",99)),199,99)),FIND(":",TRIM(MID(SUBSTITUTE($R16,";",REPT(" ",99)),199,99)))-1),Materiales!$A$2:$E$502,5,FALSE)*VALUE(MID(TRIM(MID(SUBSTITUTE($R16,";",REPT(" ",99)),199,99)),FIND(":",TRIM(MID(SUBSTITUTE($R16,";",REPT(" ",99)),199,99)))+1,99)),0) + IFERROR(VLOOKUP(LEFT(TRIM(MID(SUBSTITUTE($R16,";",REPT(" ",99)),298,99)),FIND(":",TRIM(MID(SUBSTITUTE($R16,";",REPT(" ",99)),298,99)))-1),Materiales!$A$2:$E$502,5,FALSE)*VALUE(MID(TRIM(MID(SUBSTITUTE($R16,";",REPT(" ",99)),298,99)),FIND(":",TRIM(MID(SUBSTITUTE($R16,";",REPT(" ",99)),298,99)))+1,99)),0) + IFERROR(VLOOKUP(LEFT(TRIM(MID(SUBSTITUTE($R16,";",REPT(" ",99)),397,99)),FIND(":",TRIM(MID(SUBSTITUTE($R16,";",REPT(" ",99)),397,99)))-1),Materiales!$A$2:$E$502,5,FALSE)*VALUE(MID(TRIM(MID(SUBSTITUTE($R16,";",REPT(" ",99)),397,99)),FIND(":",TRIM(MID(SUBSTITUTE($R16,";",REPT(" ",99)),397,99)))+1,99)),0) + IFERROR(VLOOKUP(LEFT(TRIM(MID(SUBSTITUTE($R16,";",REPT(" ",99)),496,99)),FIND(":",TRIM(MID(SUBSTITUTE($R16,";",REPT(" ",99)),496,99)))-1),Materiales!$A$2:$E$502,5,FALSE)*VALUE(MID(TRIM(MID(SUBSTITUTE($R16,";",REPT(" ",99)),496,99)),FIND(":",TRIM(MID(SUBSTITUTE($R16,";",REPT(" ",99)),496,99)))+1,99)),0) + IFERROR(VLOOKUP(LEFT(TRIM(MID(SUBSTITUTE($R16,";",REPT(" ",99)),595,99)),FIND(":",TRIM(MID(SUBSTITUTE($R16,";",REPT(" ",99)),595,99)))-1),Materiales!$A$2:$E$502,5,FALSE)*VALUE(MID(TRIM(MID(SUBSTITUTE($R16,";",REPT(" ",99)),595,99)),FIND(":",TRIM(MID(SUBSTITUTE($R16,";",REPT(" ",99)),595,99)))+1,99)),0) + IFERROR(VLOOKUP(LEFT(TRIM(MID(SUBSTITUTE($R16,";",REPT(" ",99)),694,99)),FIND(":",TRIM(MID(SUBSTITUTE($R16,";",REPT(" ",99)),694,99)))-1),Materiales!$A$2:$E$502,5,FALSE)*VALUE(MID(TRIM(MID(SUBSTITUTE($R16,";",REPT(" ",99)),694,99)),FIND(":",TRIM(MID(SUBSTITUTE($R16,";",REPT(" ",99)),694,99)))+1,99)),0) + IFERROR(VLOOKUP(LEFT(TRIM(MID(SUBSTITUTE($R16,";",REPT(" ",99)),793,99)),FIND(":",TRIM(MID(SUBSTITUTE($R16,";",REPT(" ",99)),793,99)))-1),Materiales!$A$2:$E$502,5,FALSE)*VALUE(MID(TRIM(MID(SUBSTITUTE($R16,";",REPT(" ",99)),793,99)),FIND(":",TRIM(MID(SUBSTITUTE($R16,";",REPT(" ",99)),793,99)))+1,99)),0) + IFERROR(VLOOKUP(LEFT(TRIM(MID(SUBSTITUTE($R16,";",REPT(" ",99)),892,99)),FIND(":",TRIM(MID(SUBSTITUTE($R16,";",REPT(" ",99)),892,99)))-1),Materiales!$A$2:$E$502,5,FALSE)*VALUE(MID(TRIM(MID(SUBSTITUTE($R16,";",REPT(" ",99)),892,99)),FIND(":",TRIM(MID(SUBSTITUTE($R16,";",REPT(" ",99)),892,99)))+1,99)),0)))} -> 0 | U16: {=IF($A16="","",IF($T16="",0,IFERROR(VLOOKUP(LEFT(TRIM(MID(SUBSTITUTE($T16,";",REPT(" ",99)),1,99)),FIND(":",TRIM(MID(SUBSTITUTE($T16,";",REPT(" ",99)),1,99)))-1),Materiales!$A$2:$E$502,5,FALSE)*VALUE(MID(TRIM(MID(SUBSTITUTE($T16,";",REPT(" ",99)),1,99)),FIND(":",TRIM(MID(SUBSTITUTE($T16,";",REPT(" ",99)),1,99)))+1,99)),0) + IFERROR(VLOOKUP(LEFT(TRIM(MID(SUBSTITUTE($T16,";",REPT(" ",99)),100,99)),FIND(":",TRIM(MID(SUBSTITUTE($T16,";",REPT(" ",99)),100,99)))-1),Materiales!$A$2:$E$502,5,FALSE)*VALUE(MID(TRIM(MID(SUBSTITUTE($T16,";",REPT(" ",99)),100,99)),FIND(":",TRIM(MID(SUBSTITUTE($T16,";",REPT(" ",99)),100,99)))+1,99)),0) + IFERROR(VLOOKUP(LEFT(TRIM(MID(SUBSTITUTE($T16,";",REPT(" ",99)),199,99)),FIND(":",TRIM(MID(SUBSTITUTE($T16,";",REPT(" ",99)),199,99)))-1),Materiales!$A$2:$E$502,5,FALSE)*VALUE(MID(TRIM(MID(SUBSTITUTE($T16,";",REPT(" ",99)),199,99)),FIND(":",TRIM(MID(SUBSTITUTE($T16,";",REPT(" ",99)),199,99)))+1,99)),0) + IFERROR(VLOOKUP(LEFT(TRIM(MID(SUBSTITUTE($T16,";",REPT(" ",99)),298,99)),FIND(":",TRIM(MID(SUBSTITUTE($T16,";",REPT(" ",99)),298,99)))-1),Materiales!$A$2:$E$502,5,FALSE)*VALUE(MID(TRIM(MID(SUBSTITUTE($T16,";",REPT(" ",99)),298,99)),FIND(":",TRIM(MID(SUBSTITUTE($T16,";",REPT(" ",99)),298,99)))+1,99)),0) + IFERROR(VLOOKUP(LEFT(TRIM(MID(SUBSTITUTE($T16,";",REPT(" ",99)),397,99)),FIND(":",TRIM(MID(SUBSTITUTE($T16,";",REPT(" ",99)),397,99)))-1),Materiales!$A$2:$E$502,5,FALSE)*VALUE(MID(TRIM(MID(SUBSTITUTE($T16,";",REPT(" ",99)),397,99)),FIND(":",TRIM(MID(SUBSTITUTE($T16,";",REPT(" ",99)),397,99)))+1,99)),0) + IFERROR(VLOOKUP(LEFT(TRIM(MID(SUBSTITUTE($T16,";",REPT(" ",99)),496,99)),FIND(":",TRIM(MID(SUBSTITUTE($T16,";",REPT(" ",99)),496,99)))-1),Materiales!$A$2:$E$502,5,FALSE)*VALUE(MID(TRIM(MID(SUBSTITUTE($T16,";",REPT(" ",99)),496,99)),FIND(":",TRIM(MID(SUBSTITUTE($T16,";",REPT(" ",99)),496,99)))+1,99)),0) + IFERROR(VLOOKUP(LEFT(TRIM(MID(SUBSTITUTE($T16,";",REPT(" ",99)),595,99)),FIND(":",TRIM(MID(SUBSTITUTE($T16,";",REPT(" ",99)),595,99)))-1),Materiales!$A$2:$E$502,5,FALSE)*VALUE(MID(TRIM(MID(SUBSTITUTE($T16,";",REPT(" ",99)),595,99)),FIND(":",TRIM(MID(SUBSTITUTE($T16,";",REPT(" ",99)),595,99)))+1,99)),0) + IFERROR(VLOOKUP(LEFT(TRIM(MID(SUBSTITUTE($T16,";",REPT(" ",99)),694,99)),FIND(":",TRIM(MID(SUBSTITUTE($T16,";",REPT(" ",99)),694,99)))-1),Materiales!$A$2:$E$502,5,FALSE)*VALUE(MID(TRIM(MID(SUBSTITUTE($T16,";",REPT(" ",99)),694,99)),FIND(":",TRIM(MID(SUBSTITUTE($T16,";",REPT(" ",99)),694,99)))+1,99)),0) + IFERROR(VLOOKUP(LEFT(TRIM(MID(SUBSTITUTE($T16,";",REPT(" ",99)),793,99)),FIND(":",TRIM(MID(SUBSTITUTE($T16,";",REPT(" ",99)),793,99)))-1),Materiales!$A$2:$E$502,5,FALSE)*VALUE(MID(TRIM(MID(SUBSTITUTE($T16,";",REPT(" ",99)),793,99)),FIND(":",TRIM(MID(SUBSTITUTE($T16,";",REPT(" ",99)),793,99)))+1,99)),0) + IFERROR(VLOOKUP(LEFT(TRIM(MID(SUBSTITUTE($T16,";",REPT(" ",99)),892,99)),FIND(":",TRIM(MID(SUBSTITUTE($T16,";",REPT(" ",99)),892,99)))-1),Materiales!$A$2:$E$502,5,FALSE)*VALUE(MID(TRIM(MID(SUBSTITUTE($T16,";",REPT(" ",99)),892,99)),FIND(":",TRIM(MID(SUBSTITUTE($T16,";",REPT(" ",99)),892,99)))+1,99)),0)))} -> 0 | W16: {=IF($A16="","",IF($V16="",0,IFERROR(VLOOKUP(LEFT(TRIM(MID(SUBSTITUTE($V16,";",REPT(" ",99)),1,99)),FIND(":",TRIM(MID(SUBSTITUTE($V16,";",REPT(" ",99)),1,99)))-1),Materiales!$A$2:$E$502,5,FALSE)*VALUE(MID(TRIM(MID(SUBSTITUTE($V16,";",REPT(" ",99)),1,99)),FIND(":",TRIM(MID(SUBSTITUTE($V16,";",REPT(" ",99)),1,99)))+1,99)),0) + IFERROR(VLOOKUP(LEFT(TRIM(MID(SUBSTITUTE($V16,";",REPT(" ",99)),100,99)),FIND(":",TRIM(MID(SUBSTITUTE($V16,";",REPT(" ",99)),100,99)))-1),Materiales!$A$2:$E$502,5,FALSE)*VALUE(MID(TRIM(MID(SUBSTITUTE($V16,";",REPT(" ",99)),100,99)),FIND(":",TRIM(MID(SUBSTITUTE($V16,";",REPT(" ",99)),100,99)))+1,99)),0) + IFERROR(VLOOKUP(LEFT(TRIM(MID(SUBSTITUTE($V16,";",REPT(" ",99)),199,99)),FIND(":",TRIM(MID(SUBSTITUTE($V16,";",REPT(" ",99)),199,99)))-1),Materiales!$A$2:$E$502,5,FALSE)*VALUE(MID(TRIM(MID(SUBSTITUTE($V16,";",REPT(" ",99)),199,99)),FIND(":",TRIM(MID(SUBSTITUTE($V16,";",REPT(" ",99)),199,99)))+1,99)),0) + IFERROR(VLOOKUP(LEFT(TRIM(MID(SUBSTITUTE($V16,";",REPT(" ",99)),298,99)),FIND(":",TRIM(MID(SUBSTITUTE($V16,";",REPT(" ",99)),298,99)))-1),Materiales!$A$2:$E$502,5,FALSE)*VALUE(MID(TRIM(MID(SUBSTITUTE($V16,";",REPT(" ",99)),298,99)),FIND(":",TRIM(MID(SUBSTITUTE($V16,";",REPT(" ",99)),298,99)))+1,99)),0) + IFERROR(VLOOKUP(LEFT(TRIM(MID(SUBSTITUTE($V16,";",REPT(" ",99)),397,99)),FIND(":",TRIM(MID(SUBSTITUTE($V16,";",REPT(" ",99)),397,99)))-1),Materiales!$A$2:$E$502,5,FALSE)*VALUE(MID(TRIM(MID(SUBSTITUTE($V16,";",REPT(" ",99)),397,99)),FIND(":",TRIM(MID(SUBSTITUTE($V16,";",REPT(" ",99)),397,99)))+1,99)),0) + IFERROR(VLOOKUP(LEFT(TRIM(MID(SUBSTITUTE($V16,";",REPT(" ",99)),496,99)),FIND(":",TRIM(MID(SUBSTITUTE($V16,";",REPT(" ",99)),496,99)))-1),Materiales!$A$2:$E$502,5,FALSE)*VALUE(MID(TRIM(MID(SUBSTITUTE($V16,";",REPT(" ",99)),496,99)),FIND(":",TRIM(MID(SUBSTITUTE($V16,";",REPT(" ",99)),496,99)))+1,99)),0) + IFERROR(VLOOKUP(LEFT(TRIM(MID(SUBSTITUTE($V16,";",REPT(" ",99)),595,99)),FIND(":",TRIM(MID(SUBSTITUTE($V16,";",REPT(" ",99)),595,99)))-1),Materiales!$A$2:$E$502,5,FALSE)*VALUE(MID(TRIM(MID(SUBSTITUTE($V16,";",REPT(" ",99)),595,99)),FIND(":",TRIM(MID(SUBSTITUTE($V16,";",REPT(" ",99)),595,99)))+1,99)),0) + IFERROR(VLOOKUP(LEFT(TRIM(MID(SUBSTITUTE($V16,";",REPT(" ",99)),694,99)),FIND(":",TRIM(MID(SUBSTITUTE($V16,";",REPT(" ",99)),694,99)))-1),Materiales!$A$2:$E$502,5,FALSE)*VALUE(MID(TRIM(MID(SUBSTITUTE($V16,";",REPT(" ",99)),694,99)),FIND(":",TRIM(MID(SUBSTITUTE($V16,";",REPT(" ",99)),694,99)))+1,99)),0) + IFERROR(VLOOKUP(LEFT(TRIM(MID(SUBSTITUTE($V16,";",REPT(" ",99)),793,99)),FIND(":",TRIM(MID(SUBSTITUTE($V16,";",REPT(" ",99)),793,99)))-1),Materiales!$A$2:$E$502,5,FALSE)*VALUE(MID(TRIM(MID(SUBSTITUTE($V16,";",REPT(" ",99)),793,99)),FIND(":",TRIM(MID(SUBSTITUTE($V16,";",REPT(" ",99)),793,99)))+1,99)),0) + IFERROR(VLOOKUP(LEFT(TRIM(MID(SUBSTITUTE($V16,";",REPT(" ",99)),892,99)),FIND(":",TRIM(MID(SUBSTITUTE($V16,";",REPT(" ",99)),892,99)))-1),Materiales!$A$2:$E$502,5,FALSE)*VALUE(MID(TRIM(MID(SUBSTITUTE($V16,";",REPT(" ",99)),892,99)),FIND(":",TRIM(MID(SUBSTITUTE($V16,";",REPT(" ",99)),892,99)))+1,99)),0)))} -> 0 | X16: =IF($A16="","",SUM($G16,$H16,$K16,$N16,$Q16,$S16,$U16,$W16)) -> 2826.4837 | Y16: 3 | Z16: =X16*Y16 -> 8479.4512 | AA16: 0 | AB16: =AA16+Z16 -> 8479.4512 | AC16: 8000 | AD16: =AB16-X16 -> 5652.9675 | AE16: =AC16-X16 -> 5173.5163 | AF16: =AE16/AD16 -> 0.91518592
A17: Vela Leon | B17: CERA_MOLDE | C17: 1 | F17: 24 | G17: {=IF($A17="","",IFERROR($F17*(N($C17)*XLOOKUP($B17,Ceras!$A$2:$A$500,Ceras!$G$2:$G$500,0)+IF($D17="",0,N($E17)*XLOOKUP($D17,Ceras!$A$2:$A$500,Ceras!$G$2:$G$500,0))),"Revisar cera"))} -> 432 | H17: =F17*1.5 -> 36 | I17: PABILO2-4 | J17: 6 | K17: {=IF($A17="","",IFERROR($J17*XLOOKUP($I17,Pabilos!$A$2:$A$500,Pabilos!$H$2:$H$500,0),"Revisar pabilo"))} -> 90 | L17: ES_BEDOYA | M17: =F17/10 -> 2.4 | N17: {=IF($A17="","",IFERROR($M17*XLOOKUP($L17,Esencias!$A$2:$A$501,Esencias!$G$2:$G$501,0),"Revisar esencia"))} -> 338.02817 | O17: COLOR_CAFE | P17: 1 | Q17: {=IF($A17="","",IFERROR(IF($P17="",1,$P17)*XLOOKUP($O17,Colores!$A$2:$A$500,Colores!$H$2:$H$500,0),"Revisar color"))} -> 92.307692 | S17: {=IF($A17="","",IF($R17="",0,IFERROR(VLOOKUP(LEFT(TRIM(MID(SUBSTITUTE($R17,";",REPT(" ",99)),1,99)),FIND(":",TRIM(MID(SUBSTITUTE($R17,";",REPT(" ",99)),1,99)))-1),Materiales!$A$2:$E$502,5,FALSE)*VALUE(MID(TRIM(MID(SUBSTITUTE($R17,";",REPT(" ",99)),1,99)),FIND(":",TRIM(MID(SUBSTITUTE($R17,";",REPT(" ",99)),1,99)))+1,99)),0) + IFERROR(VLOOKUP(LEFT(TRIM(MID(SUBSTITUTE($R17,";",REPT(" ",99)),100,99)),FIND(":",TRIM(MID(SUBSTITUTE($R17,";",REPT(" ",99)),100,99)))-1),Materiales!$A$2:$E$502,5,FALSE)*VALUE(MID(TRIM(MID(SUBSTITUTE($R17,";",REPT(" ",99)),100,99)),FIND(":",TRIM(MID(SUBSTITUTE($R17,";",REPT(" ",99)),100,99)))+1,99)),0) + IFERROR(VLOOKUP(LEFT(TRIM(MID(SUBSTITUTE($R17,";",REPT(" ",99)),199,99)),FIND(":",TRIM(MID(SUBSTITUTE($R17,";",REPT(" ",99)),199,99)))-1),Materiales!$A$2:$E$502,5,FALSE)*VALUE(MID(TRIM(MID(SUBSTITUTE($R17,";",REPT(" ",99)),199,99)),FIND(":",TRIM(MID(SUBSTITUTE($R17,";",REPT(" ",99)),199,99)))+1,99)),0) + IFERROR(VLOOKUP(LEFT(TRIM(MID(SUBSTITUTE($R17,";",REPT(" ",99)),298,99)),FIND(":",TRIM(MID(SUBSTITUTE($R17,";",REPT(" ",99)),298,99)))-1),Materiales!$A$2:$E$502,5,FALSE)*VALUE(MID(TRIM(MID(SUBSTITUTE($R17,";",REPT(" ",99)),298,99)),FIND(":",TRIM(MID(SUBSTITUTE($R17,";",REPT(" ",99)),298,99)))+1,99)),0) + IFERROR(VLOOKUP(LEFT(TRIM(MID(SUBSTITUTE($R17,";",REPT(" ",99)),397,99)),FIND(":",TRIM(MID(SUBSTITUTE($R17,";",REPT(" ",99)),397,99)))-1),Materiales!$A$2:$E$502,5,FALSE)*VALUE(MID(TRIM(MID(SUBSTITUTE($R17,";",REPT(" ",99)),397,99)),FIND(":",TRIM(MID(SUBSTITUTE($R17,";",REPT(" ",99)),397,99)))+1,99)),0) + IFERROR(VLOOKUP(LEFT(TRIM(MID(SUBSTITUTE($R17,";",REPT(" ",99)),496,99)),FIND(":",TRIM(MID(SUBSTITUTE($R17,";",REPT(" ",99)),496,99)))-1),Materiales!$A$2:$E$502,5,FALSE)*VALUE(MID(TRIM(MID(SUBSTITUTE($R17,";",REPT(" ",99)),496,99)),FIND(":",TRIM(MID(SUBSTITUTE($R17,";",REPT(" ",99)),496,99)))+1,99)),0) + IFERROR(VLOOKUP(LEFT(TRIM(MID(SUBSTITUTE($R17,";",REPT(" ",99)),595,99)),FIND(":",TRIM(MID(SUBSTITUTE($R17,";",REPT(" ",99)),595,99)))-1),Materiales!$A$2:$E$502,5,FALSE)*VALUE(MID(TRIM(MID(SUBSTITUTE($R17,";",REPT(" ",99)),595,99)),FIND(":",TRIM(MID(SUBSTITUTE($R17,";",REPT(" ",99)),595,99)))+1,99)),0) + IFERROR(VLOOKUP(LEFT(TRIM(MID(SUBSTITUTE($R17,";",REPT(" ",99)),694,99)),FIND(":",TRIM(MID(SUBSTITUTE($R17,";",REPT(" ",99)),694,99)))-1),Materiales!$A$2:$E$502,5,FALSE)*VALUE(MID(TRIM(MID(SUBSTITUTE($R17,";",REPT(" ",99)),694,99)),FIND(":",TRIM(MID(SUBSTITUTE($R17,";",REPT(" ",99)),694,99)))+1,99)),0) + IFERROR(VLOOKUP(LEFT(TRIM(MID(SUBSTITUTE($R17,";",REPT(" ",99)),793,99)),FIND(":",TRIM(MID(SUBSTITUTE($R17,";",REPT(" ",99)),793,99)))-1),Materiales!$A$2:$E$502,5,FALSE)*VALUE(MID(TRIM(MID(SUBSTITUTE($R17,";",REPT(" ",99)),793,99)),FIND(":",TRIM(MID(SUBSTITUTE($R17,";",REPT(" ",99)),793,99)))+1,99)),0) + IFERROR(VLOOKUP(LEFT(TRIM(MID(SUBSTITUTE($R17,";",REPT(" ",99)),892,99)),FIND(":",TRIM(MID(SUBSTITUTE($R17,";",REPT(" ",99)),892,99)))-1),Materiales!$A$2:$E$502,5,FALSE)*VALUE(MID(TRIM(MID(SUBSTITUTE($R17,";",REPT(" ",99)),892,99)),FIND(":",TRIM(MID(SUBSTITUTE($R17,";",REPT(" ",99)),892,99)))+1,99)),0)))} -> 0 | U17: {=IF($A17="","",IF($T17="",0,IFERROR(VLOOKUP(LEFT(TRIM(MID(SUBSTITUTE($T17,";",REPT(" ",99)),1,99)),FIND(":",TRIM(MID(SUBSTITUTE($T17,";",REPT(" ",99)),1,99)))-1),Materiales!$A$2:$E$502,5,FALSE)*VALUE(MID(TRIM(MID(SUBSTITUTE($T17,";",REPT(" ",99)),1,99)),FIND(":",TRIM(MID(SUBSTITUTE($T17,";",REPT(" ",99)),1,99)))+1,99)),0) + IFERROR(VLOOKUP(LEFT(TRIM(MID(SUBSTITUTE($T17,";",REPT(" ",99)),100,99)),FIND(":",TRIM(MID(SUBSTITUTE($T17,";",REPT(" ",99)),100,99)))-1),Materiales!$A$2:$E$502,5,FALSE)*VALUE(MID(TRIM(MID(SUBSTITUTE($T17,";",REPT(" ",99)),100,99)),FIND(":",TRIM(MID(SUBSTITUTE($T17,";",REPT(" ",99)),100,99)))+1,99)),0) + IFERROR(VLOOKUP(LEFT(TRIM(MID(SUBSTITUTE($T17,";",REPT(" ",99)),199,99)),FIND(":",TRIM(MID(SUBSTITUTE($T17,";",REPT(" ",99)),199,99)))-1),Materiales!$A$2:$E$502,5,FALSE)*VALUE(MID(TRIM(MID(SUBSTITUTE($T17,";",REPT(" ",99)),199,99)),FIND(":",TRIM(MID(SUBSTITUTE($T17,";",REPT(" ",99)),199,99)))+1,99)),0) + IFERROR(VLOOKUP(LEFT(TRIM(MID(SUBSTITUTE($T17,";",REPT(" ",99)),298,99)),FIND(":",TRIM(MID(SUBSTITUTE($T17,";",REPT(" ",99)),298,99)))-1),Materiales!$A$2:$E$502,5,FALSE)*VALUE(MID(TRIM(MID(SUBSTITUTE($T17,";",REPT(" ",99)),298,99)),FIND(":",TRIM(MID(SUBSTITUTE($T17,";",REPT(" ",99)),298,99)))+1,99)),0) + IFERROR(VLOOKUP(LEFT(TRIM(MID(SUBSTITUTE($T17,";",REPT(" ",99)),397,99)),FIND(":",TRIM(MID(SUBSTITUTE($T17,";",REPT(" ",99)),397,99)))-1),Materiales!$A$2:$E$502,5,FALSE)*VALUE(MID(TRIM(MID(SUBSTITUTE($T17,";",REPT(" ",99)),397,99)),FIND(":",TRIM(MID(SUBSTITUTE($T17,";",REPT(" ",99)),397,99)))+1,99)),0) + IFERROR(VLOOKUP(LEFT(TRIM(MID(SUBSTITUTE($T17,";",REPT(" ",99)),496,99)),FIND(":",TRIM(MID(SUBSTITUTE($T17,";",REPT(" ",99)),496,99)))-1),Materiales!$A$2:$E$502,5,FALSE)*VALUE(MID(TRIM(MID(SUBSTITUTE($T17,";",REPT(" ",99)),496,99)),FIND(":",TRIM(MID(SUBSTITUTE($T17,";",REPT(" ",99)),496,99)))+1,99)),0) + IFERROR(VLOOKUP(LEFT(TRIM(MID(SUBSTITUTE($T17,";",REPT(" ",99)),595,99)),FIND(":",TRIM(MID(SUBSTITUTE($T17,";",REPT(" ",99)),595,99)))-1),Materiales!$A$2:$E$502,5,FALSE)*VALUE(MID(TRIM(MID(SUBSTITUTE($T17,";",REPT(" ",99)),595,99)),FIND(":",TRIM(MID(SUBSTITUTE($T17,";",REPT(" ",99)),595,99)))+1,99)),0) + IFERROR(VLOOKUP(LEFT(TRIM(MID(SUBSTITUTE($T17,";",REPT(" ",99)),694,99)),FIND(":",TRIM(MID(SUBSTITUTE($T17,";",REPT(" ",99)),694,99)))-1),Materiales!$A$2:$E$502,5,FALSE)*VALUE(MID(TRIM(MID(SUBSTITUTE($T17,";",REPT(" ",99)),694,99)),FIND(":",TRIM(MID(SUBSTITUTE($T17,";",REPT(" ",99)),694,99)))+1,99)),0) + IFERROR(VLOOKUP(LEFT(TRIM(MID(SUBSTITUTE($T17,";",REPT(" ",99)),793,99)),FIND(":",TRIM(MID(SUBSTITUTE($T17,";",REPT(" ",99)),793,99)))-1),Materiales!$A$2:$E$502,5,FALSE)*VALUE(MID(TRIM(MID(SUBSTITUTE($T17,";",REPT(" ",99)),793,99)),FIND(":",TRIM(MID(SUBSTITUTE($T17,";",REPT(" ",99)),793,99)))+1,99)),0) + IFERROR(VLOOKUP(LEFT(TRIM(MID(SUBSTITUTE($T17,";",REPT(" ",99)),892,99)),FIND(":",TRIM(MID(SUBSTITUTE($T17,";",REPT(" ",99)),892,99)))-1),Materiales!$A$2:$E$502,5,FALSE)*VALUE(MID(TRIM(MID(SUBSTITUTE($T17,";",REPT(" ",99)),892,99)),FIND(":",TRIM(MID(SUBSTITUTE($T17,";",REPT(" ",99)),892,99)))+1,99)),0)))} -> 0 | W17: {=IF($A17="","",IF($V17="",0,IFERROR(VLOOKUP(LEFT(TRIM(MID(SUBSTITUTE($V17,";",REPT(" ",99)),1,99)),FIND(":",TRIM(MID(SUBSTITUTE($V17,";",REPT(" ",99)),1,99)))-1),Materiales!$A$2:$E$502,5,FALSE)*VALUE(MID(TRIM(MID(SUBSTITUTE($V17,";",REPT(" ",99)),1,99)),FIND(":",TRIM(MID(SUBSTITUTE($V17,";",REPT(" ",99)),1,99)))+1,99)),0) + IFERROR(VLOOKUP(LEFT(TRIM(MID(SUBSTITUTE($V17,";",REPT(" ",99)),100,99)),FIND(":",TRIM(MID(SUBSTITUTE($V17,";",REPT(" ",99)),100,99)))-1),Materiales!$A$2:$E$502,5,FALSE)*VALUE(MID(TRIM(MID(SUBSTITUTE($V17,";",REPT(" ",99)),100,99)),FIND(":",TRIM(MID(SUBSTITUTE($V17,";",REPT(" ",99)),100,99)))+1,99)),0) + IFERROR(VLOOKUP(LEFT(TRIM(MID(SUBSTITUTE($V17,";",REPT(" ",99)),199,99)),FIND(":",TRIM(MID(SUBSTITUTE($V17,";",REPT(" ",99)),199,99)))-1),Materiales!$A$2:$E$502,5,FALSE)*VALUE(MID(TRIM(MID(SUBSTITUTE($V17,";",REPT(" ",99)),199,99)),FIND(":",TRIM(MID(SUBSTITUTE($V17,";",REPT(" ",99)),199,99)))+1,99)),0) + IFERROR(VLOOKUP(LEFT(TRIM(MID(SUBSTITUTE($V17,";",REPT(" ",99)),298,99)),FIND(":",TRIM(MID(SUBSTITUTE($V17,";",REPT(" ",99)),298,99)))-1),Materiales!$A$2:$E$502,5,FALSE)*VALUE(MID(TRIM(MID(SUBSTITUTE($V17,";",REPT(" ",99)),298,99)),FIND(":",TRIM(MID(SUBSTITUTE($V17,";",REPT(" ",99)),298,99)))+1,99)),0) + IFERROR(VLOOKUP(LEFT(TRIM(MID(SUBSTITUTE($V17,";",REPT(" ",99)),397,99)),FIND(":",TRIM(MID(SUBSTITUTE($V17,";",REPT(" ",99)),397,99)))-1),Materiales!$A$2:$E$502,5,FALSE)*VALUE(MID(TRIM(MID(SUBSTITUTE($V17,";",REPT(" ",99)),397,99)),FIND(":",TRIM(MID(SUBSTITUTE($V17,";",REPT(" ",99)),397,99)))+1,99)),0) + IFERROR(VLOOKUP(LEFT(TRIM(MID(SUBSTITUTE($V17,";",REPT(" ",99)),496,99)),FIND(":",TRIM(MID(SUBSTITUTE($V17,";",REPT(" ",99)),496,99)))-1),Materiales!$A$2:$E$502,5,FALSE)*VALUE(MID(TRIM(MID(SUBSTITUTE($V17,";",REPT(" ",99)),496,99)),FIND(":",TRIM(MID(SUBSTITUTE($V17,";",REPT(" ",99)),496,99)))+1,99)),0) + IFERROR(VLOOKUP(LEFT(TRIM(MID(SUBSTITUTE($V17,";",REPT(" ",99)),595,99)),FIND(":",TRIM(MID(SUBSTITUTE($V17,";",REPT(" ",99)),595,99)))-1),Materiales!$A$2:$E$502,5,FALSE)*VALUE(MID(TRIM(MID(SUBSTITUTE($V17,";",REPT(" ",99)),595,99)),FIND(":",TRIM(MID(SUBSTITUTE($V17,";",REPT(" ",99)),595,99)))+1,99)),0) + IFERROR(VLOOKUP(LEFT(TRIM(MID(SUBSTITUTE($V17,";",REPT(" ",99)),694,99)),FIND(":",TRIM(MID(SUBSTITUTE($V17,";",REPT(" ",99)),694,99)))-1),Materiales!$A$2:$E$502,5,FALSE)*VALUE(MID(TRIM(MID(SUBSTITUTE($V17,";",REPT(" ",99)),694,99)),FIND(":",TRIM(MID(SUBSTITUTE($V17,";",REPT(" ",99)),694,99)))+1,99)),0) + IFERROR(VLOOKUP(LEFT(TRIM(MID(SUBSTITUTE($V17,";",REPT(" ",99)),793,99)),FIND(":",TRIM(MID(SUBSTITUTE($V17,";",REPT(" ",99)),793,99)))-1),Materiales!$A$2:$E$502,5,FALSE)*VALUE(MID(TRIM(MID(SUBSTITUTE($V17,";",REPT(" ",99)),793,99)),FIND(":",TRIM(MID(SUBSTITUTE($V17,";",REPT(" ",99)),793,99)))+1,99)),0) + IFERROR(VLOOKUP(LEFT(TRIM(MID(SUBSTITUTE($V17,";",REPT(" ",99)),892,99)),FIND(":",TRIM(MID(SUBSTITUTE($V17,";",REPT(" ",99)),892,99)))-1),Materiales!$A$2:$E$502,5,FALSE)*VALUE(MID(TRIM(MID(SUBSTITUTE($V17,";",REPT(" ",99)),892,99)),FIND(":",TRIM(MID(SUBSTITUTE($V17,";",REPT(" ",99)),892,99)))+1,99)),0)))} -> 0 | X17: =IF($A17="","",SUM($G17,$H17,$K17,$N17,$Q17,$S17,$U17,$W17)) -> 988.33586 | Y17: 3 | Z17: =X17*Y17 -> 2965.0076 | AA17: 0 | AB17: =AA17+Z17 -> 2965.0076 | AC17: 3000 | AD17: =AB17-X17 -> 1976.6717 | AE17: =AC17-X17 -> 2011.6641 | AF17: =AE17/AD17 -> 1.0177027
A18: Vela Frutilla | B18: CERA_MOLDE | C18: 1 | F18: 12 | G18: {=IF($A18="","",IFERROR($F18*(N($C18)*XLOOKUP($B18,Ceras!$A$2:$A$500,Ceras!$G$2:$G$500,0)+IF($D18="",0,N($E18)*XLOOKUP($D18,Ceras!$A$2:$A$500,Ceras!$G$2:$G$500,0))),"Revisar cera"))} -> 216 | H18: =F18*1.5 -> 18 | I18: PABILO2-4 | J18: 3 | K18: {=IF($A18="","",IFERROR($J18*XLOOKUP($I18,Pabilos!$A$2:$A$500,Pabilos!$H$2:$H$500,0),"Revisar pabilo"))} -> 45 | L18: ES_BEDOYA | M18: =F18/10 -> 1.2 | N18: {=IF($A18="","",IFERROR($M18*XLOOKUP($L18,Esencias!$A$2:$A$501,Esencias!$G$2:$G$501,0),"Revisar esencia"))} -> 169.01408 | O18: COLOR_CAFE | P18: 0.5 | Q18: {=IF($A18="","",IFERROR(IF($P18="",1,$P18)*XLOOKUP($O18,Colores!$A$2:$A$500,Colores!$H$2:$H$500,0),"Revisar color"))} -> 46.153846 | S18: {=IF($A18="","",IF($R18="",0,IFERROR(VLOOKUP(LEFT(TRIM(MID(SUBSTITUTE($R18,";",REPT(" ",99)),1,99)),FIND(":",TRIM(MID(SUBSTITUTE($R18,";",REPT(" ",99)),1,99)))-1),Materiales!$A$2:$E$502,5,FALSE)*VALUE(MID(TRIM(MID(SUBSTITUTE($R18,";",REPT(" ",99)),1,99)),FIND(":",TRIM(MID(SUBSTITUTE($R18,";",REPT(" ",99)),1,99)))+1,99)),0) + IFERROR(VLOOKUP(LEFT(TRIM(MID(SUBSTITUTE($R18,";",REPT(" ",99)),100,99)),FIND(":",TRIM(MID(SUBSTITUTE($R18,";",REPT(" ",99)),100,99)))-1),Materiales!$A$2:$E$502,5,FALSE)*VALUE(MID(TRIM(MID(SUBSTITUTE($R18,";",REPT(" ",99)),100,99)),FIND(":",TRIM(MID(SUBSTITUTE($R18,";",REPT(" ",99)),100,99)))+1,99)),0) + IFERROR(VLOOKUP(LEFT(TRIM(MID(SUBSTITUTE($R18,";",REPT(" ",99)),199,99)),FIND(":",TRIM(MID(SUBSTITUTE($R18,";",REPT(" ",99)),199,99)))-1),Materiales!$A$2:$E$502,5,FALSE)*VALUE(MID(TRIM(MID(SUBSTITUTE($R18,";",REPT(" ",99)),199,99)),FIND(":",TRIM(MID(SUBSTITUTE($R18,";",REPT(" ",99)),199,99)))+1,99)),0) + IFERROR(VLOOKUP(LEFT(TRIM(MID(SUBSTITUTE($R18,";",REPT(" ",99)),298,99)),FIND(":",TRIM(MID(SUBSTITUTE($R18,";",REPT(" ",99)),298,99)))-1),Materiales!$A$2:$E$502,5,FALSE)*VALUE(MID(TRIM(MID(SUBSTITUTE($R18,";",REPT(" ",99)),298,99)),FIND(":",TRIM(MID(SUBSTITUTE($R18,";",REPT(" ",99)),298,99)))+1,99)),0) + IFERROR(VLOOKUP(LEFT(TRIM(MID(SUBSTITUTE($R18,";",REPT(" ",99)),397,99)),FIND(":",TRIM(MID(SUBSTITUTE($R18,";",REPT(" ",99)),397,99)))-1),Materiales!$A$2:$E$502,5,FALSE)*VALUE(MID(TRIM(MID(SUBSTITUTE($R18,";",REPT(" ",99)),397,99)),FIND(":",TRIM(MID(SUBSTITUTE($R18,";",REPT(" ",99)),397,99)))+1,99)),0) + IFERROR(VLOOKUP(LEFT(TRIM(MID(SUBSTITUTE($R18,";",REPT(" ",99)),496,99)),FIND(":",TRIM(MID(SUBSTITUTE($R18,";",REPT(" ",99)),496,99)))-1),Materiales!$A$2:$E$502,5,FALSE)*VALUE(MID(TRIM(MID(SUBSTITUTE($R18,";",REPT(" ",99)),496,99)),FIND(":",TRIM(MID(SUBSTITUTE($R18,";",REPT(" ",99)),496,99)))+1,99)),0) + IFERROR(VLOOKUP(LEFT(TRIM(MID(SUBSTITUTE($R18,";",REPT(" ",99)),595,99)),FIND(":",TRIM(MID(SUBSTITUTE($R18,";",REPT(" ",99)),595,99)))-1),Materiales!$A$2:$E$502,5,FALSE)*VALUE(MID(TRIM(MID(SUBSTITUTE($R18,";",REPT(" ",99)),595,99)),FIND(":",TRIM(MID(SUBSTITUTE($R18,";",REPT(" ",99)),595,99)))+1,99)),0) + IFERROR(VLOOKUP(LEFT(TRIM(MID(SUBSTITUTE($R18,";",REPT(" ",99)),694,99)),FIND(":",TRIM(MID(SUBSTITUTE($R18,";",REPT(" ",99)),694,99)))-1),Materiales!$A$2:$E$502,5,FALSE)*VALUE(MID(TRIM(MID(SUBSTITUTE($R18,";",REPT(" ",99)),694,99)),FIND(":",TRIM(MID(SUBSTITUTE($R18,";",REPT(" ",99)),694,99)))+1,99)),0) + IFERROR(VLOOKUP(LEFT(TRIM(MID(SUBSTITUTE($R18,";",REPT(" ",99)),793,99)),FIND(":",TRIM(MID(SUBSTITUTE($R18,";",REPT(" ",99)),793,99)))-1),Materiales!$A$2:$E$502,5,FALSE)*VALUE(MID(TRIM(MID(SUBSTITUTE($R18,";",REPT(" ",99)),793,99)),FIND(":",TRIM(MID(SUBSTITUTE($R18,";",REPT(" ",99)),793,99)))+1,99)),0) + IFERROR(VLOOKUP(LEFT(TRIM(MID(SUBSTITUTE($R18,";",REPT(" ",99)),892,99)),FIND(":",TRIM(MID(SUBSTITUTE($R18,";",REPT(" ",99)),892,99)))-1),Materiales!$A$2:$E$502,5,FALSE)*VALUE(MID(TRIM(MID(SUBSTITUTE($R18,";",REPT(" ",99)),892,99)),FIND(":",TRIM(MID(SUBSTITUTE($R18,";",REPT(" ",99)),892,99)))+1,99)),0)))} -> 0 | U18: {=IF($A18="","",IF($T18="",0,IFERROR(VLOOKUP(LEFT(TRIM(MID(SUBSTITUTE($T18,";",REPT(" ",99)),1,99)),FIND(":",TRIM(MID(SUBSTITUTE($T18,";",REPT(" ",99)),1,99)))-1),Materiales!$A$2:$E$502,5,FALSE)*VALUE(MID(TRIM(MID(SUBSTITUTE($T18,";",REPT(" ",99)),1,99)),FIND(":",TRIM(MID(SUBSTITUTE($T18,";",REPT(" ",99)),1,99)))+1,99)),0) + IFERROR(VLOOKUP(LEFT(TRIM(MID(SUBSTITUTE($T18,";",REPT(" ",99)),100,99)),FIND(":",TRIM(MID(SUBSTITUTE($T18,";",REPT(" ",99)),100,99)))-1),Materiales!$A$2:$E$502,5,FALSE)*VALUE(MID(TRIM(MID(SUBSTITUTE($T18,";",REPT(" ",99)),100,99)),FIND(":",TRIM(MID(SUBSTITUTE($T18,";",REPT(" ",99)),100,99)))+1,99)),0) + IFERROR(VLOOKUP(LEFT(TRIM(MID(SUBSTITUTE($T18,";",REPT(" ",99)),199,99)),FIND(":",TRIM(MID(SUBSTITUTE($T18,";",REPT(" ",99)),199,99)))-1),Materiales!$A$2:$E$502,5,FALSE)*VALUE(MID(TRIM(MID(SUBSTITUTE($T18,";",REPT(" ",99)),199,99)),FIND(":",TRIM(MID(SUBSTITUTE($T18,";",REPT(" ",99)),199,99)))+1,99)),0) + IFERROR(VLOOKUP(LEFT(TRIM(MID(SUBSTITUTE($T18,";",REPT(" ",99)),298,99)),FIND(":",TRIM(MID(SUBSTITUTE($T18,";",REPT(" ",99)),298,99)))-1),Materiales!$A$2:$E$502,5,FALSE)*VALUE(MID(TRIM(MID(SUBSTITUTE($T18,";",REPT(" ",99)),298,99)),FIND(":",TRIM(MID(SUBSTITUTE($T18,";",REPT(" ",99)),298,99)))+1,99)),0) + IFERROR(VLOOKUP(LEFT(TRIM(MID(SUBSTITUTE($T18,";",REPT(" ",99)),397,99)),FIND(":",TRIM(MID(SUBSTITUTE($T18,";",REPT(" ",99)),397,99)))-1),Materiales!$A$2:$E$502,5,FALSE)*VALUE(MID(TRIM(MID(SUBSTITUTE($T18,";",REPT(" ",99)),397,99)),FIND(":",TRIM(MID(SUBSTITUTE($T18,";",REPT(" ",99)),397,99)))+1,99)),0) + IFERROR(VLOOKUP(LEFT(TRIM(MID(SUBSTITUTE($T18,";",REPT(" ",99)),496,99)),FIND(":",TRIM(MID(SUBSTITUTE($T18,";",REPT(" ",99)),496,99)))-1),Materiales!$A$2:$E$502,5,FALSE)*VALUE(MID(TRIM(MID(SUBSTITUTE($T18,";",REPT(" ",99)),496,99)),FIND(":",TRIM(MID(SUBSTITUTE($T18,";",REPT(" ",99)),496,99)))+1,99)),0) + IFERROR(VLOOKUP(LEFT(TRIM(MID(SUBSTITUTE($T18,";",REPT(" ",99)),595,99)),FIND(":",TRIM(MID(SUBSTITUTE($T18,";",REPT(" ",99)),595,99)))-1),Materiales!$A$2:$E$502,5,FALSE)*VALUE(MID(TRIM(MID(SUBSTITUTE($T18,";",REPT(" ",99)),595,99)),FIND(":",TRIM(MID(SUBSTITUTE($T18,";",REPT(" ",99)),595,99)))+1,99)),0) + IFERROR(VLOOKUP(LEFT(TRIM(MID(SUBSTITUTE($T18,";",REPT(" ",99)),694,99)),FIND(":",TRIM(MID(SUBSTITUTE($T18,";",REPT(" ",99)),694,99)))-1),Materiales!$A$2:$E$502,5,FALSE)*VALUE(MID(TRIM(MID(SUBSTITUTE($T18,";",REPT(" ",99)),694,99)),FIND(":",TRIM(MID(SUBSTITUTE($T18,";",REPT(" ",99)),694,99)))+1,99)),0) + IFERROR(VLOOKUP(LEFT(TRIM(MID(SUBSTITUTE($T18,";",REPT(" ",99)),793,99)),FIND(":",TRIM(MID(SUBSTITUTE($T18,";",REPT(" ",99)),793,99)))-1),Materiales!$A$2:$E$502,5,FALSE)*VALUE(MID(TRIM(MID(SUBSTITUTE($T18,";",REPT(" ",99)),793,99)),FIND(":",TRIM(MID(SUBSTITUTE($T18,";",REPT(" ",99)),793,99)))+1,99)),0) + IFERROR(VLOOKUP(LEFT(TRIM(MID(SUBSTITUTE($T18,";",REPT(" ",99)),892,99)),FIND(":",TRIM(MID(SUBSTITUTE($T18,";",REPT(" ",99)),892,99)))-1),Materiales!$A$2:$E$502,5,FALSE)*VALUE(MID(TRIM(MID(SUBSTITUTE($T18,";",REPT(" ",99)),892,99)),FIND(":",TRIM(MID(SUBSTITUTE($T18,";",REPT(" ",99)),892,99)))+1,99)),0)))} -> 0 | V18: REC_YESO:1 | W18: {=IF($A18="","",IF($V18="",0,IFERROR(VLOOKUP(LEFT(TRIM(MID(SUBSTITUTE($V18,";",REPT(" ",99)),1,99)),FIND(":",TRIM(MID(SUBSTITUTE($V18,";",REPT(" ",99)),1,99)))-1),Materiales!$A$2:$E$502,5,FALSE)*VALUE(MID(TRIM(MID(SUBSTITUTE($V18,";",REPT(" ",99)),1,99)),FIND(":",TRIM(MID(SUBSTITUTE($V18,";",REPT(" ",99)),1,99)))+1,99)),0) + IFERROR(VLOOKUP(LEFT(TRIM(MID(SUBSTITUTE($V18,";",REPT(" ",99)),100,99)),FIND(":",TRIM(MID(SUBSTITUTE($V18,";",REPT(" ",99)),100,99)))-1),Materiales!$A$2:$E$502,5,FALSE)*VALUE(MID(TRIM(MID(SUBSTITUTE($V18,";",REPT(" ",99)),100,99)),FIND(":",TRIM(MID(SUBSTITUTE($V18,";",REPT(" ",99)),100,99)))+1,99)),0) + IFERROR(VLOOKUP(LEFT(TRIM(MID(SUBSTITUTE($V18,";",REPT(" ",99)),199,99)),FIND(":",TRIM(MID(SUBSTITUTE($V18,";",REPT(" ",99)),199,99)))-1),Materiales!$A$2:$E$502,5,FALSE)*VALUE(MID(TRIM(MID(SUBSTITUTE($V18,";",REPT(" ",99)),199,99)),FIND(":",TRIM(MID(SUBSTITUTE($V18,";",REPT(" ",99)),199,99)))+1,99)),0) + IFERROR(VLOOKUP(LEFT(TRIM(MID(SUBSTITUTE($V18,";",REPT(" ",99)),298,99)),FIND(":",TRIM(MID(SUBSTITUTE($V18,";",REPT(" ",99)),298,99)))-1),Materiales!$A$2:$E$502,5,FALSE)*VALUE(MID(TRIM(MID(SUBSTITUTE($V18,";",REPT(" ",99)),298,99)),FIND(":",TRIM(MID(SUBSTITUTE($V18,";",REPT(" ",99)),298,99)))+1,99)),0) + IFERROR(VLOOKUP(LEFT(TRIM(MID(SUBSTITUTE($V18,";",REPT(" ",99)),397,99)),FIND(":",TRIM(MID(SUBSTITUTE($V18,";",REPT(" ",99)),397,99)))-1),Materiales!$A$2:$E$502,5,FALSE)*VALUE(MID(TRIM(MID(SUBSTITUTE($V18,";",REPT(" ",99)),397,99)),FIND(":",TRIM(MID(SUBSTITUTE($V18,";",REPT(" ",99)),397,99)))+1,99)),0) + IFERROR(VLOOKUP(LEFT(TRIM(MID(SUBSTITUTE($V18,";",REPT(" ",99)),496,99)),FIND(":",TRIM(MID(SUBSTITUTE($V18,";",REPT(" ",99)),496,99)))-1),Materiales!$A$2:$E$502,5,FALSE)*VALUE(MID(TRIM(MID(SUBSTITUTE($V18,";",REPT(" ",99)),496,99)),FIND(":",TRIM(MID(SUBSTITUTE($V18,";",REPT(" ",99)),496,99)))+1,99)),0) + IFERROR(VLOOKUP(LEFT(TRIM(MID(SUBSTITUTE($V18,";",REPT(" ",99)),595,99)),FIND(":",TRIM(MID(SUBSTITUTE($V18,";",REPT(" ",99)),595,99)))-1),Materiales!$A$2:$E$502,5,FALSE)*VALUE(MID(TRIM(MID(SUBSTITUTE($V18,";",REPT(" ",99)),595,99)),FIND(":",TRIM(MID(SUBSTITUTE($V18,";",REPT(" ",99)),595,99)))+1,99)),0) + IFERROR(VLOOKUP(LEFT(TRIM(MID(SUBSTITUTE($V18,";",REPT(" ",99)),694,99)),FIND(":",TRIM(MID(SUBSTITUTE($V18,";",REPT(" ",99)),694,99)))-1),Materiales!$A$2:$E$502,5,FALSE)*VALUE(MID(TRIM(MID(SUBSTITUTE($V18,";",REPT(" ",99)),694,99)),FIND(":",TRIM(MID(SUBSTITUTE($V18,";",REPT(" ",99)),694,99)))+1,99)),0) + IFERROR(VLOOKUP(LEFT(TRIM(MID(SUBSTITUTE($V18,";",REPT(" ",99)),793,99)),FIND(":",TRIM(MID(SUBSTITUTE($V18,";",REPT(" ",99)),793,99)))-1),Materiales!$A$2:$E$502,5,FALSE)*VALUE(MID(TRIM(MID(SUBSTITUTE($V18,";",REPT(" ",99)),793,99)),FIND(":",TRIM(MID(SUBSTITUTE($V18,";",REPT(" ",99)),793,99)))+1,99)),0) + IFERROR(VLOOKUP(LEFT(TRIM(MID(SUBSTITUTE($V18,";",REPT(" ",99)),892,99)),FIND(":",TRIM(MID(SUBSTITUTE($V18,";",REPT(" ",99)),892,99)))-1),Materiales!$A$2:$E$502,5,FALSE)*VALUE(MID(TRIM(MID(SUBSTITUTE($V18,";",REPT(" ",99)),892,99)),FIND(":",TRIM(MID(SUBSTITUTE($V18,";",REPT(" ",99)),892,99)))+1,99)),0)))} -> 3000 | X18: =IF($A18="","",SUM($G18,$H18,$K18,$N18,$Q18,$S18,$U18,$W18)) -> 3494.1679 | Y18: 3 | Z18: =X18*Y18 -> 10482.504 | AA18: 0 | AB18: =AA18+Z18 -> 10482.504 | AC18: 6000 | AD18: =AB18-X18 -> 6988.3359 | AE18: =AC18-X18 -> 2505.8321 | AF18: =AE18/AD18 -> 0.3585735
A19: Vela Cebolla | B19: CERA_MOLDE | C19: 1 | F19: 110 | G19: {=IF($A19="","",IFERROR($F19*(N($C19)*XLOOKUP($B19,Ceras!$A$2:$A$500,Ceras!$G$2:$G$500,0)+IF($D19="",0,N($E19)*XLOOKUP($D19,Ceras!$A$2:$A$500,Ceras!$G$2:$G$500,0))),"Revisar cera"))} -> 1980 | H19: =F19*1.5 -> 165 | I19: PABILO6-8 | J19: 9 | K19: {=IF($A19="","",IFERROR($J19*XLOOKUP($I19,Pabilos!$A$2:$A$500,Pabilos!$H$2:$H$500,0),"Revisar pabilo"))} -> 180 | L19: ES_BEDOYA | M19: =F19/10 -> 11 | N19: {=IF($A19="","",IFERROR($M19*XLOOKUP($L19,Esencias!$A$2:$A$501,Esencias!$G$2:$G$501,0),"Revisar esencia"))} -> 1549.2958 | O19: COLOR_CAFE | P19: 1 | Q19: {=IF($A19="","",IFERROR(IF($P19="",1,$P19)*XLOOKUP($O19,Colores!$A$2:$A$500,Colores!$H$2:$H$500,0),"Revisar color"))} -> 92.307692 | S19: {=IF($A19="","",IF($R19="",0,IFERROR(VLOOKUP(LEFT(TRIM(MID(SUBSTITUTE($R19,";",REPT(" ",99)),1,99)),FIND(":",TRIM(MID(SUBSTITUTE($R19,";",REPT(" ",99)),1,99)))-1),Materiales!$A$2:$E$502,5,FALSE)*VALUE(MID(TRIM(MID(SUBSTITUTE($R19,";",REPT(" ",99)),1,99)),FIND(":",TRIM(MID(SUBSTITUTE($R19,";",REPT(" ",99)),1,99)))+1,99)),0) + IFERROR(VLOOKUP(LEFT(TRIM(MID(SUBSTITUTE($R19,";",REPT(" ",99)),100,99)),FIND(":",TRIM(MID(SUBSTITUTE($R19,";",REPT(" ",99)),100,99)))-1),Materiales!$A$2:$E$502,5,FALSE)*VALUE(MID(TRIM(MID(SUBSTITUTE($R19,";",REPT(" ",99)),100,99)),FIND(":",TRIM(MID(SUBSTITUTE($R19,";",REPT(" ",99)),100,99)))+1,99)),0) + IFERROR(VLOOKUP(LEFT(TRIM(MID(SUBSTITUTE($R19,";",REPT(" ",99)),199,99)),FIND(":",TRIM(MID(SUBSTITUTE($R19,";",REPT(" ",99)),199,99)))-1),Materiales!$A$2:$E$502,5,FALSE)*VALUE(MID(TRIM(MID(SUBSTITUTE($R19,";",REPT(" ",99)),199,99)),FIND(":",TRIM(MID(SUBSTITUTE($R19,";",REPT(" ",99)),199,99)))+1,99)),0) + IFERROR(VLOOKUP(LEFT(TRIM(MID(SUBSTITUTE($R19,";",REPT(" ",99)),298,99)),FIND(":",TRIM(MID(SUBSTITUTE($R19,";",REPT(" ",99)),298,99)))-1),Materiales!$A$2:$E$502,5,FALSE)*VALUE(MID(TRIM(MID(SUBSTITUTE($R19,";",REPT(" ",99)),298,99)),FIND(":",TRIM(MID(SUBSTITUTE($R19,";",REPT(" ",99)),298,99)))+1,99)),0) + IFERROR(VLOOKUP(LEFT(TRIM(MID(SUBSTITUTE($R19,";",REPT(" ",99)),397,99)),FIND(":",TRIM(MID(SUBSTITUTE($R19,";",REPT(" ",99)),397,99)))-1),Materiales!$A$2:$E$502,5,FALSE)*VALUE(MID(TRIM(MID(SUBSTITUTE($R19,";",REPT(" ",99)),397,99)),FIND(":",TRIM(MID(SUBSTITUTE($R19,";",REPT(" ",99)),397,99)))+1,99)),0) + IFERROR(VLOOKUP(LEFT(TRIM(MID(SUBSTITUTE($R19,";",REPT(" ",99)),496,99)),FIND(":",TRIM(MID(SUBSTITUTE($R19,";",REPT(" ",99)),496,99)))-1),Materiales!$A$2:$E$502,5,FALSE)*VALUE(MID(TRIM(MID(SUBSTITUTE($R19,";",REPT(" ",99)),496,99)),FIND(":",TRIM(MID(SUBSTITUTE($R19,";",REPT(" ",99)),496,99)))+1,99)),0) + IFERROR(VLOOKUP(LEFT(TRIM(MID(SUBSTITUTE($R19,";",REPT(" ",99)),595,99)),FIND(":",TRIM(MID(SUBSTITUTE($R19,";",REPT(" ",99)),595,99)))-1),Materiales!$A$2:$E$502,5,FALSE)*VALUE(MID(TRIM(MID(SUBSTITUTE($R19,";",REPT(" ",99)),595,99)),FIND(":",TRIM(MID(SUBSTITUTE($R19,";",REPT(" ",99)),595,99)))+1,99)),0) + IFERROR(VLOOKUP(LEFT(TRIM(MID(SUBSTITUTE($R19,";",REPT(" ",99)),694,99)),FIND(":",TRIM(MID(SUBSTITUTE($R19,";",REPT(" ",99)),694,99)))-1),Materiales!$A$2:$E$502,5,FALSE)*VALUE(MID(TRIM(MID(SUBSTITUTE($R19,";",REPT(" ",99)),694,99)),FIND(":",TRIM(MID(SUBSTITUTE($R19,";",REPT(" ",99)),694,99)))+1,99)),0) + IFERROR(VLOOKUP(LEFT(TRIM(MID(SUBSTITUTE($R19,";",REPT(" ",99)),793,99)),FIND(":",TRIM(MID(SUBSTITUTE($R19,";",REPT(" ",99)),793,99)))-1),Materiales!$A$2:$E$502,5,FALSE)*VALUE(MID(TRIM(MID(SUBSTITUTE($R19,";",REPT(" ",99)),793,99)),FIND(":",TRIM(MID(SUBSTITUTE($R19,";",REPT(" ",99)),793,99)))+1,99)),0) + IFERROR(VLOOKUP(LEFT(TRIM(MID(SUBSTITUTE($R19,";",REPT(" ",99)),892,99)),FIND(":",TRIM(MID(SUBSTITUTE($R19,";",REPT(" ",99)),892,99)))-1),Materiales!$A$2:$E$502,5,FALSE)*VALUE(MID(TRIM(MID(SUBSTITUTE($R19,";",REPT(" ",99)),892,99)),FIND(":",TRIM(MID(SUBSTITUTE($R19,";",REPT(" ",99)),892,99)))+1,99)),0)))} -> 0 | U19: {=IF($A19="","",IF($T19="",0,IFERROR(VLOOKUP(LEFT(TRIM(MID(SUBSTITUTE($T19,";",REPT(" ",99)),1,99)),FIND(":",TRIM(MID(SUBSTITUTE($T19,";",REPT(" ",99)),1,99)))-1),Materiales!$A$2:$E$502,5,FALSE)*VALUE(MID(TRIM(MID(SUBSTITUTE($T19,";",REPT(" ",99)),1,99)),FIND(":",TRIM(MID(SUBSTITUTE($T19,";",REPT(" ",99)),1,99)))+1,99)),0) + IFERROR(VLOOKUP(LEFT(TRIM(MID(SUBSTITUTE($T19,";",REPT(" ",99)),100,99)),FIND(":",TRIM(MID(SUBSTITUTE($T19,";",REPT(" ",99)),100,99)))-1),Materiales!$A$2:$E$502,5,FALSE)*VALUE(MID(TRIM(MID(SUBSTITUTE($T19,";",REPT(" ",99)),100,99)),FIND(":",TRIM(MID(SUBSTITUTE($T19,";",REPT(" ",99)),100,99)))+1,99)),0) + IFERROR(VLOOKUP(LEFT(TRIM(MID(SUBSTITUTE($T19,";",REPT(" ",99)),199,99)),FIND(":",TRIM(MID(SUBSTITUTE($T19,";",REPT(" ",99)),199,99)))-1),Materiales!$A$2:$E$502,5,FALSE)*VALUE(MID(TRIM(MID(SUBSTITUTE($T19,";",REPT(" ",99)),199,99)),FIND(":",TRIM(MID(SUBSTITUTE($T19,";",REPT(" ",99)),199,99)))+1,99)),0) + IFERROR(VLOOKUP(LEFT(TRIM(MID(SUBSTITUTE($T19,";",REPT(" ",99)),298,99)),FIND(":",TRIM(MID(SUBSTITUTE($T19,";",REPT(" ",99)),298,99)))-1),Materiales!$A$2:$E$502,5,FALSE)*VALUE(MID(TRIM(MID(SUBSTITUTE($T19,";",REPT(" ",99)),298,99)),FIND(":",TRIM(MID(SUBSTITUTE($T19,";",REPT(" ",99)),298,99)))+1,99)),0) + IFERROR(VLOOKUP(LEFT(TRIM(MID(SUBSTITUTE($T19,";",REPT(" ",99)),397,99)),FIND(":",TRIM(MID(SUBSTITUTE($T19,";",REPT(" ",99)),397,99)))-1),Materiales!$A$2:$E$502,5,FALSE)*VALUE(MID(TRIM(MID(SUBSTITUTE($T19,";",REPT(" ",99)),397,99)),FIND(":",TRIM(MID(SUBSTITUTE($T19,";",REPT(" ",99)),397,99)))+1,99)),0) + IFERROR(VLOOKUP(LEFT(TRIM(MID(SUBSTITUTE($T19,";",REPT(" ",99)),496,99)),FIND(":",TRIM(MID(SUBSTITUTE($T19,";",REPT(" ",99)),496,99)))-1),Materiales!$A$2:$E$502,5,FALSE)*VALUE(MID(TRIM(MID(SUBSTITUTE($T19,";",REPT(" ",99)),496,99)),FIND(":",TRIM(MID(SUBSTITUTE($T19,";",REPT(" ",99)),496,99)))+1,99)),0) + IFERROR(VLOOKUP(LEFT(TRIM(MID(SUBSTITUTE($T19,";",REPT(" ",99)),595,99)),FIND(":",TRIM(MID(SUBSTITUTE($T19,";",REPT(" ",99)),595,99)))-1),Materiales!$A$2:$E$502,5,FALSE)*VALUE(MID(TRIM(MID(SUBSTITUTE($T19,";",REPT(" ",99)),595,99)),FIND(":",TRIM(MID(SUBSTITUTE($T19,";",REPT(" ",99)),595,99)))+1,99)),0) + IFERROR(VLOOKUP(LEFT(TRIM(MID(SUBSTITUTE($T19,";",REPT(" ",99)),694,99)),FIND(":",TRIM(MID(SUBSTITUTE($T19,";",REPT(" ",99)),694,99)))-1),Materiales!$A$2:$E$502,5,FALSE)*VALUE(MID(TRIM(MID(SUBSTITUTE($T19,";",REPT(" ",99)),694,99)),FIND(":",TRIM(MID(SUBSTITUTE($T19,";",REPT(" ",99)),694,99)))+1,99)),0) + IFERROR(VLOOKUP(LEFT(TRIM(MID(SUBSTITUTE($T19,";",REPT(" ",99)),793,99)),FIND(":",TRIM(MID(SUBSTITUTE($T19,";",REPT(" ",99)),793,99)))-1),Materiales!$A$2:$E$502,5,FALSE)*VALUE(MID(TRIM(MID(SUBSTITUTE($T19,";",REPT(" ",99)),793,99)),FIND(":",TRIM(MID(SUBSTITUTE($T19,";",REPT(" ",99)),793,99)))+1,99)),0) + IFERROR(VLOOKUP(LEFT(TRIM(MID(SUBSTITUTE($T19,";",REPT(" ",99)),892,99)),FIND(":",TRIM(MID(SUBSTITUTE($T19,";",REPT(" ",99)),892,99)))-1),Materiales!$A$2:$E$502,5,FALSE)*VALUE(MID(TRIM(MID(SUBSTITUTE($T19,";",REPT(" ",99)),892,99)),FIND(":",TRIM(MID(SUBSTITUTE($T19,";",REPT(" ",99)),892,99)))+1,99)),0)))} -> 0 | W19: {=IF($A19="","",IF($V19="",0,IFERROR(VLOOKUP(LEFT(TRIM(MID(SUBSTITUTE($V19,";",REPT(" ",99)),1,99)),FIND(":",TRIM(MID(SUBSTITUTE($V19,";",REPT(" ",99)),1,99)))-1),Materiales!$A$2:$E$502,5,FALSE)*VALUE(MID(TRIM(MID(SUBSTITUTE($V19,";",REPT(" ",99)),1,99)),FIND(":",TRIM(MID(SUBSTITUTE($V19,";",REPT(" ",99)),1,99)))+1,99)),0) + IFERROR(VLOOKUP(LEFT(TRIM(MID(SUBSTITUTE($V19,";",REPT(" ",99)),100,99)),FIND(":",TRIM(MID(SUBSTITUTE($V19,";",REPT(" ",99)),100,99)))-1),Materiales!$A$2:$E$502,5,FALSE)*VALUE(MID(TRIM(MID(SUBSTITUTE($V19,";",REPT(" ",99)),100,99)),FIND(":",TRIM(MID(SUBSTITUTE($V19,";",REPT(" ",99)),100,99)))+1,99)),0) + IFERROR(VLOOKUP(LEFT(TRIM(MID(SUBSTITUTE($V19,";",REPT(" ",99)),199,99)),FIND(":",TRIM(MID(SUBSTITUTE($V19,";",REPT(" ",99)),199,99)))-1),Materiales!$A$2:$E$502,5,FALSE)*VALUE(MID(TRIM(MID(SUBSTITUTE($V19,";",REPT(" ",99)),199,99)),FIND(":",TRIM(MID(SUBSTITUTE($V19,";",REPT(" ",99)),199,99)))+1,99)),0) + IFERROR(VLOOKUP(LEFT(TRIM(MID(SUBSTITUTE($V19,";",REPT(" ",99)),298,99)),FIND(":",TRIM(MID(SUBSTITUTE($V19,";",REPT(" ",99)),298,99)))-1),Materiales!$A$2:$E$502,5,FALSE)*VALUE(MID(TRIM(MID(SUBSTITUTE($V19,";",REPT(" ",99)),298,99)),FIND(":",TRIM(MID(SUBSTITUTE($V19,";",REPT(" ",99)),298,99)))+1,99)),0) + IFERROR(VLOOKUP(LEFT(TRIM(MID(SUBSTITUTE($V19,";",REPT(" ",99)),397,99)),FIND(":",TRIM(MID(SUBSTITUTE($V19,";",REPT(" ",99)),397,99)))-1),Materiales!$A$2:$E$502,5,FALSE)*VALUE(MID(TRIM(MID(SUBSTITUTE($V19,";",REPT(" ",99)),397,99)),FIND(":",TRIM(MID(SUBSTITUTE($V19,";",REPT(" ",99)),397,99)))+1,99)),0) + IFERROR(VLOOKUP(LEFT(TRIM(MID(SUBSTITUTE($V19,";",REPT(" ",99)),496,99)),FIND(":",TRIM(MID(SUBSTITUTE($V19,";",REPT(" ",99)),496,99)))-1),Materiales!$A$2:$E$502,5,FALSE)*VALUE(MID(TRIM(MID(SUBSTITUTE($V19,";",REPT(" ",99)),496,99)),FIND(":",TRIM(MID(SUBSTITUTE($V19,";",REPT(" ",99)),496,99)))+1,99)),0) + IFERROR(VLOOKUP(LEFT(TRIM(MID(SUBSTITUTE($V19,";",REPT(" ",99)),595,99)),FIND(":",TRIM(MID(SUBSTITUTE($V19,";",REPT(" ",99)),595,99)))-1),Materiales!$A$2:$E$502,5,FALSE)*VALUE(MID(TRIM(MID(SUBSTITUTE($V19,";",REPT(" ",99)),595,99)),FIND(":",TRIM(MID(SUBSTITUTE($V19,";",REPT(" ",99)),595,99)))+1,99)),0) + IFERROR(VLOOKUP(LEFT(TRIM(MID(SUBSTITUTE($V19,";",REPT(" ",99)),694,99)),FIND(":",TRIM(MID(SUBSTITUTE($V19,";",REPT(" ",99)),694,99)))-1),Materiales!$A$2:$E$502,5,FALSE)*VALUE(MID(TRIM(MID(SUBSTITUTE($V19,";",REPT(" ",99)),694,99)),FIND(":",TRIM(MID(SUBSTITUTE($V19,";",REPT(" ",99)),694,99)))+1,99)),0) + IFERROR(VLOOKUP(LEFT(TRIM(MID(SUBSTITUTE($V19,";",REPT(" ",99)),793,99)),FIND(":",TRIM(MID(SUBSTITUTE($V19,";",REPT(" ",99)),793,99)))-1),Materiales!$A$2:$E$502,5,FALSE)*VALUE(MID(TRIM(MID(SUBSTITUTE($V19,";",REPT(" ",99)),793,99)),FIND(":",TRIM(MID(SUBSTITUTE($V19,";",REPT(" ",99)),793,99)))+1,99)),0) + IFERROR(VLOOKUP(LEFT(TRIM(MID(SUBSTITUTE($V19,";",REPT(" ",99)),892,99)),FIND(":",TRIM(MID(SUBSTITUTE($V19,";",REPT(" ",99)),892,99)))-1),Materiales!$A$2:$E$502,5,FALSE)*VALUE(MID(TRIM(MID(SUBSTITUTE($V19,";",REPT(" ",99)),892,99)),FIND(":",TRIM(MID(SUBSTITUTE($V19,";",REPT(" ",99)),892,99)))+1,99)),0)))} -> 0 | X19: =IF($A19="","",SUM($G19,$H19,$K19,$N19,$Q19,$S19,$U19,$W19)) -> 3966.6035 | Y19: 3 | Z19: =X19*Y19 -> 11899.81 | AA19: 0 | AB19: =AA19+Z19 -> 11899.81 | AC19: 12000 | AD19: =AB19-X19 -> 7933.2069 | AE19: =AC19-X19 -> 8033.3965 | AF19: =AE19/AD19 -> 1.0126291
